Workbook

Sheet commodity_summary
B1: Commodity Code | C1: Description | D1: Average RPC | E1: Average RSC
A2: 1 | B2: 3001 | C2: 111 - Crop Production | D2: 0.4828 | E2: 0.3371
A3: 2 | B3: 3002 | C3: 112 - Animal Production and Aquaculture | D3: 0.7721 | E3: 0.8002
A4: 3 | B4: 3003 | C4: 113 - Forestry and Logging | D4: 0.7772 | E4: 0.512
A5: 4 | B5: 3004 | C5: 114 - Fishing, Hunting and Trapping | D5: 0.3657 | E5: 0.7408
A6: 5 | B6: 3005 | C6: 115 - Support Activities for Agriculture and Forestry | D6: 0.982 | E6: 0.4846
A7: 6 | B7: 3006 | C7: 211 - Oil and Gas Extraction | D7: 0.1288 | E7: 0.6825
A8: 7 | B8: 3007 | C8: 212 - Mining (except Oil and Gas) | D8: 0.3134 | E8: 0.7955
A9: 8 | B9: 3008 | C9: 213 - Support Activities for Mining | D9: 0.198 | E9: 0.9976
A10: 9 | B10: 3009 | C10: 221 - Utilities | D10: 0.6417 | E10: 0.4689
A11: 10 | B11: 3010 | C11: 23 - Construction | D11: 0.9573 | E11: 1
A12: 11 | B12: 3011 | C12: 311 - Food Manufacturing | D12: 0.4278 | E12: 0.5936
A13: 12 | B13: 3012 | C13: 312 - Beverage and Tobacco Product Manufacturing | D13: 0.5673 | E13: 0.5225
... A88: 87 | B88: 3087 | C88: Fruit farming | D88: 0.5339 | E88: 0.2421

Sheet industry_detail
B1: Industry Code | C1: Description | D1: Total Output | E1: Wage and Salary Employment | F1: Employee Compensation | G1: Proprietor Employment | H1: Proprietor Income | I1: Other Property Income | J1: Taxes on Production and Imports Net of Subsidies
A2: 1 | B2: 1 | C2: 111 - Crop Production | D2: 1.9263875e+10 | E2: 70042.83 | F2: 4.3609373e+09 | G2: 39386.72 | H2: 2.9593404e+09 | I2: 5.8312208e+09 | J2: 2.6958594e+08
A3: 2 | B3: 2 | C3: 112 - Animal Production and Aquaculture | D3: 1.795651e+10 | E3: 28405.04 | F3: 9.2640051e+08 | G3: 13021.31 | H3: 7.4732466e+08 | I3: 3.0777779e+09 | J3: 77448874
A4: 3 | B4: 3 | C4: 113 - Forestry and Logging | D4: 8.0663856e+08 | E4: 3541.33 | F4: 3.955565e+08 | G4: 1827.32 | H4: 2.3682529e+08 | I4: 69348345 | J4: 21601407
A5: 4 | B5: 4 | C5: 114 - Fishing, Hunting and Trapping | D5: 3.1710805e+08 | E5: 545.58 | F5: 56623220 | G5: 4446.35 | H5: 1.0503178e+08 | I5: 89377942 | J5: 63411011
A6: 5 | B6: 5 | C6: 115 - Support Activities for Agriculture and Forestry | D6: 1.4764521e+10 | E6: 245075.66 | F6: 1.339349e+10 | G6: 16010.01 | H6: 7.6907345e+08 | I6: -2779702.5 | J6: 5.8760081e+08
A7: 6 | B7: 6 | C7: 211 - Oil and Gas Extraction | D7: 1.1974433e+10 | E7: 3109.11 | F7: 1.0418136e+09 | G7: 14667.41 | H7: 4.4207668e+08 | I7: 2.2692799e+09 | J7: 1.2953619e+09
A8: 7 | B8: 7 | C8: 212 - Mining (except Oil and Gas) | D8: 3.8725935e+09 | E8: 5353.68 | F8: 7.0688064e+08 | G8: 2049.11 | H8: 3.1323058e+08 | I8: 1.3166371e+09 | J8: 1.9881881e+08
A9: 8 | B9: 8 | C9: 213 - Support Activities for Mining | D9: 2.623339e+09 | E9: 6935.36 | F9: 9.5804271e+08 | G9: 2278.7 | H9: 46877348 | I9: 5.7899493e+08 | J9: 1.4860121e+08
A10: 9 | B10: 9 | C10: 221 - Utilities | D10: 9.3106158e+10 | E10: 67084.79 | F10: 1.483185e+10 | G10: 5880.5 | H10: 3.1726348e+09 | I10: 3.5360048e+10 | J10: 1.1040996e+10
A11: 10 | B11: 10 | C11: 23 - Construction | D11: 2.9417517e+11 | E11: 977750.63 | F11: 1.0478454e+11 | G11: 339251.1 | H11: 2.2005385e+10 | I11: 3.9603697e+10 | J11: 3.4029085e+09
A12: 11 | B12: 11 | C12: 311 - Food Manufacturing | D12: 1.1397705e+11 | E12: 184786.51 | F12: 1.4236526e+10 | G12: 12933.01 | H12: 9.3061289e+08 | I12: 8.0198927e+09 | J12: 1.6296063e+09
A13: 12 | B13: 12 | C13: 312 - Beverage and Tobacco Product Manufacturing | D13: 3.2007511e+10 | E13: 65507.21 | F13: 5.9928529e+09 | G13: 4041.9 | H13: 2.0207804e+08 | I13: 3.9831619e+09 | J13: 1.9762802e+09
... A88: 87 | B88: 87 | C88: Fruit farming | D88: 1.7230428e+10 | E88: 78514.04 | F88: 2.2131513e+09 | G88: 17791.61 | H88: 3.0745376e+09 | I88: 4.2515472e+09 | J88: 3.0992703e+08
J89: 2.4611213e+11

Sheet Detail IxI SAM
A1: PayingCode | B1: PayingDescription | C1: ReceivingCode | D1: ReceivingDescription | E1: TransferCode | F1: TransferDescription | G1: Value
A2: 1 | B2: 111 - Crop Production | C2: 1 | D2: 111 - Crop Production | E2: 15055 | F2: Industry Use | G2: 3.5000368e+08
A3: 1 | B3: 111 - Crop Production | C3: 2 | D3: 112 - Animal Production and Aquaculture | E3: 15055 | F3: Industry Use | G3: 20004131
A4: 1 | B4: 111 - Crop Production | C4: 3 | D4: 113 - Forestry and Logging | E4: 15055 | F4: Industry Use | G4: 26271.042
A5: 1 | B5: 111 - Crop Production | C5: 5 | D5: 115 - Support Activities for Agriculture and Forestry | E5: 15055 | F5: Industry Use | G5: 1.0714269e+09
A6: 1 | B6: 111 - Crop Production | C6: 6 | D6: 211 - Oil and Gas Extraction | E6: 15055 | F6: Industry Use | G6: 4173471.3
A7: 1 | B7: 111 - Crop Production | C7: 7 | D7: 212 - Mining (except Oil and Gas) | E7: 15055 | F7: Industry Use | G7: 9474926.3
A8: 1 | B8: 111 - Crop Production | C8: 8 | D8: 213 - Support Activities for Mining | E8: 15055 | F8: Industry Use | G8: 3959.0695
A9: 1 | B9: 111 - Crop Production | C9: 9 | D9: 221 - Utilities | E9: 15055 | F9: Industry Use | G9: 1.4283748e+08
A10: 1 | B10: 111 - Crop Production | C10: 10 | D10: 23 - Construction | E10: 15055 | F10: Industry Use | G10: 46657718
A11: 1 | B11: 111 - Crop Production | C11: 11 | D11: 311 - Food Manufacturing | E11: 15055 | F11: Industry Use | G11: 261125.35
A12: 1 | B12: 111 - Crop Production | C12: 12 | D12: 312 - Beverage and Tobacco Product Manufacturing | E12: 15055 | F12: Industry Use | G12: 427.63126
A13: 1 | B13: 111 - Crop Production | C13: 13 | D13: 313 - Textile Mills | E13: 15055 | F13: Industry Use | G13: 113709.52
... A10009: 28001 | B10009: Domestic Trade | C10009: 14002 | D10009: Inventory Additions/Deletions | E10009: 15051 | F10009: Commodity Trade | G10009: 1.0192615e+09

Sheet IxI pivot
A3: Sum of Value | B3: Column Labels
A4: Row Labels | B4: 1 | C4: 2 | D4: 3 | E4: 4 | F4: 5 | G4: 6 | H4: 7 | I4: 8 | J4: 9 | K4: 10 | L4: 11 | M4: 12 | N4: 13 | O4: 14 | P4: 15 | Q4: 16 | R4: 17 | S4: 18 | T4: 19 | U4: 20 | V4: 21 | W4: 22 | X4: 23 | Y4: 24 | Z4: 25 | AA4: 26 | AB4: 27 | AC4: 28 | AD4: 29 | AE4: 30 | AF4: 31 | AG4: 32 | AH4: 33 | AI4: 34 | AJ4: 35 | AK4: 36 | AL4: 37 | AM4: 38 | AN4: 39 | AO4: 40 | AP4: 41 | AQ4: 42 | AR4: 43 | AS4: 44 | AT4: 45 | AU4: 46 | AV4: 47 | AW4: 48 | AX4: 49 | AY4: 50 | AZ4: 51 | BA4: 52 | BB4: 53 | BC4: 54 | BD4: 55 | BE4: 56 | BF4: 57 | BG4: 58 | BH4: 59 | BI4: 60 | BJ4: 61 | BK4: 62 | BL4: 63 | BM4: 64 | BN4: 65 | BO4: 66 | BP4: 67 | BQ4: 68 | BR4: 69 | BS4: 70 | BT4: 71 | BU4: 72 | BV4: 73 | BW4: 74 | BX4: 75 | BY4: 76 | BZ4: 77 | CA4: 78 | CB4: 79 | CC4: 80 | CD4: 81 | CE4: 82 | CF4: 83 | CG4: 85 | CH4: 86 | CI4: 87 | CJ4: 5001 | CK4: 6001 | CL4: 7001 | CM4: 8001 | CN4: 10001 | CO4: 10002 | CP4: 10003 | CQ4: 10004 | CR4: 10005 | CS4: 10006 | CT4: 10007 | CU4: 10008 | CV4: 10009 | CW4: 11001 | CX4: 11002 | CY4: 11003 | CZ4: 12001 | DA4: 12002 | DB4: 12003 | DC4: 12004 | DD4: 13001 | DE4: 14001 | DF4: 14002 | DG4: 25001 | DH4: 28001 | DI4: Grand Total
A5: 1 | B5: 3.5000368e+08 | C5: 3.3876685e+08 | D5: 6476600.7 | E5: 177.57912 | F5: 119434.91 | H5: 388693.05 | I5: 89626.476 | J5: 5018.2717 | K5: 77333386 | L5: 3.1613548e+09 | M5: 88518566 | N5: 8898969.3 | O5: 307.24735 | P5: 8624970.8 | Q5: 147370.67 | R5: 67456209 | S5: 2572527 | T5: 169451.31 | U5: 740.96881 | V5: 2.8777525e+08 | W5: 9412174.4 | X5: 39748.938 | Y5: 4018.08 | Z5: 3238.0838 | AA5: 3920.8077 | AB5: 41106.795 | AC5: 4074.6214 | AD5: 16024.14 | AE5: 721216.84 | AF5: 14726032 | AG5: 2276261.9 | AH5: 12539322 | AI5: 1711.7622 | AJ5: 2715.3615 | AK5: 7745341.4 | AL5: 2875.9914 | AM5: 4764014.2 | AN5: 3176.8186 | AO5: 15981.199 | AP5: 543367.16 | AR5: 13294.19 | AT5: 4668.8731 | AV5: 29.10344 | AW5: 24807.807 | AX5: 140.96415 | AY5: 2429.0103 | AZ5: 3389.2414 | BA5: 4593.5178 | BB5: 3541.7297 | BC5: 13101.164 | BD5: 48360.45 | BE5: 14600.84 | BF5: 12127.848 | BG5: 31166.779 | BH5: 49524.649 | BI5: 2904.097 | BJ5: 3422.3683 | BK5: 540085.91 | BL5: 20402.651 | BN5: 27273529 | BO5: 341187.06 | BP5: 92326280 | BQ5: 4089.2611 | BR5: 1940220.3 | BS5: 39002.765 | BT5: 4749.1152 | BU5: 3462.7923 | BV5: 24264.339 | BW5: 31906.65 | BY5: 2756045.3 | BZ5: 430027.85 | CA5: 2869076.2 | CB5: 3836.6812 | CC5: 2983.8288 | CD5: 607244.8 | CF5: 40110.761 | CH5: 17115400 | CI5: 14958024 | CN5: 55011829 | CO5: 62071826 | CP5: 51558299 | CQ5: 60737985 | CR5: 1.5131388e+08 | CS5: 2.028119e+08 | CT5: 3.495471e+08 | CU5: 2.7335106e+08 | CV5: 5.8357399e+08 | CW5: 4969562.8 | CX5: 1635.6765 | CY5: 82.413125 | CZ5: 1.6760034e+08 | DA5: 8089421.3 | DB5: 2377363.6 | DE5: 252771.23 | DF5: 6587933.5 | DG5: 6.3422223e+09 | DH5: 6.3286632e+09 | DI5: 1.9263875e+10
A6: 2 | B6: 20004131 | C6: 2.2761685e+09 | D6: 280654.08 | E6: 194.50563 | F6: 832586.67 | H6: 1.1188251 | I6: 185.11211 | J6: 5588.7798 | K6: 17730.175 | L6: 9.551859e+09 | M6: 309073.33 | N6: 1713479 | O6: 5075172.9 | P6: 73504.49 | Q6: 1255.9354 | R6: 572851.41 | S6: 22768.848 | T6: 2438.5706 | U6: 825.20671 | V6: 37515.769 | W6: 81566.014 | X6: 2138.1401 | Y6: 410.55086 | Z6: 2558.1698 | AA6: 679.98761 | AB6: 655.11861 | AD6: 788.40956 | AE6: 6113.9405 | AF6: 1247973.5 | AG6: 88381.355 | AH6: 700.08895 | AI6: 1659.9098 | AJ6: 2569.8864 | AK6: 4660.1209 | AL6: 43.987443 | AM6: 3917.8432 | AN6: 62.280961 | AO6: 15684.617 | AP6: 102003.95 | AW6: 362728.33 | AY6: 157.13938 | AZ6: 3400.3708 | BA6: 2955.1556 | BB6: 297.38853 | BC6: 5601.4112 | BD6: 30357.854 | BE6: 9846.3995 | BF6: 13102.268 | BG6: 34620.456 | BH6: 21624.741 | BI6: 3234.2526 | BJ6: 3811.4442 | BK6: 146.6861 | BL6: 12274.585 | BN6: 1.7148299e+08 | BO6: 2023212.5 | BP6: 1070195.1 | BQ6: 4276.8112 | BR6: 6709281.6 | BS6: 36249.125 | BT6: 1325.687 | BU6: 3814.0673 | BV6: 13658.92 | BW6: 35411.105 | BY6: 36490752 | BZ6: 2358002.9 | CA6: 3.1742412e+08 | CB6: 1680.5171 | CC6: 3002.8924 | CD6: 178132.95 | CF6: 34057.747 | CH6: 23836904 | CI6: 53965282 | CN6: 72814811 | CO6: 73927106 | CP6: 59091510 | CQ6: 66499060 | CR6: 1.5981715e+08 | CS6: 1.9798674e+08 | CT6: 3.1023926e+08 | CU6: 2.4604752e+08 | CV6: 4.8388357e+08 | CW6: 131.95518 | CX6: 2140964.2 | CZ6: 99671832 | DA6: 2954875.4 | DB6: 38809810 | DF6: 57306791 | DG6: 45033692 | DH6: 3.5655686e+09 | DI6: 1.795651e+10
A7: 3 | B7: 26271.042 | C7: 25724.501 | D7: 18717017 | F7: 6178.0757 | H7: 421.35742 | I7: 6.8234766 | K7: 5849.4683 | L7: 78494312 | M7: 14372046 | N7: 680.95768 | P7: 25732145 | Q7: 439672.61 | R7: 2.0032159e+08 | S7: 7649702.5 | T7: 502738.93 | V7: 12986809 | W7: 28046349 | X7: 101741.61 | AE7: 1896971.7 | AF7: 12507925 | AG7: 163.18034 | AH7: 959.32346 | AK7: 591.30149 | AM7: 364.23302 | AP7: 41.405001 | AW7: 1.8684839 | BH7: 2.2649789 | BK7: 28.635415 | BN7: 4284158.4 | BO7: 16.253479 | BP7: 301460.37 | BR7: 345652.34 | BY7: 206.54916 | BZ7: 28.940259 | CA7: 208.20818 | CD7: 45.365127 | CH7: 435.11688 | CN7: 4072.2602 | CO7: 4560.4275 | CP7: 3774.9107 | CQ7: 4500.5543 | CR7: 11307.096 | CS7: 15129.226 | CT7: 25903.501 | CU7: 20151.828 | CV7: 43258.42 | CW7: 380.22431 | CZ7: 12202.281 | DA7: 614.93822 | DB7: 181.56374 | DF7: 5845719.3 | DG7: 81326849 | DH7: 3.1255143e+08 | DI7: 8.0663856e+08
A8: 4 | L8: 44900790 | V8: 69107.703 | AK8: 4618407.2 | AW8: 2999.5721 | BN8: 401153.58 | BR8: 584992.13 | BY8: 2253892.2 | BZ8: 3517546.3 | CA8: 63700216 | CD8: 1333627.6 | CF8: 1312.8851 | CN8: 7051647 | CO8: 5413076.1 | CP8: 3636610.1 | CQ8: 6670115.3 | CR8: 6224911.4 | CS8: 13966019 | CT8: 21297172 | CU8: 11960842 | CV8: 27860890 | CZ8: 3353589.7 | DA8: 463624.1 | DB8: 5535505.4 | DF8: 94697.441 | DG8: 79598687 | DH8: 2596621.2 | DI8: 3.1710805e+08
A9: 5 | B9: 1.0714269e+09 | C9: 4.1503957e+08 | D9: 32537106 | E9: 27856.389 | BN9: 97216934 | BO9: 3227933.2 | CH9: 1.8278219e+09 | CI9: 2.3946997e+09 | CN9: 1933651.5 | CO9: 2132879.7 | CP9: 1945303.5 | CQ9: 1986615.9 | CR9: 5350634 | CS9: 4735380.8 | CT9: 6753597.8 | CU9: 6411981.5 | CV9: 12130747 | CZ9: 1.268897e+09 | DG9: 36054973 | DH9: 7.5741902e+09 | DI9: 1.4764521e+10
A10: 6 | B10: 4173471.3 | C10: 3992392.6 | D10: 2679.2508 | E10: 3947.16 | F10: 2106.7942 | G10: 1.1734962e+08 | H10: 1086431.2 | I10: 454602.43 | J10: 4.9639964e+08 | K10: 95129386 | L10: 3677437.2 | M10: 880453.02 | N10: 64010.425 | O10: 32608.021 | P10: 153.20238 | Q10: 6737.2681 | R10: 1111648.7 | S10: 1217828.1 | T10: 675249.88 | U10: 6.3241975e+09 | V10: 26551719 | W10: 993644.59 | X10: 1279687.4 | Y10: 887570.29 | Z10: 1702004.1 | AA10: 1036274.6 | AB10: 2320499.2 | AC10: 1521050.5 | AD10: 867972.7 | AE10: 394673.17 | AF10: 1941835.3 | AG10: 8608050.2 | AH10: 878486.72 | AI10: 30152.575 | AJ10: 308016.02 | AK10: 624983.79 | AL10: 91788.658 | AM10: 207143.1 | AN10: 180610.51 | AO10: 277254.27 | AP10: 300796.33 | AQ10: 41965872 | AR10: 3907900.1 | AS10: 5099197.7 | AT10: 37430550 | AU10: 8081658.5 | AV10: 274518.45 | AW10: 824425.28 | AX10: 3132621.1 | AY10: 7902867.2 | AZ10: 250131.29 | BA10: 268527.03 | BB10: 96285.86 | BC10: 693525.19 | BD10: 1382398.6 | BE10: 828582.44 | BF10: 3093071.6 | BG10: 7259110.9 | BH10: 3059569.7 | BI10: 41443.823 | BJ10: 1333657.5 | BK10: 15023625 | BL10: 3361524.8 | BM10: 770187.84 | BN10: 7023835.7 | BO10: 1385774.9 | BP10: 9579894 | BQ10: 3170632.5 | BR10: 7916522 | BS10: 1712190.7 | BT10: 1917450.9 | BU10: 1280094.5 | BV10: 1585246.9 | BW10: 494327.32 | BX10: 87378.599 | BY10: 2009157.3 | BZ10: 1584805 | CA10: 8264881.8 | CB10: 2400186.4 | CC10: 1211546.7 | CD10: 2530051.2 | CF10: 4.0166575e+08 | CH10: 2946357.4 | CI10: 1792671.5 | CN10: 10406658 | CO10: 12921015 | CP10: 11759338 | CQ10: 13101844 | CR10: 33554073 | CS10: 42534635 | CT10: 68828495 | CU10: 47798846 | CV10: 91764559 | CW10: 973700.29 | CX10: 38760719 | CY10: 706.8717 | CZ10: 1.6800776e+08 | DA10: 54161177 | DB10: 12648041 | DC10: 8886.1661 | DE10: 2950874.4 | DF10: 8036498.2 | DG10: 3.5387288e+09 | DH10: 1.0938401e+08 | DI10: 1.1974433e+10
A11: 7 | B11: 9474926.3 | C11: 7329170.8 | D11: 14.339965 | E11: 51.079472 | F11: 5147.4062 | G11: 1650095.8 | H11: 73517378 | I11: 407615.43 | J11: 4.2419714e+08 | K11: 6.4168298e+08 | L11: 46566718 | M11: 7635269.1 | N11: 1524454.2 | O11: 542278.08 | P11: 5511.2412 | Q11: 13090.29 | R11: 575234.69 | S11: 12143291 | T11: 519176.67 | U11: 92341707 | V11: 1.6892475e+08 | W11: 8402869.8 | X11: 3.3882914e+08 | Y11: 1.5165705e+08 | Z11: 19911855 | AA11: 3640828.6 | AB11: 3881332.4 | AC11: 3288312.4 | AD11: 6066007.6 | AE11: 601637.04 | AF11: 6328362.7 | AG11: 1744137.9 | AH11: 21326.031 | AI11: 2534.9646 | AJ11: 3611.2322 | AK11: 11315.647 | AL11: 5744.4173 | AM11: 3044.1958 | AN11: 89210.798 | AO11: 23750.903 | AP11: 4149.7976 | AQ11: 224704.79 | AR11: 1718616.2 | AS11: 27881.044 | AT11: 460999.48 | AU11: 137584.05 | AV11: 985.22414 | AW11: 30205.093 | AX11: 17709.357 | AY11: 160340.23 | AZ11: 364096.77 | BA11: 1746912.4 | BB11: 6520385.5 | BC11: 4112023.5 | BD11: 2304796.4 | BE11: 55596390 | BF11: 18983.009 | BG11: 48209.966 | BH11: 20342.839 | BI11: 3163.0036 | BJ11: 7138.0407 | BK11: 2300278.5 | BL11: 98644.168 | BM11: 13698.753 | BN11: 68273966 | BO11: 1565871 | BP11: 38510155 | BQ11: 3449983.3 | BR11: 28049653 | BS11: 3544068 | BT11: 5161848.4 | BU11: 1502522.6 | BV11: 1343949.7 | BW11: 14228143 | BX11: 76538.767 | BY11: 30922493 | BZ11: 5423069.2 | CA11: 42203720 | CB11: 8646329.1 | CC11: 38043453 | CD11: 10145497 | CF11: 2.2620616e+08 | CH11: 7449937.5 | CI11: 3573634.5 | CN11: 1172916.5 | CO11: 2095126.3 | CP11: 1623258.6 | CQ11: 1918456.8 | CR11: 5134694.3 | CS11: 4886285.9 | CT11: 7586122.3 | CU11: 5448868.2 | CV11: 10902208 | CW11: 41934868 | CX11: 1553355.9 | CZ11: 98187380 | DA11: 11536933 | DB11: 37856241 | DE11: 45728851 | DF11: 763619.76 | DG11: 3.0248288e+08 | DH11: 6.4395417e+08 | DI11: 3.8725935e+09
A12: 8 | B12: 3959.0695 | C12: 13529.36 | D12: 1.675336 | E12: 12.517858 | F12: 3.171165 | G12: 13164549 | H12: 545444.29 | I12: 725832.3 | J12: 20392.903 | K12: 1333632 | L12: 140842.32 | M12: 100865.18 | N12: 1431.7779 | O12: 1770.5807 | P12: 368.91522 | Q12: 263.05178 | R12: 24880.823 | S12: 30373.594 | T12: 7272.4445 | U12: 29302.741 | V12: 78968.955 | W12: 48947.132 | X12: 19298.536 | Y12: 22232.738 | Z12: 364025.89 | AA12: 178233.3 | AB12: 475936.74 | AC12: 125128.52 | AD12: 317739.76 | AE12: 38292.422 | AF12: 75599.448 | AG12: 33080.843 | AH12: 2554.2504 | AI12: 441.60212 | AJ12: 372.68977 | AK12: 1527.4506 | AL12: 584.49818 | AM12: 580.45027 | AN12: 870.7237 | AO12: 4296.3859 | AP12: 834.73487 | AQ12: 28734.847 | AR12: 4597.1657 | AS12: 23567.723 | AT12: 44958.134 | AU12: 13703.428 | AV12: 26270.727 | AW12: 1344.6081 | AX12: 2529.7969 | AY12: 11172.152 | AZ12: 9199.0878 | BA12: 707.65986 | BB12: 40615.584 | BC12: 51165.779 | BD12: 20611.203 | BE12: 11843.998 | BF12: 2904.4227 | BG12: 6624.096 | BH12: 2716.4885 | BI12: 25.704051 | BJ12: 1112.2656 | BK12: 36702.722 | BL12: 23620.23 | BM12: 481.59859 | BN12: 226095.85 | BO12: 10420.668 | BP12: 34368.506 | BQ12: 41367.696 | BR12: 9582.5012 | BS12: 5883.4643 | BT12: 11133.869 | BU12: 1023.0809 | BV12: 28977.046 | BW12: 990.17243 | BX12: 71.288276 | BY12: 6224.644 | BZ12: 13829.528 | CA12: 46778.283 | CB12: 74239.461 | CC12: 3631.2883 | CD12: 12379.3 | CF12: 191278.24 | CH12: 3855.5697 | CI12: 2302.4113 | CN12: 12742.533 | CO12: 17100.902 | CP12: 14758.709 | CQ12: 16370.687 | CR12: 46653.842 | CS12: 56951.927 | CT12: 87470.318 | CU12: 66331.879 | CV12: 150903.15 | CW12: 4290.6708 | CX12: 170422.64 | CY12: 3539.2473 | CZ12: 192407.19 | DA12: 38073.062 | DB12: 21664.489 | DC12: 1757.1463 | DE12: 2.5938345e+09 | DF12: 37061.429 | DG12: 5830053 | DH12: 3711990.5 | DI12: 2.623339e+09
A13: 9 | B13: 1.4283748e+08 | C13: 1.0755043e+08 | D13: 23327.794 | E13: 13537.649 | F13: 92923.83 | G13: 1.0399539e+08 | H13: 40465758 | I13: 4084343.6 | J13: 4.4203523e+09 | K13: 5.5767854e+08 | L13: 3.9651955e+08 | M13: 79381037 | N13: 14151332 | O13: 6359190.8 | P13: 1027474.2 | Q13: 910010.85 | R13: 66275230 | S13: 1.0042095e+08 | T13: 52174993 | U13: 4.5453456e+08 | V13: 6.5114819e+08 | W13: 1.7636253e+08 | X13: 2.1976898e+08 | Y13: 1.0477778e+08 | Z13: 2.3444034e+08 | AA13: 79814024 | AB13: 9.287127e+08 | AC13: 71595599 | AD13: 2.4047652e+08 | AE13: 29963409 | AF13: 82007185 | AG13: 8.7304869e+08 | AH13: 1.2284053e+08 | AI13: 8875751.3 | AJ13: 32174351 | AK13: 3.213472e+08 | AL13: 62776905 | AM13: 90652003 | AN13: 83837751 | AO13: 82873666 | AP13: 2.3777379e+08 | AQ13: 14431954 | AR13: 2051014.5 | AS13: 15620286 | AT13: 2.6022516e+08 | AU13: 36245665 | AV13: 42612105 | AW13: 21525795 | AX13: 5597721.4 | AY13: 1.2901885e+08 | AZ13: 36666023 | BA13: 61966723 | BB13: 32353697 | BC13: 1.0061746e+08 | BD13: 1.9811272e+08 | BE13: 1.5473887e+08 | BF13: 20708752 | BG13: 84196153 | BH13: 1.1178399e+08 | BI13: 29463542 | BJ13: 1.5090145e+08 | BK13: 3.1182426e+09 | BL13: 99219174 | BM13: 34679836 | BN13: 4.795557e+08 | BO13: 2.129807e+08 | BP13: 1.6872126e+08 | BQ13: 1.0019787e+08 | BR13: 3.2324623e+08 | BS13: 3.6106567e+08 | BT13: 3.3386568e+08 | BU13: 1.9133307e+08 | BV13: 91717044 | BW13: 69914978 | BX13: 13666927 | BY13: 1.8243285e+08 | BZ13: 3.5453467e+08 | CA13: 1.4243752e+09 | CB13: 1.795332e+08 | CC13: 1.5469271e+08 | CD13: 1.0966294e+08 | CF13: 2.65235e+09 | CH13: 2.6341445e+08 | CI13: 2.5045239e+08 | CN13: 6.9080499e+08 | CO13: 8.9427861e+08 | CP13: 7.396153e+08 | CQ13: 7.7582238e+08 | CR13: 1.7233254e+09 | CS13: 2.0577241e+09 | CT13: 3.1371771e+09 | CU13: 2.2148899e+09 | CV13: 4.487042e+09 | CW13: 29960511 | CX13: 4.6652907e+08 | CZ13: 1.6784246e+09 | DA13: 4.7132635e+08 | DB13: 5.8407238e+08 | DG13: 3.1988444e+08 | DH13: 4.8872472e+10 | DI13: 9.3106158e+10
A14: 10 | B14: 46657718 | C14: 19524971 | E14: 12576.927 | F14: 53787.845 | G14: 9992563.1 | H14: 63769688 | I14: 29847410 | J14: 3.8170645e+08 | K14: 37463381 | L14: 1.9070259e+08 | M14: 38437345 | N14: 4052221.1 | O14: 2002102.3 | P14: 500502.69 | Q14: 436143.33 | R14: 30503274 | S14: 57639372 | T14: 24705458 | U14: 1.6085577e+09 | V14: 1.5754694e+08 | W14: 59262257 | X14: 1.0304464e+08 | Y14: 47865176 | Z14: 1.4188555e+08 | AA14: 61786815 | AB14: 4.7232363e+08 | AC14: 27171754 | AD14: 1.1412144e+08 | AE14: 12871511 | AF14: 60800315 | AG14: 4.2094259e+08 | AH14: 77857800 | AI14: 3533566.7 | AJ14: 17701652 | AK14: 75608919 | AL14: 21128489 | AM14: 62398819 | AN14: 42669369 | AO14: 33434819 | AP14: 1.3383148e+08 | AQ14: 27440115 | AR14: 1.3406578e+08 | AS14: 5980123.6 | AT14: 75785791 | AU14: 83831080 | AV14: 64869638 | AW14: 34440285 | AX14: 11440235 | AY14: 86453284 | AZ14: 10158491 | BA14: 30190294 | BB14: 9281085.1 | BC14: 2.1481673e+08 | BD14: 40970773 | BE14: 1.773365e+08 | BF14: 50310272 | BG14: 2.1325605e+08 | BH14: 3.5180599e+08 | BI14: 51797522 | BJ14: 9234151.8 | BK14: 1.8560529e+10 | BL14: 1.0670646e+08 | BN14: 2.8053611e+08 | BO14: 76502467 | BP14: 1.0417844e+08 | BQ14: 17238877 | BR14: 59788886 | BS14: 1.4991754e+08 | BT14: 1.0037653e+08 | BU14: 67427680 | BV14: 67729565 | BW14: 17156043 | BX14: 6547900.5 | BY14: 78765835 | BZ14: 5.5888071e+08 | CA14: 3.0711319e+08 | CB14: 95095474 | CC14: 77050477 | CD14: 3.073224e+08 | CF14: 1.3389139e+10 | CH14: 97896335 | CI14: 71954937 | CW14: 29149269 | CX14: 2.8062932e+09 | CY14: 3.4121717e+09 | CZ14: 8.5991377e+09 | DA14: 1.7794371e+09 | DB14: 2.0930176e+09 | DC14: 4.7332005e+10 | DE14: 1.871351e+11 | DG14: 13122292 | DH14: 61539.992 | DI14: 2.9417517e+11
A15: 11 | B15: 261125.35 | C15: 1.5603034e+09 | D15: 3.078126 | E15: 21033.827 | F15: 389916.21 | G15: 119725.92 | H15: 23998.258 | I15: 13024.694 | J15: 50556.012 | K15: 697161.86 | L15: 1.1766211e+10 | M15: 8.4238998e+08 | N15: 89305.701 | O15: 2026333.6 | P15: 30741.136 | Q15: 7640039.1 | R15: 2424727.8 | S15: 3226552.7 | T15: 21571574 | U15: 23485603 | V15: 3.0511913e+08 | W15: 22416838 | X15: 74467046 | Y15: 158164.64 | Z15: 297371.31 | AA15: 56761.082 | AB15: 571922.95 | AC15: 121209.56 | AD15: 486963.71 | AE15: 60319.889 | AF15: 741535.29 | AG15: 1.847361e+08 | AH15: 6572.5314 | AI15: 661.82997 | AJ15: 1202.2315 | AK15: 40193708 | AL15: 2570.7569 | AM15: 24968.246 | AN15: 7988.486 | AO15: 6225.3367 | AP15: 9451330.9 | AQ15: 10339915 | AR15: 61846.272 | AS15: 14689082 | AT15: 1117987.4 | AU15: 11549.662 | AV15: 303.90063 | AW15: 138633.72 | AX15: 3738.0179 | AY15: 18266.36 | AZ15: 1000014 | BA15: 3553453.8 | BB15: 2878.8835 | BC15: 19062.015 | BD15: 17824.509 | BE15: 33378995 | BF15: 6908.0105 | BG15: 18734.424 | BH15: 6837.7024 | BI15: 3970.5513 | BJ15: 2044.3619 | BK15: 639829.23 | BL15: 9439.9074 | BM15: 2062.6876 | BN15: 5.6238442e+08 | BO15: 3360964.6 | BP15: 383973.85 | BQ15: 110729.71 | BR15: 3.5086222e+08 | BS15: 1327300.6 | BT15: 2.9072484e+08 | BU15: 3.192618e+08 | BV15: 1.1578441e+09 | BW15: 34257767 | BX15: 918841.8 | BY15: 1.8447241e+08 | BZ15: 2.5340203e+08 | CA15: 5.3427589e+09 | CB15: 113599.02 | CC15: 540345.75 | CD15: 1.1304843e+08 | CF15: 617433.86 | CH15: 456834.59 | CI15: 319246.14 | CN15: 1.7431516e+09 | CO15: 1.6629454e+09 | CP15: 1.3266106e+09 | CQ15: 1.6019981e+09 | CR15: 3.7836708e+09 | CS15: 4.7554149e+09 | CT15: 7.3564301e+09 | CU15: 5.1625572e+09 | CV15: 1.0198615e+10 | CW15: 1731317.4 | CX15: 5.6434554e+08 | CY15: 24701.293 | CZ15: 2.0991004e+09 | DA15: 1.0798174e+09 | DB15: 2.289563e+09 | DC15: 16569.025 | DE15: 450088.17 | DF15: 3.791559e+08 | DG15: 4.8270723e+09 | DH15: 4.1592266e+10 | DI15: 1.1397705e+11
A16: 12 | B16: 427.63126 | C16: 37303338 | D16: 0.0010056252 | E16: 48.138239 | F16: 890.86992 | G16: 185.79834 | H16: 73.263958 | I16: 28.185254 | J16: 82.558412 | K16: 5567.1486 | L16: 1.7391258e+08 | M16: 7.8744555e+08 | N16: 256.88718 | O16: 4611.292 | P16: 13.894698 | Q16: 17406.084 | R16: 6718.2907 | S16: 51467.653 | T16: 59464.51 | U16: 52257.859 | V16: 703284 | W16: 54133.923 | X16: 172934.01 | Y16: 1097.3046 | Z16: 2541.8013 | AA16: 1991.6936 | AB16: 5318.2369 | AC16: 2766.8788 | AD16: 9239.6591 | AE16: 1846.7768 | AF16: 6855.8526 | AG16: 1738701 | AH16: 134.41735 | AI16: 23.096142 | AJ16: 34.801608 | AK16: 92928.779 | AL16: 232.19184 | AM16: 99.577592 | AN16: 321.29574 | AO16: 197.82463 | AP16: 21913.9 | AQ16: 24962216 | AR16: 156.53364 | AS16: 2046705 | AT16: 1086692.2 | AU16: 2762.2464 | AV16: 55.444381 | AW16: 51750.58 | AX16: 262.64467 | AY16: 366.59228 | AZ16: 2876.6763 | BA16: 8304.5233 | BB16: 14.336872 | BC16: 493.48821 | BD16: 243.78202 | BE16: 76759.816 | BF16: 377.94542 | BG16: 718.54537 | BH16: 432.56499 | BI16: 470.03548 | BJ16: 2.9695605 | BK16: 2808.407 | BL16: 331.17919 | BM16: 2569.4487 | BN16: 33418516 | BO16: 1662802.5 | BP16: 5827.3802 | BQ16: 640.918 | BR16: 44410282 | BS16: 6244.628 | BT16: 18851893 | BU16: 8764808.8 | BV16: 15014071 | BW16: 4334010.7 | BX16: 3556207.5 | BY16: 1.8241943e+08 | BZ16: 70927637 | CA16: 1.7332193e+09 | CB16: 618.92084 | CC16: 1388.2525 | CD16: 32247507 | CF16: 75486.495 | CH16: 2067.7036 | CI16: 1704.5255 | CN16: 6.0141295e+08 | CO16: 6.1702848e+08 | CP16: 5.2355485e+08 | CQ16: 5.4052395e+08 | CR16: 1.2737345e+09 | CS16: 1.5116312e+09 | CT16: 2.5930332e+09 | CU16: 1.854697e+09 | CV16: 3.2541527e+09 | CW16: 5206.9466 | CX16: 18151049 | CZ16: 4.4626585e+08 | DA16: 45412274 | DB16: 80965532 | DE16: 408.36103 | DF16: 2.0360364e+08 | DG16: 1.0234949e+09 | DH16: 1.4240998e+10 | DI16: 3.2007511e+10
A17: 13 | B17: 113709.52 | C17: 51915.483 | E17: 52.420503 | F17: 837.7968 | G17: 48280.857 | H17: 9633.6933 | I17: 5282.9214 | J17: 18299.806 | K17: 3237764.1 | L17: 169741.38 | M17: 26401.431 | N17: 55964913 | O17: 32952931 | P17: 85821438 | Q17: 603580.37 | R17: 2794553.4 | S17: 13937351 | T17: 2341861.5 | U17: 846512.39 | V17: 1815072.2 | W17: 5130477.9 | X17: 1366891.4 | Y17: 17858.594 | Z17: 141740.31 | AA17: 5684240.3 | AB17: 303752.52 | AC17: 52611.638 | AD17: 3670469.4 | AE17: 33887970 | AF17: 61809016 | AG17: 10174735 | AH17: 73597.044 | AI17: 391866.9 | AJ17: 679.91642 | AK17: 17385.561 | AL17: 4378.6305 | AM17: 1113.7717 | AN17: 4549001.4 | AO17: 3861033.2 | AP17: 339400.79 | AQ17: 264.49188 | AR17: 1713.9742 | AS17: 13893.835 | AT17: 11074.771 | AU17: 1212.2872 | AV17: 567.45915 | AW17: 3628.7398 | AX17: 2047.6535 | AY17: 5974.9848 | AZ17: 10502.851 | BA17: 6374390.7 | BB17: 4201.9633 | BC17: 15321.077 | BD17: 7086.03 | BE17: 40459.973 | BF17: 427.66919 | BG17: 1733.9523 | BH17: 624.8073 | BI17: 1365.4594 | BJ17: 2.370965 | BK17: 297680.11 | BL17: 361624.8 | BM17: 1835.7235 | BN17: 6306257.6 | BO17: 180414.88 | BP17: 255239.79 | BQ17: 73991.137 | BR17: 500421.19 | BS17: 856988.94 | BT17: 680999.51 | BU17: 255511.47 | BV17: 5159554.7 | BW17: 1947.273 | BX17: 2232.971 | BY17: 1463441 | BZ17: 210290.05 | CA17: 767160.1 | CB17: 1671350.4 | CC17: 530012.87 | CD17: 36574.383 | CF17: 83735.569 | CH17: 218275.77 | CI17: 157394.71 | CN17: 684207.23 | CO17: 968165.58 | CP17: 699827.07 | CQ17: 866457.13 | CR17: 2207640.1 | CS17: 2833121.6 | CT17: 5224471.9 | CU17: 3727129.4 | CV17: 14592938 | CW17: 183886.32 | CX17: 2584710.3 | CY17: 2353.0681 | CZ17: 1568405.3 | DA17: 144205.08 | DB17: 1543314.1 | DC17: 1657.7778 | DE17: 2017479.8 | DF17: 718786.98 | DG17: 1.6914437e+08 | DH17: 1.1013333e+09 | DI17: 1.6698542e+09
A18: 14 | B18: 518399.24 | C18: 151013.48 | D18: 0.039734832 | E18: 3936.1435 | F18: 9330.0193 | G18: 19788.921 | H18: 29404.243 | I18: 13812.983 | J18: 15658.506 | K18: 38395545 | L18: 6341085.8 | M18: 1365980.4 | N18: 175996.84 | O18: 3371106.4 | P18: 2383937.1 | Q18: 12522.48 | R18: 1724741.5 | S18: 220092.35 | T18: 516005.57 | U18: 174549.74 | V18: 1490033.5 | W18: 3061536.6 | X18: 1043172.2 | Y18: 45620.072 | Z18: 498256.97 | AA18: 804199.29 | AB18: 2777360.1 | AC18: 390181.9 | AD18: 57306670 | AE18: 3048982.7 | AF18: 1415818.7 | AG18: 38717712 | AH18: 533580.81 | AI18: 41193.446 | AJ18: 64248.448 | AK18: 1498907.2 | AL18: 360179.92 | AM18: 115878.39 | AN18: 4939289.3 | AO18: 281112.57 | AP18: 26333286 | AQ18: 46700.873 | AR18: 4125.0994 | AS18: 1093973 | AT18: 825304.62 | AU18: 94263.857 | AV18: 41856.685 | AW18: 278566.48 | AX18: 204741.75 | AY18: 182655.24 | AZ18: 249624.82 | BA18: 217659.45 | BB18: 596946.79 | BC18: 464163.54 | BD18: 259154.6 | BE18: 2394330.1 | BF18: 69318.309 | BG18: 294228.52 | BH18: 69466.491 | BI18: 405846.13 | BJ18: 514.83467 | BK18: 3547079 | BL18: 2191919 | BM18: 393747.44 | BN18: 8024947.3 | BO18: 280385.54 | BP18: 2703005.5 | BQ18: 2358438.6 | BR18: 623362.06 | BS18: 1817170.9 | BT18: 3689789.1 | BU18: 18660515 | BV18: 29941490 | BW18: 110224.24 | BX18: 94238.669 | BY18: 5968217.4 | BZ18: 16413887 | CA18: 5196593.2 | CB18: 1637565.6 | CC18: 7115264.2 | CD18: 2352267.6 | CF18: 1816829 | CH18: 2408279.4 | CI18: 2051757.9 | CN18: 5688941.6 | CO18: 7629128.2 | CP18: 9100283.3 | CQ18: 7475904.4 | CR18: 17619212 | CS18: 26740451 | CT18: 51549922 | CU18: 47000650 | CV18: 1.2822067e+08 | CW18: 1546491.9 | CX18: 36024602 | CY18: 302476.57 | CZ18: 17959239 | DA18: 2635604.9 | DB18: 32914158 | DC18: 192175.43 | DE18: 1.2652693e+08 | DF18: 1491015.4 | DG18: 1.2854149e+08 | DH18: 9.708709e+08 | DI18: 1.9474308e+09
A19: 15 | B19: 6789.9335 | C19: 2791.0912 | E19: 36.860195 | F19: 84.802176 | G19: 158.59181 | H19: 739.31041 | I19: 363.25112 | J19: 1218.2462 | K19: 503349.1 | L19: 119692.19 | M19: 31032.877 | N19: 1621519.8 | O19: 1337774.6 | P19: 17197801 | Q19: 16418.362 | R19: 88096.31 | S19: 357555.43 | T19: 20472649 | U19: 3457.4425 | V19: 53208.776 | W19: 175267.31 | X19: 44806.829 | Y19: 716.44813 | Z19: 9796.6497 | AA19: 163051.98 | AB19: 73902.504 | AC19: 9552.478 | AD19: 597185.45 | AE19: 894832.95 | AF19: 1598156.2 | AG19: 8446310.9 | AH19: 23754.807 | AI19: 15303.308 | AJ19: 3998.7744 | AK19: 41514.487 | AL19: 16264.967 | AM19: 8605.9993 | AN19: 670916.57 | AO19: 130184.96 | AP19: 3189405 | AQ19: 1442.9171 | AR19: 232.44901 | AS19: 9512.6598 | AT19: 19333.404 | AU19: 10222.054 | AV19: 661.53747 | AW19: 5592.7602 | AX19: 3754.703 | AY19: 2714.2065 | AZ19: 51248.89 | BA19: 287593.55 | BB19: 189784.59 | BC19: 6459821 | BD19: 23543.623 | BE19: 535035.02 | BF19: 15123.202 | BG19: 63390.047 | BH19: 14907.523 | BI19: 86580.923 | BK19: 40946.201 | BL19: 2866939.9 | BM19: 48274.927 | BN19: 1364585.7 | BO19: 72070.936 | BP19: 1507069.6 | BQ19: 286571.48 | BR19: 918962.08 | BS19: 537243.38 | BT19: 219086.67 | BU19: 175475.95 | BV19: 22407643 | BW19: 1828753.6 | BX19: 21667.194 | BY19: 367393.21 | BZ19: 265578.2 | CA19: 2637144.1 | CB19: 2655349.6 | CC19: 374004.77 | CD19: 7293713.4 | CF19: 768857.55 | CH19: 22220.17 | CI19: 18684.46 | CN19: 53004501 | CO19: 43842304 | CP19: 35154994 | CQ19: 51633310 | CR19: 1.296525e+08 | CS19: 1.8590506e+08 | CT19: 2.9302806e+08 | CU19: 2.3134265e+08 | CV19: 5.5742904e+08 | CW19: 64950.808 | CX19: 610016.83 | CY19: 1632.0007 | CZ19: 10401556 | DA19: 2530964.7 | DB19: 4057490.3 | DC19: 1056.6585 | DE19: 1005573.4 | DF19: 6892464.9 | DG19: 6.2099778e+08 | DH19: 3.6752757e+09 | DI19: 6.0152386e+09
A20: 16 | B20: 29273.471 | C20: 259382.25 | D20: 0.022288741 | E20: 15.709301 | F20: 260.57832 | G20: 19034.923 | H20: 5155.9401 | I20: 3903.2442 | J20: 5705.465 | K20: 2385981.2 | L20: 1891302.1 | M20: 277000.72 | N20: 13745.442 | O20: 103877.28 | P20: 332316.03 | Q20: 506162.5 | R20: 23235.808 | S20: 17710.677 | T20: 135519.23 | U20: 235545.83 | V20: 527976.71 | W20: 188980.95 | X20: 391589.97 | Y20: 19194.303 | Z20: 51525.656 | AA20: 26781.924 | AB20: 115280.67 | AC20: 43336.97 | AD20: 848679.95 | AE20: 20128.95 | AF20: 187454.05 | AG20: 264035.92 | AH20: 19972.474 | AI20: 766.05805 | AJ20: 1698.7981 | AK20: 13438.266 | AL20: 4066.1582 | AM20: 4615.4024 | AN20: 82232.381 | AO20: 5555.5304 | AP20: 65274.89 | AQ20: 1658.6842 | AR20: 675.58133 | AS20: 4693.3937 | AT20: 6795.8569 | AU20: 1025.3576 | AV20: 89.785706 | AW20: 990.08744 | AX20: 429.57118 | AY20: 2413.0646 | AZ20: 5381.2261 | BA20: 5843.2514 | BB20: 13803.273 | BC20: 46289.536 | BD20: 34463.22 | BE20: 51195.479 | BF20: 2217.933 | BG20: 7704.5523 | BH20: 2145.6667 | BI20: 6749.9628 | BJ20: 186.45004 | BK20: 86701.828 | BL20: 24573.406 | BM20: 5701.5475 | BN20: 325271.53 | BO20: 8888.6281 | BP20: 95117.868 | BQ20: 22657.511 | BR20: 65449.644 | BS20: 202840.47 | BT20: 278489.69 | BU20: 98871.016 | BV20: 282430.82 | BW20: 12699.608 | BX20: 2040.656 | BY20: 56950.219 | BZ20: 81676.043 | CA20: 901798.34 | CB20: 396746.31 | CC20: 41247.166 | CD20: 71220.569 | CF20: 232504.69 | CH20: 52185.414 | CI20: 37309.191 | CN20: 2122132.4 | CO20: 2610393.8 | CP20: 2412535.7 | CQ20: 3752167.6 | CR20: 7900913.9 | CS20: 12073580 | CT20: 18413521 | CU20: 12633831 | CV20: 26450636 | CW20: 27192.771 | CX20: 642819.14 | CY20: 8893.272 | CZ20: 610763.33 | DA20: 209568.52 | DB20: 683936.26 | DC20: 6900.5567 | DE20: 567777.71 | DF20: 195540.97 | DG20: 1.7454974e+08 | DH20: 4.8817959e+08 | DI20: 7.6675827e+08
A21: 17 | B21: 3823068.6 | C21: 965615.67 | D21: 1.803211 | E21: 15424.822 | F21: 42.885349 | G21: 73818.361 | H21: 2624112.2 | I21: 1184253.7 | J21: 70078.969 | K21: 3.5479267e+09 | L21: 3793730.2 | M21: 13092439 | N21: 8006.921 | O21: 1249194.8 | P21: 2315.7687 | Q21: 3247.0935 | R21: 1.2578026e+09 | S21: 31116006 | T21: 264933.14 | U21: 244448.19 | V21: 8931413.6 | W21: 41894755 | X21: 17503511 | Y21: 14963116 | Z21: 4740988.6 | AA21: 13991254 | AB21: 1.6566648e+08 | AC21: 16923370 | AD21: 63843274 | AE21: 3.4282102e+08 | AF21: 92828514 | AG21: 2.6110738e+08 | AH21: 7930644 | AI21: 900725.09 | AJ21: 1653370.2 | AK21: 45482610 | AL21: 11473610 | AM21: 2374587.4 | AN21: 12645525 | AO21: 7726388.6 | AP21: 8246904.2 | AQ21: 248008.34 | AR21: 53712766 | AS21: 59153.699 | AT21: 18971381 | AU21: 28500.633 | AV21: 177644.17 | AW21: 638150.25 | AX21: 594373.13 | AY21: 9271080.9 | AZ21: 1395328.4 | BA21: 7858221.1 | BB21: 13477901 | BC21: 33036249 | BD21: 85491751 | BE21: 23328753 | BF21: 1483508.4 | BG21: 768117.29 | BH21: 2078568.7 | BI21: 24474.847 | BJ21: 3423.7099 | BK21: 6.7053492e+08 | BL21: 38074136 | BM21: 103352.29 | BN21: 94327517 | BO21: 274009.67 | BP21: 59585696 | BQ21: 1130222.8 | BR21: 1668532.1 | BS21: 26493337 | BT21: 14593722 | BU21: 213549.73 | BV21: 48671420 | BW21: 551120.18 | BX21: 460.72052 | BY21: 10022695 | BZ21: 18001095 | CA21: 54986750 | CB21: 9938453.5 | CC21: 1267454.3 | CD21: 19356459 | CF21: 39926399 | CH21: 1.0393496e+08 | CI21: 73901984 | CN21: 8155873.3 | CO21: 11953324 | CP21: 10672397 | CQ21: 10657895 | CR21: 25947620 | CS21: 30718494 | CT21: 48983583 | CU21: 38916823 | CV21: 81632285 | CW21: 2285037.3 | CX21: 4617532.3 | CY21: 341501.1 | CZ21: 1.1920723e+08 | DA21: 1.7563311e+08 | DB21: 6551053.4 | DC21: 66291.48 | DE21: 1.029615e+09 | DF21: 45238174 | DG21: 3.3594999e+08 | DH21: 1.3874779e+09 | DI21: 1.0922736e+10
A22: 18 | B22: 2676502.4 | C22: 308912.72 | D22: 7.8975185 | E22: 159.9333 | F22: 247.91943 | G22: 925046.44 | H22: 1470095.9 | I22: 364413.13 | J22: 393779.75 | K22: 1.7222727e+08 | L22: 1.0487808e+09 | M22: 2.1185243e+08 | N22: 4596002.7 | O22: 4646738.1 | P22: 782836.85 | Q22: 911656.78 | R22: 43100829 | S22: 1.5174288e+09 | T22: 3.5297209e+08 | U22: 9243685.8 | V22: 3.0775416e+08 | W22: 1.478152e+08 | X22: 90002955 | Y22: 24741285 | Z22: 73474861 | AA22: 66554903 | AB22: 1.5795883e+08 | AC22: 89620866 | AD22: 2.994661e+08 | AE22: 61424360 | AF22: 1.9096466e+08 | AG22: 3.6681946e+08 | AH22: 4711107.3 | AI22: 783216.38 | AJ22: 1210238.9 | AK22: 32318615 | AL22: 7944159.7 | AM22: 1586146.8 | AN22: 11041675 | AO22: 6680597.5 | AP22: 9704149.3 | AQ22: 1688039.1 | AR22: 1035556.6 | AS22: 182649.24 | AT22: 11733107 | AU22: 94772448 | AV22: 1876832.2 | AW22: 24103478 | AX22: 9039298.3 | AY22: 12137953 | AZ22: 20902180 | BA22: 6540875.2 | BB22: 985361.91 | BC22: 15566397 | BD22: 8049162.7 | BE22: 17946469 | BF22: 12944971 | BG22: 17860807 | BH22: 14599809 | BI22: 16305362 | BJ22: 90316.689 | BK22: 68116144 | BL22: 11193781 | BM22: 87956602 | BN22: 2.0081984e+08 | BO22: 20983280 | BP22: 1.8350841e+08 | BQ22: 17035988 | BR22: 16792078 | BS22: 1.4949045e+08 | BT22: 83525585 | BU22: 62074897 | BV22: 1.3817304e+08 | BW22: 3599572.8 | BX22: 148001.15 | BY22: 6462701.3 | BZ22: 1.4351446e+08 | CA22: 3.1328647e+08 | CB22: 15850342 | CC22: 9293012.8 | CD22: 54367435 | CF22: 10174138 | CH22: 49677693 | CI22: 43611823 | CN22: 66289592 | CO22: 80349182 | CP22: 70882928 | CQ22: 68219761 | CR22: 1.6321768e+08 | CS22: 1.9113388e+08 | CT22: 3.1749439e+08 | CU22: 2.0976101e+08 | CV22: 4.2652799e+08 | CW22: 44160093 | CX22: 18074130 | CY22: 1637991.3 | CZ22: 3.1151198e+08 | DA22: 1.9554673e+08 | DB22: 3.6582065e+08 | DC22: 1076253.8 | DE22: 5739498.8 | DF22: 33904627 | DG22: 5.4421134e+08 | DH22: 2.8239516e+09 | DI22: 1.3242788e+10
A23: 19 | B23: 302363.87 | C23: 981673.86 | D23: 181.22592 | E23: 477.85749 | F23: 3147.6422 | G23: 3456938.4 | H23: 119041.3 | I23: 78058.152 | J23: 8235397.5 | K23: 22590689 | L23: 17717960 | M23: 3310286.6 | N23: 126030.22 | O23: 187137.76 | P23: 716487.94 | Q23: 23769.418 | R23: 1540759.6 | S23: 9130968.9 | T23: 77186293 | U23: 1705764.3 | V23: 23441627 | W23: 2463754.1 | X23: 1412084.6 | Y23: 624080.75 | Z23: 5757240.4 | AA23: 8222366.4 | AB23: 10660930 | AC23: 1601237.7 | AD23: 8445290.7 | AE23: 1372312.6 | AF23: 4172200.5 | AG23: 7.7385312e+08 | AH23: 28541064 | AI23: 7400585.7 | AJ23: 5305023.6 | AK23: 39909225 | AL23: 19462502 | AM23: 10374307 | AN23: 27566236 | AO23: 44193418 | AP23: 27326683 | AQ23: 1553823.3 | AR23: 742321.33 | AS23: 465203.07 | AT23: 17205588 | AU23: 15691602 | AV23: 548918.85 | AW23: 4850733.3 | AX23: 596755.06 | AY23: 1820313.8 | AZ23: 80048923 | BA23: 63805783 | BB23: 32051059 | BC23: 22844028 | BD23: 42787925 | BE23: 7.8468988e+08 | BF23: 29072119 | BG23: 1.1145451e+08 | BH23: 27391249 | BI23: 1.290993e+08 | BJ23: 1485772.4 | BK23: 43476579 | BL23: 9181541.7 | BM23: 63504738 | BN23: 6.2017998e+08 | BO23: 83479958 | BP23: 1.7878237e+08 | BQ23: 2641948.2 | BR23: 81225538 | BS23: 1.2815462e+08 | BT23: 1.3576384e+08 | BU23: 11245813 | BV23: 3.0130491e+08 | BW23: 38053965 | BX23: 30668456 | BY23: 21681652 | BZ23: 53125613 | CA23: 89587749 | CB23: 13775996 | CC23: 50263452 | CD23: 1.2338067e+08 | CF23: 83255450 | CH23: 876813.87 | CI23: 503044.99 | CN23: 8717983.1 | CO23: 11661155 | CP23: 11848444 | CQ23: 10148731 | CR23: 22167003 | CS23: 33989208 | CT23: 64072932 | CU23: 55913491 | CV23: 1.3589426e+08 | CW23: 36647694 | CX23: 84606235 | CY23: 67037770 | CZ23: 2.6729755e+08 | DA23: 3.1376785e+08 | DB23: 1.9774976e+08 | DC23: 43761090 | DE23: 1.1405456e+08 | DF23: 30642346 | DG23: 5.3556022e+08 | DH23: 1.571582e+09 | DI23: 8.3489595e+09
A24: 20 | B24: 3.0846134e+08 | C24: 2.8877931e+08 | D24: 189873.67 | E24: 279995.84 | F24: 238617.17 | G24: 1.645282e+08 | H24: 74220074 | I24: 32743404 | J24: 2.8270143e+08 | K24: 6.7346169e+09 | L24: 2.6993282e+08 | M24: 63376194 | N24: 8570149.1 | O24: 10261076 | P24: 106336.32 | Q24: 704506.03 | R24: 78682224 | S24: 92709705 | T24: 56723251 | U24: 1.8673741e+09 | V24: 1.1229223e+09 | W24: 1.5056593e+08 | X24: 80036389 | Y24: 56071055 | Z24: 1.3439792e+08 | AA24: 73045656 | AB24: 1.9332827e+08 | AC24: 1.1345703e+08 | AD24: 77654583 | AE24: 31019490 | AF24: 1.5552298e+08 | AG24: 6.1161937e+08 | AH24: 60408614 | AI24: 2163148.1 | AJ24: 20649992 | AK24: 44359475 | AL24: 6591531.7 | AM24: 14706163 | AN24: 12812688 | AO24: 19904682 | AP24: 20728221 | AQ24: 2.9740472e+09 | AR24: 2.7706232e+08 | AS24: 3.6137588e+08 | AT24: 2.6529231e+09 | AU24: 5.7279619e+08 | AV24: 10771299 | AW24: 58402538 | AX24: 2.2201227e+08 | AY24: 4.8884903e+08 | AZ24: 16639478 | BA24: 19636762 | BB24: 6405300.9 | BC24: 48684597 | BD24: 96446465 | BE24: 38272435 | BF24: 2.1923009e+08 | BG24: 5.1454767e+08 | BH24: 2.1687915e+08 | BI24: 2948306.7 | BJ24: 94513903 | BK24: 1.0443712e+09 | BL24: 2.3839631e+08 | BM24: 54585644 | BN24: 5.1527194e+08 | BO24: 97398292 | BP24: 6.9532684e+08 | BQ24: 2.2708492e+08 | BR24: 2.2354137e+08 | BS24: 1.8060297e+08 | BT24: 2.1036144e+08 | BU24: 92796131 | BV24: 1.1398944e+08 | BW24: 34302253 | BX24: 6437592.2 | BY24: 1.2103057e+08 | BZ24: 1.1217816e+08 | CA24: 5.857976e+08 | CB24: 1.7230679e+08 | CC24: 89416850 | CD24: 1.7828343e+08 | CF24: 2.8516022e+09 | CH24: 2.3176887e+08 | CI24: 1.4318875e+08 | CN24: 7.5383665e+08 | CO24: 9.4674777e+08 | CP24: 8.5669227e+08 | CQ24: 9.5680084e+08 | CR24: 2.4550798e+09 | CS24: 3.0836133e+09 | CT24: 4.9851846e+09 | CU24: 3.4637479e+09 | CV24: 6.6524142e+09 | CW24: 69051358 | CX24: 2.7696682e+09 | CY24: 71.339888 | CZ24: 1.1943099e+10 | DA24: 3.8467979e+09 | DB24: 1.0002604e+09 | DC24: 112.29355 | DE24: 16976459 | DF24: 5.7976053e+08 | DG24: 1.1811451e+10 | DH24: 9.9140073e+09 | DI24: 9.6554839e+10
A25: 21 | B25: 2.3461621e+08 | C25: 1.1774973e+08 | D25: 552.43257 | E25: 6910.0921 | F25: 1584091.6 | G25: 1.0613361e+08 | H25: 21060634 | I25: 11516555 | J25: 40720486 | K25: 5.7700191e+08 | L25: 2.6625873e+08 | M25: 43241784 | N25: 72731798 | O25: 1.4095667e+08 | P25: 1806796.2 | Q25: 4092834.8 | R25: 51063067 | S25: 1.2830579e+08 | T25: 1.6044491e+08 | U25: 1.7586322e+09 | V25: 3.9810117e+09 | W25: 1.4299687e+09 | X25: 1.2048661e+08 | Y25: 38631536 | Z25: 2.6969123e+08 | AA25: 50631038 | AB25: 5.3292978e+08 | AC25: 1.103818e+08 | AD25: 4.0712596e+08 | AE25: 55718953 | AF25: 3.2834495e+08 | AG25: 89486695 | AH25: 2497657 | AI25: 494940.48 | AJ25: 569481.58 | AK25: 2166193.8 | AL25: 1728548.1 | AM25: 726534.41 | AN25: 766079.61 | AO25: 4799045.7 | AP25: 951239.95 | AQ25: 8986106.7 | AR25: 4531505.8 | AS25: 1315036.9 | AT25: 15536253 | AU25: 3702091.6 | AV25: 135627.82 | AW25: 995077.78 | AX25: 1063402.8 | AY25: 10872444 | AZ25: 8758727.9 | BA25: 12960448 | BB25: 2774831.8 | BC25: 15176815 | BD25: 11347023 | BE25: 76223215 | BF25: 1196098.2 | BG25: 3672079 | BH25: 1618397.9 | BI25: 699035.1 | BJ25: 283079.44 | BK25: 5.6262026e+08 | BL25: 5898467.1 | BM25: 951057.47 | BN25: 4.9325911e+08 | BO25: 20753739 | BP25: 3.3520614e+08 | BQ25: 98091634 | BR25: 33467932 | BS25: 1.056032e+09 | BT25: 1.3243101e+09 | BU25: 40589598 | BV25: 36476123 | BW25: 685094.38 | BX25: 4457568.3 | BY25: 31962246 | BZ25: 4786642.9 | CA25: 77184346 | CB25: 72174184 | CC25: 1.2115997e+08 | CD25: 12916288 | CF25: 1.6483612e+08 | CH25: 4.1366552e+08 | CI25: 2.8930729e+08 | CN25: 3.0284576e+08 | CO25: 5.6459165e+08 | CP25: 4.2527424e+08 | CQ25: 5.1465853e+08 | CR25: 1.3993808e+09 | CS25: 1.2681331e+09 | CT25: 1.9702332e+09 | CU25: 1.4001517e+09 | CV25: 2.7381648e+09 | CW25: 40399249 | CX25: 4.2008854e+08 | CY25: 70947.052 | CZ25: 8.0107143e+08 | DA25: 1.8013478e+08 | DB25: 1.8896055e+09 | DC25: 175612.38 | DE25: 3.0291119e+08 | DF25: 2.0417051e+08 | DG25: 1.5155703e+10 | DH25: 5.3995503e+10 | DI25: 1.0012294e+11
A26: 22 | B26: 33384033 | C26: 18205542 | D26: 28.174331 | E26: 28818.206 | F26: 28199.2 | G26: 1099334.6 | H26: 8319400.3 | I26: 4093725.6 | J26: 375029.14 | K26: 1.6253301e+09 | L26: 9.4881754e+08 | M26: 3.1228816e+08 | N26: 6759587.4 | O26: 4920398.6 | P26: 928602.59 | Q26: 3654402 | R26: 45951518 | S26: 58468182 | T26: 85741109 | U26: 17848774 | V26: 4.4991159e+08 | W26: 5.415523e+08 | X26: 44408966 | Y26: 8483830.6 | Z26: 1.0066145e+08 | AA26: 2.1383798e+08 | AB26: 8.1526248e+08 | AC26: 1.0629846e+08 | AD26: 9.7070889e+08 | AE26: 1.3360645e+08 | AF26: 3.0984932e+08 | AG26: 8.8517845e+08 | AH26: 23079896 | AI26: 2045418.3 | AJ26: 5842558.5 | AK26: 49906022 | AL26: 13287229 | AM26: 14249485 | AN26: 16242493 | AO26: 17932879 | AP26: 11864997 | AQ26: 13387453 | AR26: 139113.54 | AS26: 125475.94 | AT26: 41232378 | AU26: 7404434.1 | AV26: 3139676.4 | AW26: 2838685.7 | AX26: 27079854 | AY26: 11981142 | AZ26: 8422823.3 | BA26: 7686078.3 | BB26: 1.5742277e+08 | BC26: 1.0357483e+08 | BD26: 13397900 | BE26: 27308108 | BF26: 754387.63 | BG26: 6784124 | BH26: 1140858.8 | BI26: 12449107 | BJ26: 29734.904 | BK26: 21958644 | BL26: 65503103 | BM26: 72852136 | BN26: 4.8297882e+08 | BO26: 4231036.6 | BP26: 92571098 | BQ26: 21870574 | BR26: 29704443 | BS26: 3.5702447e+08 | BT26: 1.0261351e+08 | BU26: 58803312 | BV26: 85184778 | BW26: 2266677.1 | BX26: 330464.01 | BY26: 11114972 | BZ26: 6714501.4 | CA26: 4.3758659e+08 | CB26: 2.0780002e+08 | CC26: 36082387 | CD26: 27746121 | CF26: 4.0300744e+08 | CH26: 10166531 | CI26: 7049585.4 | CN26: 64308210 | CO26: 88582384 | CP26: 80512795 | CQ26: 84417054 | CR26: 2.011862e+08 | CS26: 2.4664059e+08 | CT26: 3.3386926e+08 | CU26: 2.3934524e+08 | CV26: 5.1472335e+08 | CW26: 10900186 | CX26: 1.1803076e+08 | CY26: 887368.4 | CZ26: 1.8164895e+08 | DA26: 75443257 | DB26: 4.1752569e+08 | DC26: 486660.63 | DE26: 96893879 | DF26: 49930309 | DG26: 1.4186967e+09 | DH26: 6.1716995e+09 | DI26: 2.1297642e+10
A27: 23 | B27: 5965279.5 | C27: 167583.28 | D27: 10.397707 | E27: 10259.349 | F27: 104.67876 | G27: 20966302 | H27: 9984536.5 | I27: 8232402.8 | J27: 7972665.4 | K27: 7.1175819e+09 | L27: 85796108 | M27: 4.5441313e+08 | N27: 144577.62 | O27: 13940.309 | P27: 2070.6919 | Q27: 2475.0135 | R27: 42528362 | S27: 5915287.6 | T27: 115268 | U27: 67043112 | V27: 95396080 | W27: 64360883 | X27: 1.1562626e+09 | Y27: 49191041 | Z27: 65771379 | AA27: 59896559 | AB27: 1.7704219e+08 | AC27: 96775500 | AD27: 4.5953493e+08 | AE27: 15972661 | AF27: 65006349 | AG27: 6613304.1 | AH27: 9175531.8 | AI27: 774862.68 | AJ27: 527768.7 | AK27: 3148687.2 | AL27: 136610.03 | AM27: 117942.75 | AN27: 4701248.5 | AO27: 6760386.1 | AP27: 198849.82 | AQ27: 170726.95 | AR27: 631254.37 | AS27: 45350.074 | AT27: 12225737 | AU27: 61309.283 | AV27: 33628.822 | AW27: 169659.87 | AX27: 370739.78 | AY27: 2742327.6 | AZ27: 235918.03 | BA27: 225599.94 | BB27: 37983073 | BC27: 1.3352178e+08 | BD27: 94513715 | BE27: 1867346.4 | BF27: 684442.45 | BG27: 2416364.9 | BH27: 842615.48 | BI27: 1042037.6 | BJ27: 5546.0451 | BK27: 36201701 | BL27: 59773720 | BM27: 8695474.4 | BN27: 4.1001311e+08 | BO27: 2897787.1 | BP27: 81968477 | BQ27: 19560020 | BR27: 7850287.3 | BS27: 1.135663e+08 | BT27: 94875000 | BU27: 8236923.8 | BV27: 37238381 | BW27: 1924482.9 | BX27: 1694.2873 | BY27: 11727386 | BZ27: 5538392.9 | CA27: 1.8267031e+08 | CB27: 42830729 | CC27: 24493749 | CD27: 23681712 | CF27: 5.9289344e+08 | CH27: 178539.57 | CI27: 99576.575 | CN27: 49908069 | CO27: 45376138 | CP27: 44605783 | CQ27: 64575971 | CR27: 1.1007308e+08 | CS27: 1.584657e+08 | CT27: 1.7358875e+08 | CU27: 1.3524916e+08 | CV27: 2.9361354e+08 | CW27: 14879400 | CX27: 19209522 | CY27: 6220.3166 | CZ27: 55849027 | DA27: 16051673 | DB27: 61264878 | DC27: 10080.402 | DE27: 3506146.1 | DF27: 56372441 | DG27: 5.5389277e+08 | DH27: 1.1980064e+09 | DI27: 1.5275432e+10
A28: 24 | B28: 628288.81 | C28: 847865.54 | D28: 137.01827 | E28: 349.20679 | F28: 245.87464 | G28: 30743900 | H28: 5459151.9 | I28: 1499534.2 | J28: 450023.44 | K28: 1.5009915e+08 | L28: 11682918 | M28: 36193983 | N28: 21871.887 | O28: 1241431 | P28: 6671.5543 | Q28: 3214.0758 | R28: 6242128.8 | S28: 11871354 | T28: 238328.26 | U28: 1769179.2 | V28: 2377080.5 | W28: 20073273 | X28: 27799580 | Y28: 6.5051849e+08 | Z28: 1.8200516e+09 | AA28: 5.0852996e+08 | AB28: 6.5444436e+08 | AC28: 5.1844816e+08 | AD28: 6.7532897e+08 | AE28: 66237014 | AF28: 1.6259295e+08 | AG28: 13611989 | AH28: 82394.059 | AI28: 12808.99 | AJ28: 17484.008 | AK28: 64183.81 | AL28: 16103.499 | AM28: 18622.705 | AN28: 166179.17 | AO28: 120218.77 | AP28: 50609.573 | AQ28: 2534530.8 | AR28: 7904527.8 | AS28: 491253.66 | AT28: 2133107.7 | AU28: 497956.14 | AV28: 279325.57 | AW28: 1928594.1 | AX28: 168114.4 | AY28: 424849.57 | AZ28: 246609.31 | BA28: 413891.53 | BB28: 2693954.8 | BC28: 6123037.4 | BD28: 4482202.8 | BE28: 19999362 | BF28: 187837.41 | BG28: 1148644.8 | BH28: 201868.34 | BI28: 27674.266 | BJ28: 74464.815 | BK28: 97591360 | BL28: 3033330.8 | BM28: 104076.31 | BN28: 38686828 | BO28: 1064305.3 | BP28: 18556326 | BQ28: 10159866 | BR28: 6973237.9 | BS28: 9225809.7 | BT28: 625882.44 | BU28: 429205.41 | BV28: 8179534 | BW28: 1297672.4 | BX28: 5138.3823 | BY28: 9181623 | BZ28: 939173.95 | CA28: 4483619.6 | CB28: 25927123 | CC28: 3167821.3 | CD28: 1940993.9 | CF28: 32267338 | CH28: 382580.21 | CI28: 279955.59 | CN28: 1742710.4 | CO28: 2451727.9 | CP28: 2030621.3 | CQ28: 2356581.3 | CR28: 5535326.7 | CS28: 6262175.6 | CT28: 9249606.7 | CU28: 6881665 | CV28: 14867800 | CW28: 4284905.4 | CX28: 9977167.7 | CY28: 39535.735 | CZ28: 11048348 | DA28: 2970629.2 | DB28: 1560249.1 | DC28: 50396.963 | DE28: 11553231 | DF28: 20424559 | DG28: 1.7843726e+09 | DH28: 4.4923503e+09 | DI28: 1.2096036e+10
A29: 25 | B29: 7106896 | C29: 55443938 | D29: 154.88202 | E29: 50744.639 | F29: 10113.786 | G29: 1.0823118e+08 | H29: 8820423.1 | I29: 7054428.8 | J29: 90120410 | K29: 6.4011918e+09 | L29: 6.9938398e+08 | M29: 5.0502516e+08 | N29: 7101059.8 | O29: 8910693.7 | P29: 1999621.5 | Q29: 1318422.5 | R29: 1.2509751e+08 | S29: 1.4896265e+08 | T29: 35161345 | U29: 70586894 | V29: 3.5962226e+08 | W29: 2.46174e+08 | X29: 95043771 | Y29: 1.286813e+08 | Z29: 1.8664742e+09 | AA29: 9.0555204e+08 | AB29: 2.3979766e+09 | AC29: 6.3639205e+08 | AD29: 1.6212233e+09 | AE29: 1.9390155e+08 | AF29: 3.791237e+08 | AG29: 1.5049691e+08 | AH29: 10486847 | AI29: 2162770.1 | AJ29: 1047647 | AK29: 6508535.8 | AL29: 2876802.3 | AM29: 2454022.8 | AN29: 4154312 | AO29: 20960320 | AP29: 3733895.6 | AQ29: 15228652 | AR29: 11156421 | AS29: 1.0204046e+08 | AT29: 1.0902404e+08 | AU29: 43579089 | AV29: 1.308328e+08 | AW29: 4483859.5 | AX29: 3073985.6 | AY29: 34604650 | AZ29: 45782066 | BA29: 3217723.9 | BB29: 2.0404548e+08 | BC29: 2.5557032e+08 | BD29: 99747097 | BE29: 61474028 | BF29: 5108490.9 | BG29: 15825429 | BH29: 4477729 | BI29: 769674.52 | BJ29: 1431853.5 | BK29: 1.4489828e+08 | BL29: 1.0924906e+08 | BM29: 1073314.9 | BN29: 5.6716514e+08 | BO29: 29449530 | BP29: 1.4556803e+08 | BQ29: 1.981866e+08 | BR29: 39447310 | BS29: 28073418 | BT29: 51841820 | BU29: 1689309.3 | BV29: 1.4185938e+08 | BW29: 3901895.7 | BX29: 188175.46 | BY29: 26538002 | BZ29: 64660168 | CA29: 2.1271965e+08 | CB29: 3.6886825e+08 | CC29: 15661770 | CD29: 54810998 | CF29: 8.3515988e+08 | CH29: 10588176 | CI29: 6278585.5 | CN29: 33302624 | CO29: 47769855 | CP29: 39651578 | CQ29: 43512170 | CR29: 1.3479171e+08 | CS29: 1.605069e+08 | CT29: 2.3720648e+08 | CU29: 1.9452894e+08 | CV29: 5.019572e+08 | CW29: 19238306 | CX29: 7.3885939e+08 | CY29: 17926440 | CZ29: 4.4174436e+08 | DA29: 23637576 | DB29: 73415283 | DC29: 9361727.7 | DE29: 2.5922969e+09 | DF29: 1.6218738e+08 | DG29: 2.8688178e+09 | DH29: 1.3064191e+10 | DI29: 4.2930878e+10
A30: 26 | B30: 2629149.6 | C30: 4750820.7 | D30: 2.624585 | E30: 5240.0915 | F30: 1637.0259 | G30: 23086747 | H30: 4099818.6 | I30: 5998589.7 | J30: 3205196.7 | K30: 5.7380439e+08 | L30: 25946048 | M30: 50727021 | N30: 66988.822 | O30: 88541.973 | P30: 39745.026 | Q30: 6138.9652 | R30: 4566383.5 | S30: 1505310.5 | T30: 7867953.6 | U30: 733084.03 | V30: 22507691 | W30: 11325865 | X30: 1462210.7 | Y30: 4302501.5 | Z30: 42764644 | AA30: 2.4028787e+08 | AB30: 33257131 | AC30: 33762671 | AD30: 5.1109157e+08 | AE30: 974492.39 | AF30: 11014524 | AG30: 19308392 | AH30: 1764201.6 | AI30: 45964.71 | AJ30: 263637.69 | AK30: 1040342.3 | AL30: 207735.28 | AM30: 440721.95 | AN30: 1111583.7 | AO30: 429518.44 | AP30: 991020.33 | AQ30: 180275.55 | AR30: 446176.52 | AS30: 734993.32 | AT30: 10362908 | AU30: 2758176.2 | AV30: 1405310 | AW30: 5145282.1 | AX30: 82717.414 | AY30: 11228314 | AZ30: 1016254.4 | BA30: 1490127.7 | BB30: 14084495 | BC30: 4934759.9 | BD30: 4553896.1 | BE30: 21372114 | BF30: 30850.213 | BG30: 1116356.7 | BH30: 80300.75 | BI30: 1647389.1 | BJ30: 8049.255 | BK30: 3024532.7 | BL30: 9254362.6 | BM30: 37200.971 | BN30: 56070227 | BO30: 1435237.8 | BP30: 31255492 | BQ30: 45545225 | BR30: 31987205 | BS30: 7480928.9 | BT30: 7044211.2 | BU30: 2104402.2 | BV30: 3692376.6 | BW30: 175980.85 | BX30: 34025.332 | BY30: 2197451.3 | BZ30: 687136.17 | CA30: 9238464.8 | CB30: 1.0469677e+08 | CC30: 3920382.3 | CD30: 4483643.3 | CF30: 42504164 | CH30: 2172236.3 | CI30: 1928394.2 | CN30: 3355124.1 | CO30: 4309871.4 | CP30: 3086748.1 | CQ30: 3879802 | CR30: 8972021.6 | CS30: 13655917 | CT30: 24905031 | CU30: 20401578 | CV30: 44535764 | CW30: 885718.63 | CX30: 27908812 | CY30: 4183721.2 | CZ30: 72323079 | DA30: 15577668 | DB30: 18065624 | DC30: 50344432 | DE30: 9.0667891e+09 | DF30: 82155078 | DG30: 1.0241635e+10 | DH30: 1.5622226e+10 | DI30: 3.7430328e+10
A31: 27 | B31: 1218730.1 | C31: 777826.18 | D31: 8.411211 | E31: 493.41435 | F31: 1525.1082 | G31: 811622.5 | H31: 123754.16 | I31: 381054.31 | J31: 1150049.8 | K31: 1.6716742e+08 | L31: 10686020 | M31: 1.6938315e+08 | N31: 4015465.7 | O31: 5466054.6 | P31: 779423.44 | Q31: 1258986.9 | R31: 39851789 | S31: 25479169 | T31: 21030384 | U31: 11340608 | V31: 96647588 | W31: 54148544 | X31: 26795945 | Y31: 25658492 | Z31: 2.1013461e+08 | AA31: 2.1604648e+08 | AB31: 7.7750696e+09 | AC31: 2.3897356e+08 | AD31: 6.6473344e+08 | AE31: 37944868 | AF31: 1.3476738e+08 | AG31: 1.55195e+09 | AH31: 8126127.7 | AI31: 102392.48 | AJ31: 466966.52 | AK31: 2223163.3 | AL31: 4841476.1 | AM31: 962002.28 | AN31: 706094.05 | AO31: 914503.98 | AP31: 1599503.1 | AQ31: 162825.64 | AR31: 696961.88 | AS31: 119916.08 | AT31: 2181523 | AU31: 325603.7 | AV31: 120084.25 | AW31: 353565.08 | AX31: 54206.004 | AY31: 1901649.5 | AZ31: 62831070 | BA31: 1.4389918e+08 | BB31: 5155819.3 | BC31: 1.7907206e+08 | BD31: 1.1703534e+08 | BE31: 33905095 | BF31: 2572429.1 | BG31: 11008380 | BH31: 3446475 | BI31: 723217.79 | BJ31: 6813683.7 | BK31: 6911871.9 | BL31: 2556288.6 | BM31: 1092023 | BN31: 4.331598e+08 | BO31: 26724579 | BP31: 79940667 | BQ31: 8943365 | BR31: 31499147 | BS31: 58785903 | BT31: 9824065.5 | BU31: 2583757.9 | BV31: 7216814.8 | BW31: 689220.65 | BX31: 50352.336 | BY31: 1349770.7 | BZ31: 23261191 | CA31: 4501884.1 | CB31: 2.8778391e+08 | CC31: 3247890.5 | CD31: 9143245.9 | CF31: 46476494 | CH31: 610998.14 | CI31: 473193 | CN31: 34507078 | CO31: 44952392 | CP31: 40776472 | CQ31: 53772970 | CR31: 1.270939e+08 | CS31: 1.5501381e+08 | CT31: 2.6926903e+08 | CU31: 2.3347211e+08 | CV31: 4.6029724e+08 | CW31: 13724226 | CX31: 4.5359502e+08 | CY31: 57199337 | CZ31: 31066700 | DA31: 11484455 | DB31: 8027673.9 | DC31: 78933560 | DE31: 1.0025332e+10 | DF31: 3.1960421e+08 | DG31: 2.9539432e+10 | DH31: 1.3842767e+11 | DI31: 1.9351816e+11
... A36: 32 | B36: 7.0544783e+08 | C36: 2.0006475e+09 | D36: 7946154.2 | E36: 352739.56 | F36: 3140540.1 | G36: 4.0994645e+08 | H36: 1.3142775e+08 | I36: 88275106 | J36: 7.2588942e+08 | K36: 1.8100444e+10 | L36: 1.1483746e+10 | M36: 3.5302937e+09 | N36: 1.1106843e+08 | O36: 96754436 | P36: 3.2704619e+08 | Q36: 74956734 | R36: 1.2826984e+09 | S36: 1.2052529e+09 | T36: 5.1977732e+08 | U36: 4.1536029e+09 | V36: 8.2253925e+09 | W36: 1.6552387e+09 | X36: 9.3985082e+08 | Y36: 1.3007759e+09 | Z36: 2.8800674e+09 | AA36: 3.2089997e+09 | AB36: 1.6747354e+10 | AC36: 2.3378235e+09 | AD36: 1.6559966e+10 | AE36: 7.1134036e+08 | AF36: 3.0987266e+09 | AG36: 9.9278886e+09 | AH36: 4.7534622e+08 | AI36: 46704365 | AJ36: 80857803 | AK36: 3.6155663e+08 | AL36: 1.1054418e+08 | AM36: 80321567 | AN36: 2.435464e+08 | AO36: 3.4161932e+08 | AP36: 2.8963495e+08 | AQ36: 4.5697413e+08 | AR36: 1.6213369e+08 | AS36: 1.7423417e+08 | AT36: 1.7548946e+09 | AU36: 4.0780633e+08 | AV36: 64764849 | AW36: 1.1419236e+08 | AX36: 1.4749181e+08 | AY36: 4.3134714e+08 | AZ36: 2.3850834e+09 | BA36: 84594200 | BB36: 5.3670042e+08 | BC36: 1.2051282e+09 | BD36: 6.6502893e+08 | BE36: 7.0188897e+08 | BF36: 1.261968e+08 | BG36: 3.7728145e+08 | BH36: 1.3268143e+08 | BI36: 88992628 | BJ36: 1.1871163e+08 | BK36: 1.7150922e+09 | BL36: 2.7021798e+09 | BM36: 1.9343976e+08 | BN36: 5.0507609e+09 | BO36: 5.9493445e+08 | BP36: 2.1329624e+09 | BQ36: 6.5642555e+08 | BR36: 6.2645839e+08 | BS36: 5.8311329e+09 | BT36: 2.8147786e+09 | BU36: 5.3824609e+08 | BV36: 1.3464983e+09 | BW36: 1.0803558e+08 | BX36: 40183912 | BY36: 6.0545986e+08 | BZ36: 4.7211627e+08 | CA36: 5.2223381e+09 | CB36: 2.6580194e+09 | CC36: 5.4198605e+08 | CD36: 5.4811546e+08 | CF36: 2.6198247e+09 | CH36: 9.0234492e+08 | CI36: 6.6503973e+08 | CN36: 3.3730604e+09 | CO36: 4.230406e+09 | CP36: 3.515707e+09 | CQ36: 4.0710336e+09 | CR36: 1.0021867e+10 | CS36: 1.2302338e+10 | CT36: 2.034404e+10 | CU36: 1.5580128e+10 | CV36: 3.2866439e+10 | CW36: 2.5643789e+08 | CX36: 6.0218278e+09 | CY36: 5.2554642e+08 | CZ36: 4.9951238e+09 | DA36: 1.7784811e+09 | DB36: 4.0917411e+09 | DC36: 1.3645516e+09 | DE36: 5.0824167e+08 | DF36: 1.5248673e+09 | DG36: 2.8425292e+10 | DH36: 3.1510186e+10 | DI36: 3.5061208e+11
A37: 33 | B37: 10102.257 | C37: 589901.71 | E37: 1590.3622 | G37: 4236172.4 | H37: 5222249.2 | I37: 1767443.9 | J37: 657656.12 | K37: 2.4322123e+08 | L37: 72772922 | M37: 86447727 | N37: 50847.36 | O37: 346220.09 | R37: 24758792 | S37: 22239321 | T37: 4488158.2 | U37: 1950387.6 | V37: 44360018 | W37: 7818882.1 | X37: 15855646 | Y37: 4691406.9 | Z37: 34841279 | AA37: 78951234 | AB37: 69693164 | AC37: 754062.55 | AD37: 1.3688882e+08 | AE37: 10328258 | AF37: 43159364 | AG37: 4018296.3 | AH37: 30735604 | AI37: 1435588.6 | AJ37: 13404480 | AK37: 51713697 | AL37: 18688428 | AM37: 3658749.7 | AN37: 3342834.8 | AO37: 10395068 | AP37: 12358705 | AR37: 331090.6 | AS37: 2712245 | AT37: 1.7715262e+08 | AU37: 1303392.6 | AV37: 8047.6802 | AW37: 441825.82 | AX37: 314707.69 | AY37: 5757381.5 | AZ37: 3829996.1 | BA37: 5254704.6 | BB37: 322044.26 | BC37: 5824391.2 | BD37: 2112511.5 | BE37: 391022.99 | BF37: 904437.36 | BG37: 1003147.2 | BH37: 1605695.7 | BI37: 586769.81 | BK37: 80968560 | BL37: 59828766 | BN37: 85558768 | BP37: 2.8152047e+08 | BQ37: 9855773.7 | BR37: 315550.72 | BS37: 291510.41 | BT37: 115325.84 | BU37: 10245.345 | BV37: 190498.5 | BW37: 923078.7 | BX37: 14317.277 | BY37: 1966036.5 | BZ37: 5648240.4 | CA37: 20030371 | CB37: 8.7476927e+08 | CC37: 26217868 | CD37: 51486498 | CF37: 563412.66 | CH37: 1661.9155 | CI37: 1551.8415 | CN37: 1.2834572e+09 | CO37: 1.5663951e+09 | CP37: 1.3334917e+09 | CQ37: 1.528504e+09 | CR37: 3.7890404e+09 | CS37: 4.9666865e+09 | CT37: 8.1813599e+09 | CU37: 6.7449264e+09 | CV37: 1.4337429e+10 | CW37: 55170.867 | CZ37: 301427.45 | DA37: 891595.95 | DB37: 51744.416 | DE37: 19718512 | DH37: 246718.5 | DI37: 4.6528544e+10
A38: 34 | B38: 1722.9289 | C38: 5974.6602 | G38: 64046.125 | H38: 4406.9346 | I38: 1368.4782 | J38: 143571.82 | K38: 1.8936791e+08 | L38: 3449618.9 | M38: 3179532.7 | O38: 360192.95 | R38: 6774052.8 | S38: 472638.86 | T38: 25540164 | U38: 3186305.3 | V38: 15942940 | W38: 493063.99 | X38: 9474.8188 | Y38: 19552.267 | Z38: 1009760.5 | AA38: 2806672.9 | AB38: 4461580.6 | AC38: 2200743.6 | AD38: 1311243.6 | AE38: 1852250 | AF38: 6374280.7 | AG38: 15758694 | AH38: 3784727.6 | AI38: 255835.84 | AJ38: 338728.85 | AK38: 1733633.3 | AL38: 572906 | AM38: 633853.91 | AN38: 563718.17 | AO38: 2163089.8 | AP38: 4914188.5 | AR38: 24207.891 | AS38: 4772160.2 | AT38: 2181390.6 | AU38: 4893.7129 | AV38: 225367.31 | AW38: 44662.866 | AX38: 390507.5 | AY38: 6211.3142 | AZ38: 417814.95 | BA38: 478889.86 | BC38: 80615.262 | BD38: 1171328.5 | BE38: 7927719.6 | BF38: 1523394.4 | BG38: 6642329.2 | BH38: 2501546.5 | BI38: 526103.97 | BK38: 59225656 | BL38: 915802.83 | BN38: 13181231 | BP38: 15345875 | BQ38: 427037.03 | BR38: 3876225.9 | BS38: 10933826 | BT38: 2844350.9 | BU38: 2378815.6 | BV38: 4618475.3 | BW38: 4617.538 | BX38: 270107.76 | BY38: 473888.85 | BZ38: 36779579 | CA38: 1.0601255e+08 | CB38: 34726638 | CC38: 2272125.9 | CD38: 3826599.7 | CH38: 2924.1189 | CI38: 2730.4451 | CN38: 4.5188599e+08 | CO38: 5.5153459e+08 | CP38: 4.695353e+08 | CQ38: 5.3899468e+08 | CR38: 1.3361276e+09 | CS38: 1.7506019e+09 | CT38: 2.8852839e+09 | CU38: 2.3784797e+09 | CV38: 5.054899e+09 | CW38: 589038.42 | CX38: 106581.88 | CZ38: 1163862.2 | DA38: 6160871.5 | DB38: 449919.53 | DE38: 8645329.2 | DH38: 1.1287916e+09 | DI38: 1.719004e+10
A39: 35 | B39: 46812.146 | C39: 366230.96 | G39: 1271834.2 | H39: 75355.625 | I39: 30533.764 | J39: 541574.37 | K39: 1.125258e+10 | L39: 57381130 | M39: 60545964 | O39: 457592.13 | Q39: 135260.14 | R39: 9975849.6 | S39: 8494849.1 | T39: 1014423.2 | U39: 7869090.5 | V39: 1.7212998e+08 | W39: 5842378.3 | X39: 192271.78 | Y39: 285296.52 | Z39: 18804175 | AA39: 44373987 | AB39: 99582878 | AC39: 42051333 | AD39: 21831673 | AE39: 32196034 | AF39: 1.2065463e+08 | AG39: 806390.03 | AH39: 12340150 | AI39: 89972.503 | AJ39: 3826435.5 | AK39: 14513857 | AL39: 2419001.2 | AM39: 8102802.5 | AN39: 28051.709 | AO39: 768462.32 | AP39: 2796536.5 | AQ39: 135064.17 | AR39: 259375.07 | AS39: 3149908.5 | AT39: 7901250.6 | AU39: 615951.91 | AV39: 9346.3006 | AW39: 41224.209 | AX39: 365490.75 | AY39: 261932.92 | AZ39: 68639.283 | BA39: 24793.059 | BC39: 671903.72 | BD39: 57138.832 | BE39: 398017.3 | BF39: 386811.45 | BG39: 1037624.1 | BH39: 550052.53 | BI39: 26865.025 | BK39: 9.605451e+08 | BL39: 8443276.2 | BN39: 7724404.8 | BP39: 1.1573129e+08 | BQ39: 171161.81 | BR39: 2010430.5 | BS39: 5037468.2 | BT39: 387708 | BU39: 2983416.9 | BV39: 221238.44 | BW39: 1.861398e+08 | BX39: 16627.596 | BY39: 32132735 | BZ39: 3103297.3 | CA39: 6.9196899e+08 | CB39: 4.347576e+08 | CC39: 600749.96 | CD39: 2914396.9 | CH39: 65623.121 | CI39: 61276.691 | CN39: 3.0863046e+08 | CO39: 3.7668868e+08 | CP39: 3.2068455e+08 | CQ39: 3.681219e+08 | CR39: 9.125467e+08 | CS39: 1.1956261e+09 | CT39: 1.9705867e+09 | CU39: 1.624451e+09 | CV39: 3.452391e+09 | CW39: 64073.558 | CZ39: 350067.53 | DA39: 1035469 | DB39: 60094.195 | DE39: 9910922.4 | DH39: 78905012 | DI39: 2.5095453e+10
A40: 36 | B40: 1694269.6 | C40: 1396618.5 | G40: 7222.426 | H40: 2459.8866 | I40: 769.27558 | J40: 1922010.6 | K40: 29947317 | L40: 825399.65 | M40: 1129958.9 | O40: 3521.8129 | R40: 18032.445 | S40: 189056.22 | T40: 3081911 | U40: 2272400.9 | V40: 8675430.6 | W40: 108089.19 | X40: 503615.98 | Y40: 2037.1256 | Z40: 320589.67 | AA40: 897418.32 | AB40: 4456841.8 | AC40: 747507.51 | AD40: 412345.56 | AE40: 548674.89 | AF40: 2107317.7 | AG40: 2300423.2 | AH40: 1842539.1 | AI40: 82514.922 | AJ40: 102148.97 | AK40: 526372.6 | AL40: 144875.98 | AM40: 236892.56 | AN40: 61638.802 | AO40: 701598.38 | AP40: 2389278.2 | AR40: 220896.77 | AS40: 2682619.5 | AT40: 33780154 | AU40: 5481907.9 | AV40: 18904.469 | AW40: 143005.5 | AX40: 1271520 | AY40: 2628.2787 | AZ40: 14952.579 | BA40: 54295.733 | BC40: 4352.0136 | BD40: 93269.377 | BE40: 1179634.4 | BF40: 254968.21 | BG40: 990837.33 | BH40: 369311.7 | BI40: 54339.043 | BK40: 22487749 | BL40: 387899.01 | BN40: 1318912.6 | BP40: 9122439.6 | BQ40: 19585.214 | BR40: 1997831.3 | BS40: 849854.35 | BT40: 418242.57 | BU40: 22762.832 | BV40: 647131.42 | BW40: 715.48928 | BX40: 14160.892 | BY40: 1930.264 | BZ40: 4980911.5 | CA40: 2.4120313e+08 | CB40: 7784193.2 | CC40: 319484.16 | CD40: 478037.31 | CH40: 1032282.9 | CI40: 435156.22 | CN40: 1.1714545e+09 | CO40: 1.4297031e+09 | CP40: 1.2171245e+09 | CQ40: 1.3951638e+09 | CR40: 3.4585007e+09 | CS40: 4.533369e+09 | CT40: 7.4676696e+09 | CU40: 6.1565289e+09 | CV40: 1.3086642e+10 | CW40: 54568.243 | CZ40: 596270 | DA40: 1373018.1 | DB40: 51179.219 | DE40: 1090781.9 | DH40: 8.8667229e+09 | DI40: 4.9195844e+10
A41: 37 | B41: 1059.1841 | C41: 1486.6786 | G41: 4043.0189 | H41: 2891.7254 | I41: 904.32371 | J41: 73882.387 | K41: 7544796.3 | L41: 124826.22 | M41: 365342.16 | O41: 4140.0754 | R41: 21198.083 | S41: 23652.666 | T41: 3133989.9 | U41: 2033170.9 | V41: 4767043.5 | W41: 40981.207 | X41: 6261.1908 | Y41: 2394.7478 | Z41: 45369.093 | AA41: 175142.22 | AB41: 1425670.5 | AC41: 67881.042 | AD41: 114368.57 | AE41: 66028.846 | AF41: 535833.67 | AG41: 2307539.2 | AH41: 1680281.5 | AI41: 94968.221 | AJ41: 33942.025 | AK41: 245046.85 | AL41: 89984.056 | AM41: 94485.295 | AN41: 69601.349 | AO41: 817484.51 | AP41: 2678472.2 | AR41: 319.33886 | AS41: 3153559.6 | AT41: 1151578.2 | AU41: 3233.8846 | AV41: 22223.193 | AW41: 377.81026 | AX41: 248756.5 | AY41: 3089.6792 | AZ41: 17577.539 | BA41: 24821.796 | BC41: 5116.0198 | BD41: 109643.03 | BE41: 1236194.9 | BF41: 188631.03 | BG41: 1051856.6 | BH41: 395753.98 | BI41: 63878.389 | BK41: 5508462.4 | BL41: 47148.422 | BN41: 1343557.2 | BP41: 1965387.6 | BQ41: 23023.444 | BR41: 904481.14 | BS41: 945771.33 | BT41: 338755.54 | BU41: 11912.385 | BV41: 393409.55 | BW41: 841.0951 | BX41: 16646.869 | BY41: 2269.1263 | BZ41: 5106857.3 | CA41: 6304400.8 | CB41: 2173391.2 | CC41: 375570.35 | CD41: 540270.57 | CH41: 1932.329 | CI41: 1804.3446 | CN41: 7.1035866e+08 | CO41: 8.6697077e+08 | CP41: 7.380662e+08 | CQ41: 8.4635941e+08 | CR41: 2.0980591e+09 | CS41: 2.7497834e+09 | CT41: 4.530297e+09 | CU41: 3.7347944e+09 | CV41: 7.9384836e+09 | CW41: 64147.826 | CZ41: 350473.3 | DA41: 1325362 | DB41: 60163.85 | DE41: 1140586.8 | DH41: 4.3262618e+08 | DI41: 2.4711116e+10
A42: 38 | B42: 38802036 | C42: 30496043 | G42: 47190.393 | H42: 49399.794 | I42: 11289.264 | J42: 41967026 | K42: 6684154.8 | L42: 356213.43 | M42: 723514.12 | O42: 2727.0453 | R42: 86323.877 | S42: 154256.02 | T42: 605769.81 | U42: 2796818.6 | V42: 5797127.5 | W42: 64568.113 | X42: 103895.81 | Y42: 1577.4074 | Z42: 94923.083 | AA42: 623404.9 | AB42: 1270767.8 | AC42: 41617.171 | AD42: 1170021.2 | AE42: 38051.997 | AF42: 501524.12 | AG42: 531780.43 | AH42: 5990269.5 | AI42: 60416.959 | AJ42: 95978.72 | AK42: 469854.21 | AL42: 212106.05 | AM42: 61851.195 | AN42: 26070.749 | AO42: 516026.07 | AP42: 1812265.2 | AR42: 4550326.7 | AS42: 3689763.3 | AT42: 7.0553611e+08 | AU42: 1.2898717e+08 | AV42: 6163.4936 | AW42: 3464800.2 | AX42: 20712359 | AY42: 83186.961 | AZ42: 13842.814 | BA42: 16349.983 | BC42: 3369.8946 | BD42: 37680.665 | BE42: 262475.73 | BF42: 51070.947 | BG42: 226529.4 | BH42: 82761.088 | BI42: 17716.358 | BK42: 3627910.2 | BL42: 722391.43 | BN42: 1082476.3 | BP42: 3736643.1 | BQ42: 112874.04 | BR42: 241671.48 | BS42: 223259.68 | BT42: 88324.843 | BU42: 7846.624 | BV42: 145897.48 | BW42: 554.0248 | BX42: 10965.203 | BY42: 1494.6613 | BZ42: 1139303.2 | CA42: 1668959.8 | CB42: 7750326.5 | CC42: 231995.97 | CD42: 629841.73 | CF42: 861.58995 | CH42: 25385016 | CI42: 13623736 | CN42: 3.0969278e+08 | CO42: 3.7797628e+08 | CP42: 3.2177865e+08 | CQ42: 3.6914362e+08 | CR42: 9.1507874e+08 | CS42: 1.1991789e+09 | CT42: 1.9759676e+09 | CU42: 1.6289526e+09 | CV42: 3.4622361e+09 | CW42: 42253.827 | CZ42: 230854.87 | DA42: 777928.61 | DB42: 39629.604 | DE42: 741564.93 | DH42: 8403449.8 | DI42: 1.1640682e+10
A43: 39 | B43: 894.86492 | C43: 1256.039 | G43: 3415.7951 | H43: 2443.1104 | I43: 764.0292 | J43: 62420.459 | K43: 1234594.4 | L43: 105460.99 | M43: 109339.33 | O43: 776069.56 | R43: 17909.466 | S43: 19983.251 | T43: 16646053 | U43: 1717749.8 | V43: 3649629.4 | W43: 22356.019 | X43: 5289.8454 | Y43: 2023.2326 | Z43: 38330.646 | AA43: 93763.57 | AB43: 1191872.7 | AC43: 57221.14 | AD43: 86363.52 | AE43: 48806.693 | AF43: 175452.21 | AG43: 682078.38 | AH43: 1266113.9 | AI43: 67751.473 | AJ43: 17894.326 | AK43: 80335.323 | AL43: 48008.354 | AM43: 21230.688 | AN43: 29466.404 | AO43: 586892.22 | AP43: 2228064 | AR43: 269.79743 | AS43: 2664324.3 | AT43: 984310.53 | AU43: 2732.1878 | AV43: 7905.4916 | AW43: 319.19772 | AX43: 210165.04 | AY43: 2610.3541 | AZ43: 14850.604 | BA43: 20971.005 | BC43: 4322.3333 | BD43: 48330.412 | BE43: 336659.67 | BF43: 65505.211 | BG43: 290553.77 | BH43: 106151.99 | BI43: 22723.561 | BK43: 1421751.7 | BL43: 39833.935 | BN43: 481366.49 | BP43: 517944.81 | BQ43: 19451.644 | BR43: 309975.48 | BS43: 286359.92 | BT43: 113288.23 | BU43: 10064.328 | BV43: 187132.72 | BW43: 710.60972 | BX43: 14064.316 | BY43: 1917.0998 | BZ43: 1461306.2 | CA43: 1588297 | CB43: 959519.23 | CC43: 108527.29 | CD43: 169678 | CH43: 1632.5523 | CI43: 1524.4231 | CN43: 6.9550663e+08 | CO43: 8.4884082e+08 | CP43: 7.2263107e+08 | CQ43: 8.2856809e+08 | CR43: 2.0539555e+09 | CS43: 2.6920718e+09 | CT43: 4.4350311e+09 | CU43: 3.6562825e+09 | CV43: 7.7717115e+09 | CW43: 54196.093 | CZ43: 296101.75 | DA43: 875842.99 | DB43: 50830.182 | DE43: 950420.24 | DH43: 7.91116e+09 | DI43: 3.1661561e+10
A44: 40 | B44: 2431.4926 | C44: 8426.3849 | G44: 88800.527 | H44: 6219.7915 | I44: 1931.4275 | J44: 266383.44 | K44: 2.6665081e+08 | L44: 4437074.3 | M44: 4696218.3 | O44: 513121.54 | R44: 9697353 | S44: 666579.51 | T44: 36017044 | U44: 4498799.7 | V44: 20020326 | W44: 695343.6 | X44: 13372.464 | Y44: 27575.969 | Z44: 1362462.8 | AA44: 3599929.9 | AB44: 11881984 | AC44: 3360619.2 | AD44: 1849419.4 | AE44: 2382194.1 | AF44: 8988935.8 | AG44: 22222100 | AH44: 5340545.9 | AI44: 360947.72 | AJ44: 477771.54 | AK44: 2445176.8 | AL44: 808109.6 | AM44: 893921.76 | AN44: 795053.17 | AO44: 3051859.1 | AP44: 6934815.8 | AR44: 34143.883 | AS44: 6735278.1 | AT44: 3078669 | AU44: 6906.8338 | AV44: 317802.23 | AW44: 62998.515 | AX44: 551150.11 | AY44: 8763.9549 | AZ44: 589683.31 | BA44: 675325.48 | BC44: 113703.34 | BD44: 1651738.6 | BE44: 11179240 | BF44: 2148226.5 | BG44: 9366706 | BH44: 3527571.2 | BI44: 741886.72 | BK44: 83517932 | BL44: 1294989.4 | BN44: 18587777 | BP44: 21178967 | BQ44: 602253.17 | BR44: 5466507.9 | BS44: 15417083 | BT44: 4010905.1 | BU44: 3353858.4 | BV44: 6512590.6 | BW44: 6511.6038 | BX44: 380903.14 | BY44: 673368.7 | BZ44: 52509406 | CA44: 1.4947633e+08 | CB44: 49131708 | CC44: 3204145.2 | CD44: 5421329 | CH44: 4127.0103 | CI44: 3853.6651 | CN44: 6.3728106e+08 | CO44: 7.7781245e+08 | CP44: 6.6217134e+08 | CQ44: 7.601278e+08 | CR44: 1.8843001e+09 | CS44: 2.4688206e+09 | CT44: 4.0690281e+09 | CU44: 3.3542975e+09 | CV44: 7.1287703e+09 | CW44: 830549.53 | CX44: 150252.82 | CZ44: 1641607.4 | DA44: 8687785.8 | DB44: 634418.14 | DE44: 12190430 | DH44: 9.1797767e+08 | DI44: 2.357133e+10
A45: 41 | B45: 4093182.2 | C45: 3266784.5 | E45: 925.72524 | G45: 291722.1 | H45: 169760.93 | I45: 66197.33 | J45: 4371315.4 | K45: 1.9978156e+08 | L45: 9719550.1 | M45: 7808987.7 | O45: 188275.04 | R45: 1190585.7 | S45: 1695852.5 | T45: 13497623 | U45: 2310071.1 | V45: 23255039 | W45: 919992.54 | X45: 1592078.4 | Y45: 239730.89 | Z45: 3004143.9 | AA45: 7377915.1 | AB45: 14614503 | AC45: 4418194.4 | AD45: 7193087.7 | AE45: 3618179.5 | AF45: 14041182 | AG45: 7505403.6 | AH45: 4468323.3 | AI45: 204690.37 | AJ45: 982651.22 | AK45: 4530271.8 | AL45: 1134648.8 | AM45: 1437657 | AN45: 475913.35 | AO45: 1652563.7 | AP45: 3386111 | AR45: 506985.71 | AS45: 2494995.5 | AT45: 79773718 | AU45: 13439758 | AV45: 58299.136 | AW45: 384603.3 | AX45: 2318602.6 | AY45: 210834.27 | AZ45: 351972.86 | BA45: 420818.81 | BC45: 309652.33 | BD45: 532733.96 | BE45: 3702478.5 | BF45: 713908.86 | BG45: 3069188.7 | BH45: 1196663.8 | BI45: 255352.61 | BK45: 1.1926213e+08 | BL45: 4860514 | BN45: 9006915 | BP45: 36631782 | BQ45: 484790.18 | BR45: 13548824 | BS45: 3402478.5 | BT45: 1202334.1 | BU45: 168149.93 | BV45: 1976689.7 | BW45: 1252372.3 | BX45: 109753.92 | BY45: 299658.84 | BZ45: 15896449 | CA45: 59487492 | CB45: 72073245 | CC45: 2085515.3 | CD45: 3527551.2 | CH45: 2860378.9 | CI45: 1195357.7 | CN45: 1.0223635e+09 | CO45: 1.2477461e+09 | CP45: 1.0622225e+09 | CQ45: 1.2176361e+09 | CR45: 3.0184236e+09 | CS45: 3.9564869e+09 | CT45: 6.517458e+09 | CU45: 5.373142e+09 | CV45: 1.1421394e+10 | CW45: 170380.73 | CZ45: 554566.52 | DA45: 2190606.1 | DB45: 47599.714 | DE45: 2497874.6 | DH45: 4722008.7 | DI45: 3.5660633e+10
A46: 42 | B46: 10863392 | C46: 4265469.8 | D46: 284231.63 | E46: 277.05591 | F46: 2342.7269 | G46: 1065120.8 | H46: 895018.79 | I46: 3430785.4 | J46: 60747754 | K46: 84406502 | L46: 63528126 | M46: 19713096 | N46: 1131053.9 | O46: 800736.32 | P46: 1357000.6 | Q46: 123665.58 | R46: 11581328 | S46: 13768951 | T46: 13632660 | U46: 14235555 | V46: 34043627 | W46: 28158031 | X46: 37854779 | Y46: 8875448.3 | Z46: 42338007 | AA46: 25514752 | AB46: 55441854 | AC46: 7748560.2 | AD46: 51100777 | AE46: 12123220 | AF46: 28973761 | AG46: 9.310611e+08 | AH46: 13825893 | AI46: 411258.55 | AJ46: 1764262.2 | AK46: 5584120 | AL46: 2159624.5 | AM46: 1304793.6 | AN46: 3859944 | AO46: 3058645.3 | AP46: 6276353.5 | AQ46: 27559797 | AR46: 1093014.4 | AS46: 11190662 | AT46: 3.2458235e+08 | AU46: 9035092.3 | AV46: 319772.83 | AW46: 37275172 | AX46: 1541535.1 | AY46: 37517234 | AZ46: 36636194 | BA46: 42642939 | BB46: 5697405.4 | BC46: 58157868 | BD46: 2.3825089e+08 | BE46: 1.3810263e+08 | BF46: 1.1981168e+08 | BG46: 4.356033e+08 | BH46: 1.9343842e+08 | BI46: 11124720 | BJ46: 48629219 | BK46: 1.7561509e+09 | BL46: 1.651191e+08 | BM46: 15104325 | BN46: 1.1419669e+09 | BO46: 41009737 | BP46: 4.7266182e+08 | BQ46: 53970946 | BR46: 92709253 | BS46: 2.811436e+08 | BT46: 27606570 | BU46: 28940438 | BV46: 1.2075789e+08 | BW46: 27656112 | BX46: 783663.21 | BY46: 28649515 | BZ46: 19147369 | CA46: 2.2867933e+08 | CB46: 21855157 | CC46: 28555963 | CD46: 93980286 | CF46: 43100889 | CH46: 15559169 | CI46: 19858484 | CN46: 2.8748334e+08 | CO46: 3.4541129e+08 | CP46: 4.5373029e+08 | CQ46: 4.5479709e+08 | CR46: 1.101368e+09 | CS46: 1.4976368e+09 | CT46: 3.3193116e+09 | CU46: 3.0532937e+09 | CV46: 1.1383811e+10 | CW46: 1.2610314e+08 | CX46: 1.0474947e+09 | CY46: 10145178 | CZ46: 4.7953999e+08 | DA46: 85223230 | DB46: 2.0423702e+08 | DC46: 8092073.2 | DE46: 14914793 | DF46: 1439117.7 | DG46: 5.0241403e+09 | DH46: 1.448876e+08 | DI46: 3.715355e+10
A47: 43 | B47: 13953208 | C47: 41519926 | D47: 26363.635 | E47: 1325.7665 | F47: 56316.356 | G47: 7270414.1 | H47: 4033010.5 | I47: 1423552.9 | J47: 57043173 | K47: 1.7464514e+08 | L47: 4.2107758e+08 | M47: 30556825 | N47: 1666865.1 | O47: 479010.19 | P47: 349882.76 | Q47: 58748.638 | R47: 46735456 | S47: 90843343 | T47: 5555923.1 | U47: 2.0565118e+08 | V47: 1.731382e+08 | W47: 82482460 | X47: 1.7447803e+08 | Y47: 66227536 | Z47: 51754001 | AA47: 16082300 | AB47: 33426051 | AC47: 23000832 | AD47: 93676534 | AE47: 13523098 | AF47: 23643920 | AG47: 19856673 | AH47: 907612.12 | AI47: 71394.377 | AJ47: 357760.63 | AK47: 2504955.3 | AL47: 227844.75 | AM47: 535984.19 | AN47: 520037.84 | AO47: 618448.61 | AP47: 738606.22 | AQ47: 7530562.9 | AR47: 5130412.3 | AS47: 978596.67 | AT47: 3.0728058e+08 | AU47: 2804213.9 | AV47: 144508.71 | AW47: 3580224.6 | AX47: 644167.27 | AY47: 2004074.5 | AZ47: 1194955.7 | BA47: 584137.47 | BB47: 830998.34 | BC47: 11645627 | BD47: 1515374.9 | BE47: 3516139.4 | BF47: 1239419 | BG47: 3107303.3 | BH47: 1377664.7 | BI47: 5317690 | BJ47: 234666.02 | BK47: 39405336 | BL47: 3404923.2 | BM47: 4804981.5 | BN47: 71586159 | BO47: 1847597.1 | BP47: 37355524 | BQ47: 3887532.6 | BR47: 5200952.5 | BS47: 28306557 | BT47: 8284525.8 | BU47: 4778645.2 | BV47: 14217349 | BW47: 1751077.7 | BX47: 114261.84 | BY47: 5092853.5 | BZ47: 5472972.3 | CA47: 77759404 | CB47: 11056860 | CC47: 3059458.3 | CD47: 4057881.5 | CF47: 1.974556e+08 | CH47: 12255236 | CI47: 6269553.9 | CN47: 16791491 | CO47: 20842418 | CP47: 18843146 | CQ47: 19866759 | CR47: 48974473 | CS47: 69348477 | CT47: 1.2407971e+08 | CU47: 97510259 | CV47: 2.4684437e+08 | CW47: 29602443 | CX47: 31733920 | CY47: 233910.47 | CZ47: 1.3416693e+08 | DA47: 31209372 | DB47: 1.0421989e+08 | DC47: 3108513.7 | DE47: 1612927.2 | DG47: 5.8100936e+08 | DH47: 5787638.4 | DI47: 4.3745921e+09
A48: 44 | B48: 6594734.8 | C48: 12214998 | E48: 1370.5905 | F48: 7624.8366 | G48: 3037386.7 | H48: 1224826.6 | I48: 445804.42 | J48: 4228590.3 | K48: 69493925 | L48: 1.0000949e+08 | M48: 15114155 | N48: 739962.88 | O48: 73859.024 | R48: 425832.69 | S48: 995830.39 | T48: 48407.617 | U48: 9791501.8 | V48: 30612856 | W48: 3284628.6 | X48: 17797468 | Y48: 9109848.7 | Z48: 6760447.7 | AA48: 2119381.6 | AB48: 8449255.4 | AC48: 6233205 | AD48: 4350766.8 | AE48: 686957.66 | AF48: 4254223.9 | AG48: 2592518.2 | AH48: 662154.92 | AI48: 10410.311 | AJ48: 45009.271 | AK48: 408124.55 | AL48: 46397.906 | AM48: 165127.77 | AN48: 141959.6 | AO48: 95025.396 | AP48: 119167.74 | AQ48: 1517568.8 | AR48: 275524.97 | AS48: 181406.68 | AT48: 1830163.6 | AU48: 297435.13 | AV48: 76822.214 | AW48: 98932.619 | AX48: 113316.25 | AY48: 376843.01 | AZ48: 1082.1587 | BA48: 2990.5142 | BB48: 199216.13 | BC48: 910973.38 | BD48: 129348.78 | BE48: 785921.21 | BF48: 95581.433 | BG48: 204859.65 | BH48: 111839.65 | BI48: 7.5571411 | BJ48: 48233.509 | BK48: 7264530.2 | BL48: 816374.35 | BM48: 217.04122 | BN48: 2.0876649e+08 | BO48: 2015279.8 | BP48: 6981319.8 | BQ48: 1511672.9 | BR48: 1644525.6 | BS48: 7894214.4 | BT48: 2730208.8 | BU48: 557261.14 | BV48: 2253015.5 | BW48: 236775.16 | BX48: 1214.0318 | BY48: 739451.16 | BZ48: 665517.75 | CA48: 6491479.9 | CB48: 2547802.7 | CC48: 1014268.2 | CD48: 508952.55 | CF48: 63297504 | CH48: 2862448.5 | CI48: 2188746.2 | CN48: 43820850 | CO48: 52644721 | CP48: 67239578 | CQ48: 67773694 | CR48: 1.6424173e+08 | CS48: 2.3580097e+08 | CT48: 5.032284e+08 | CU48: 4.7789245e+08 | CV48: 1.7488084e+09 | CW48: 4824801.3 | CX48: 1.7043902e+08 | CZ48: 37089230 | DA48: 4443658.8 | DB48: 28806327 | DE48: 2508.3694 | DF48: 158875.65 | DG48: 1.2669674e+09 | DH48: 1082865.8 | DI48: 5.5279061e+09
A49: 45 | B49: 1.3838957e+08 | C49: 4.196974e+08 | D49: 2915930.3 | E49: 124297.46 | F49: 302432.58 | G49: 42929676 | H49: 31901302 | I49: 10455548 | J49: 85965227 | K49: 4.0066954e+09 | L49: 3.7434926e+09 | M49: 6.5957766e+08 | N49: 33636612 | O49: 23695179 | P49: 89245872 | Q49: 5432883.5 | R49: 2.7901443e+08 | S49: 3.1222392e+08 | T49: 84568182 | U49: 1.5336933e+09 | V49: 8.0210332e+08 | W49: 2.6623976e+08 | X49: 4.9646705e+08 | Y49: 4.3720818e+08 | Z49: 5.3704071e+08 | AA49: 3.3901084e+08 | AB49: 1.328527e+09 | AC49: 2.8300875e+08 | AD49: 1.3081666e+09 | AE49: 1.483674e+08 | AF49: 3.1884594e+08 | AG49: 1.8228559e+09 | AH49: 2.0716662e+08 | AI49: 11478146 | AJ49: 23200019 | AK49: 1.8394072e+08 | AL49: 29574508 | AM49: 68051911 | AN49: 1.360462e+08 | AO49: 98568875 | AP49: 1.2006715e+08 | AQ49: 2.1909114e+08 | AR49: 27100589 | AS49: 28550060 | AT49: 2.1789967e+09 | AU49: 83416677 | AV49: 9985261.6 | AW49: 1.5931842e+08 | AX49: 21829551 | AY49: 2.0254261e+08 | AZ49: 80379772 | BA49: 54565285 | BB49: 53770114 | BC49: 1.0560696e+08 | BD49: 1.8165415e+08 | BE49: 2.3728281e+08 | BF49: 16671589 | BG49: 1.1892502e+08 | BH49: 19259880 | BI49: 21549349 | BJ49: 7076746.3 | BK49: 4.2584361e+08 | BL49: 94600521 | BM49: 1.5721719e+08 | BN49: 9.1661328e+08 | BO49: 48049792 | BP49: 3.1056233e+08 | BQ49: 1.259203e+08 | BR49: 1.1039161e+08 | BS49: 3.5524306e+08 | BT49: 2.1194846e+08 | BU49: 72046398 | BV49: 2.7678339e+08 | BW49: 56085015 | BX49: 11350126 | BY49: 1.2521588e+08 | BZ49: 86391574 | CA49: 6.3727535e+08 | CB49: 2.4123438e+08 | CC49: 1.0672299e+08 | CD49: 1.0934465e+08 | CF49: 5.8118832e+08 | CH49: 1.0005207e+08 | CI49: 86048333 | CN49: 5.1734955e+08 | CO49: 6.2673346e+08 | CP49: 5.3108506e+08 | CQ49: 5.5609743e+08 | CR49: 1.3435956e+09 | CS49: 1.8768325e+09 | CT49: 3.0085994e+09 | CU49: 2.4561784e+09 | CV49: 5.6875969e+09 | CW49: 40747384 | CX49: 1.6817894e+09 | CY49: 19593110 | CZ49: 1.0120328e+09 | DA49: 3.3307078e+08 | DB49: 4.5545443e+08 | DC49: 92625058 | DE49: 66555063 | DF49: 93683762 | DG49: 4.2023937e+09 | DH49: 3.8261407e+09 | DI49: 5.7971749e+10
A50: 46 | E50: 2957.2035 | H50: 44467.745 | I50: 1681509 | J50: 2.9363212e+08 | K50: 86997735 | L50: 21679262 | M50: 7009707.1 | N50: 277569.94 | O50: 286396.53 | R50: 5386780.5 | S50: 6854896.6 | T50: 6961534.3 | U50: 6650030.5 | V50: 7415773.4 | W50: 11679451 | X50: 12122892 | Y50: 3535016.1 | Z50: 20445130 | AA50: 10619517 | AB50: 13695051 | AC50: 1847082.8 | AD50: 10368726 | AE50: 6156163.3 | AF50: 15032239 | AG50: 2.2402077e+08 | AH50: 10148809 | AI50: 27750.707 | AJ50: 1586866.1 | AK50: 793357.1 | AL50: 48610.969 | AM50: 1540443.9 | AN50: 268335.54 | AO50: 106333.01 | AP50: 2640892 | AQ50: 171023.68 | AR50: 21392117 | AV50: 195271.92 | AW50: 8286438.4 | AY50: 601792.99 | AZ50: 24074625 | BA50: 21937116 | BB50: 2195614.7 | BC50: 84785307 | BD50: 2.214664e+08 | BE50: 68554378 | BF50: 94710152 | BG50: 2.5363737e+08 | BH50: 1.5774717e+08 | BI50: 87585076 | BJ50: 27524263 | BK50: 1.2650924e+09 | BL50: 1.3316705e+08 | BN50: 1.0678491e+09 | BO50: 27022278 | BP50: 3.392235e+08 | BQ50: 28892327 | BR50: 82269859 | BS50: 2.4459178e+08 | BT50: 2.364326e+08 | BU50: 81528560 | BV50: 60078914 | BW50: 8.9013998e+08 | BY50: 13152293 | BZ50: 14460851 | CA50: 1.7096051e+08 | CB50: 9038404.4 | CC50: 14416496 | CD50: 69698879 | CF50: 66231245 | CN50: 7.7537518e+08 | CO50: 7.8137777e+08 | CP50: 6.9607075e+08 | CQ50: 7.2718056e+08 | CR50: 1.8259268e+09 | CS50: 2.0179077e+09 | CT50: 3.2623344e+09 | CU50: 2.2795943e+09 | CV50: 5.671584e+09 | CW50: 318734.89 | CX50: 10067820 | CZ50: 8.1561606e+08 | DA50: 2.2944838e+09 | DB50: 32225677 | DH50: 6.1885551e+09 | DI50: 3.4059294e+10
A51: 47 | B51: 2600228.2 | C51: 1541379.6 | E51: 1902.3387 | F51: 4645.2496 | G51: 1.0693958e+08 | H51: 411697.59 | I51: 168980.55 | J51: 1.8694426e+08 | K51: 20341693 | L51: 1818494.9 | M51: 399418.72 | N51: 344650.8 | O51: 44908.583 | R51: 326209.66 | S51: 474742.17 | T51: 253337.42 | U51: 1.0735038e+09 | V51: 9717158.2 | W51: 634573.73 | X51: 382920.63 | Y51: 139371.91 | Z51: 583861.32 | AA51: 236530.95 | AB51: 787279.21 | AC51: 520316.73 | AD51: 201156.05 | AE51: 148490.6 | AF51: 818576.3 | AG51: 3694010.9 | AH51: 351463.3 | AI51: 12935.385 | AJ51: 121869.05 | AK51: 283551.49 | AL51: 45917.881 | AM51: 92580.997 | AN51: 75104.314 | AO51: 121551.16 | AP51: 120998.01 | AQ51: 16185598 | AR51: 1507010.1 | AS51: 1963097.2 | AT51: 14452768 | AU51: 3076360.8 | AV51: 90590.387 | AW51: 310761.72 | AX51: 1211457 | AY51: 2687139.3 | AZ51: 91541.412 | BA51: 91546.8 | BC51: 173218.03 | BD51: 511520.31 | BE51: 157444.01 | BF51: 1184884.7 | BG51: 2792878.2 | BH51: 1181820.1 | BJ51: 500169.51 | BK51: 6148386.1 | BL51: 1302250.3 | BM51: 311604.03 | BN51: 2241803.5 | BO51: 510984.49 | BP51: 5403767.5 | BQ51: 1087963 | BR51: 1406143.8 | BS51: 896776.25 | BT51: 771597.92 | BU51: 491577.76 | BV51: 639984.43 | BW51: 145382.84 | BX51: 35814.536 | BY51: 607340.91 | BZ51: 613912.09 | CA51: 3121896.7 | CB51: 969569.27 | CC51: 437929.65 | CD51: 924551.68 | CF51: 3.8107431e+08 | CH51: 2444472.5 | CI51: 1436955.2 | CN51: 4322027.1 | CO51: 5382169.3 | CP51: 4744583 | CQ51: 5006789.2 | CR51: 12340446 | CS51: 17605946 | CT51: 28389097 | CU51: 23366795 | CV51: 53294380 | CW51: 384454.79 | CX51: 14963393 | CZ51: 59121863 | DA51: 21046871 | DB51: 6698425.6 | DG51: 3.998975e+08 | DH51: 145697.96 | DI51: 2.5331154e+09
A52: 48 | B52: 128596.49 | C52: 386298.37 | D52: 2645.6957 | E52: 20195.688 | F52: 80082.98 | G52: 473852.63 | H52: 7785683.2 | I52: 67266.323 | J52: 2.1610317e+08 | K52: 3763626.9 | L52: 29085143 | M52: 8611156.5 | N52: 31115.881 | O52: 2011596 | P52: 80985.247 | Q52: 4932.5025 | R52: 32445663 | S52: 28237328 | T52: 19098961 | U52: 76889082 | V52: 7154015.2 | W52: 22123854 | X52: 47769079 | Y52: 6862299.8 | Z52: 5950432.9 | AA52: 1812418.8 | AB52: 1222957.4 | AC52: 482919.06 | AD52: 1265438.8 | AE52: 24481803 | AF52: 17465410 | AG52: 1.6212559e+09 | AH52: 54425128 | AI52: 5868488.6 | AJ52: 20316444 | AK52: 29827683 | AL52: 17182761 | AM52: 6763916.7 | AN52: 26978607 | AO52: 48254076 | AP52: 11503599 | AQ52: 1.8237274e+09 | AR52: 36754417 | AS52: 1.7233937e+08 | AT52: 2.556969e+09 | AU52: 77796837 | AV52: 21585630 | AW52: 3.5605656e+08 | AX52: 2.0060074e+08 | AY52: 2.824966e+08 | AZ52: 9197158.3 | BA52: 25209856 | BB52: 311380.62 | BC52: 7933618.4 | BD52: 80700011 | BE52: 97686903 | BF52: 546017.39 | BG52: 1572857 | BH52: 746070.53 | BI52: 189636.38 | BJ52: 40305.275 | BK52: 1919853.5 | BL52: 77866555 | BM52: 1909865.4 | BN52: 5.935989e+08 | BO52: 40454311 | BP52: 38100816 | BQ52: 1.1327435e+08 | BR52: 12302236 | BS52: 53508034 | BT52: 48504207 | BU52: 6881133.7 | BV52: 54924147 | BW52: 10059950 | BX52: 10215885 | BY52: 58103555 | BZ52: 3318527 | CA52: 22720453 | CB52: 8902081.9 | CC52: 15786998 | CD52: 19653233 | CF52: 5.7002199e+08 | CH52: 92114.999 | CI52: 79138.903 | CN52: 38220849 | CO52: 51695444 | CP52: 52506748 | CQ52: 47737032 | CR52: 1.240077e+08 | CS52: 1.7038474e+08 | CT52: 2.8633962e+08 | CU52: 2.3409754e+08 | CV52: 6.3861936e+08 | CW52: 6937608.5 | CX52: 1616087.6 | CY52: 17773.997 | CZ52: 47935200 | DA52: 7257565.7 | DB52: 3319926.9 | DC52: 84025.325 | DE52: 60404.204 | DF52: 85056.531 | DG52: 62475067 | DH52: 4.3087153e+09 | DI52: 1.6001046e+10
A53: 49 | B53: 7522.4235 | C53: 22820.267 | D53: 158.70629 | E53: 6.7584561 | F53: 16.442388 | G53: 2306.5886 | H53: 1732.2679 | I53: 565.73296 | J53: 4593.3055 | K53: 217584.6 | L53: 203532.82 | M53: 35845.35 | N53: 1825.2027 | O53: 1287.4042 | P53: 4856.6394 | Q53: 295.4853 | R53: 15167.072 | S53: 16968.091 | T53: 2646800.1 | U53: 83350.479 | V53: 43453.26 | W53: 112964.9 | X53: 26974.761 | Y53: 23772.715 | Z53: 29160.817 | AA53: 18419.056 | AB53: 72113.508 | AC53: 15381.931 | AD53: 71113.99 | AE53: 8058.0825 | AF53: 17310.466 | AG53: 6.331807e+09 | AH53: 1.2481644e+08 | AI53: 19458840 | AJ53: 45425503 | AK53: 1.6087054e+08 | AL53: 77195214 | AM53: 34240161 | AN53: 1.4884574e+08 | AO53: 1.4260714e+08 | AP53: 59003271 | AQ53: 160861.81 | AR53: 70465.994 | AS53: 51781146 | AT53: 2.5202882e+09 | AU53: 1.2574199e+08 | AV53: 2381492.2 | AW53: 10250611 | AX53: 50568590 | AY53: 1.8699045e+08 | AZ53: 45542900 | BA53: 1.245738e+08 | BB53: 2918.4815 | BC53: 3464673.8 | BD53: 5.7810575e+08 | BE53: 4.7647863e+08 | BF53: 31361549 | BG53: 7.2828432e+08 | BH53: 40107640 | BI53: 7933326.4 | BJ53: 263.3465 | BK53: 14719.11 | BL53: 2.1083959e+08 | BM53: 6.1190099e+08 | BN53: 7.2021023e+08 | BO53: 769900.83 | BP53: 1.7853247e+08 | BQ53: 39710027 | BR53: 67690579 | BS53: 2.3673322e+08 | BT53: 2.3545532e+08 | BU53: 32834746 | BV53: 2.9386917e+08 | BW53: 42151435 | BX53: 25415700 | BY53: 10497594 | BZ53: 7173028.5 | CA53: 1.0711586e+08 | CB53: 24474041 | CC53: 82228120 | CD53: 1.2304467e+08 | CF53: 77578144 | CH53: 5434.4441 | CI53: 4673.5232 | CN53: 4.4670533e+08 | CO53: 3.3285587e+08 | CP53: 1.5742434e+08 | CQ53: 1.0935501e+08 | CR53: 1.5724665e+08 | CS53: 1.1777368e+08 | CT53: 1.0729667e+08 | CU53: 44562545 | CV53: 51099616 | CW53: 2123.6513 | CX53: 416250.28 | CY53: 1066.4006 | CZ53: 89225103 | DA53: 12260813 | DB53: 14239808 | DC53: 5041.3343 | DE53: 3622.4142 | DF53: 5098.9568 | DG53: 1.8689373e+09 | DH53: 3.3920885e+09 | DI53: 2.216182e+10
A54: 50 | B54: 23771469 | C54: 14060117 | G54: 346385.87 | H54: 5426311.2 | J54: 1.2905218e+08 | L54: 4.6540609e+08 | M54: 3.8861395e+08 | N54: 37044810 | O54: 24862333 | P54: 60914830 | Q54: 1308667.1 | R54: 1.6699058e+08 | S54: 3.085752e+08 | T54: 94232895 | U54: 1.7254473e+08 | V54: 3.7994468e+08 | W54: 3.2572273e+08 | X54: 3.2042843e+08 | Y54: 6039284.2 | Z54: 1.0160825e+08 | AA54: 60737064 | AB54: 5.4585071e+08 | AC54: 20194388 | AD54: 53916701 | AE54: 15200558 | AF54: 1.3100134e+08 | AG54: 5.1543774e+09 | AH54: 7.9765313e+08 | AI54: 41371546 | AJ54: 85892891 | AK54: 9.1285177e+08 | AL54: 85765361 | AM54: 3.5727472e+08 | AN54: 5.9229774e+08 | AO54: 3.7408758e+08 | AP54: 6.5976563e+08 | AQ54: 13350241 | AR54: 85899.442 | AS54: 84299926 | AT54: 1.115439e+09 | AU54: 81754250 | AV54: 9950342 | AW54: 20442565 | AX54: 26169198 | AY54: 1.1107967e+09 | AZ54: 34137052 | BA54: 59678000 | BB54: 39277856 | BC54: 21658328 | BD54: 2.5206308e+08 | BE54: 2.0608411e+08 | BI54: 2890555.2 | BK54: 38448105 | BL54: 96871661 | BM54: 63597661 | BN54: 3.3901183e+08 | BO54: 1592225.2 | BP54: 1.9735997e+09 | BQ54: 53495580 | BR54: 24801867 | BS54: 1.6894588e+08 | BT54: 1.4744804e+08 | BU54: 31578235 | BV54: 1.2629538e+08 | BW54: 53627157 | BX54: 16237497 | BY54: 20385427 | BZ54: 17079474 | CA54: 3.454235e+08 | CB54: 66617323 | CC54: 59835538 | CD54: 45472380 | CF54: 33659903 | CH54: 57127233 | CI54: 56376592 | CN54: 1680072.7 | CO54: 2308861.8 | CP54: 1878162.5 | CQ54: 2039381.3 | CR54: 4654296.2 | CS54: 5867029.4 | CT54: 9318081.4 | CU54: 7283339.4 | CV54: 19446110 | CW54: 89017587 | CX54: 1.2330249e+08 | CZ54: 1.3004573e+09 | DA54: 1.6903516e+08 | DB54: 6.3932645e+08 | DG54: 30932496 | DH54: 6.7438078e+09 | DI54: 2.8981092e+10
A55: 51 | B55: 4879809.9 | C55: 4331865.6 | D55: 415.53428 | E55: 743.00775 | F55: 6646.2272 | G55: 10144840 | H55: 499470.76 | I55: 466000.56 | J55: 1.6161658e+08 | K55: 3.7004758e+08 | L55: 59266347 | M55: 15903457 | N55: 1488302.9 | O55: 1152167 | P55: 1399866.1 | Q55: 193640.81 | R55: 19025148 | S55: 22918487 | T55: 16020994 | U55: 10949818 | V55: 43215598 | W55: 14273047 | X55: 32098243 | Y55: 11159805 | Z55: 74577895 | AA55: 68434969 | AB55: 3.6462466e+08 | AC55: 20666760 | AD55: 1.678914e+08 | AE55: 19996156 | AF55: 50592515 | AG55: 1.144925e+09 | AH55: 1.5882217e+08 | AI55: 5659782.7 | AJ55: 22608841 | AK55: 56052832 | AL55: 32995612 | AM55: 30325387 | AN55: 46193618 | AO55: 48637617 | AP55: 63235156 | AQ55: 28438949 | AR55: 8380530.1 | AS55: 766621.96 | AT55: 13592497 | AU55: 17511939 | AV55: 1326299.9 | AW55: 27415572 | AX55: 3386806 | AY55: 35060918 | AZ55: 1.0827262e+10 | BA55: 36151822 | BB55: 33312519 | BC55: 2.436294e+08 | BD55: 8.6405579e+08 | BE55: 8.8696982e+08 | BF55: 5.0991159e+08 | BG55: 5.4086807e+08 | BH55: 2.9776438e+08 | BI55: 1.2100828e+08 | BJ55: 87678004 | BK55: 3.5403732e+08 | BL55: 39351559 | BM55: 2.0409629e+08 | BN55: 3.1791497e+09 | BO55: 1.5095186e+08 | BP55: 1.3107158e+09 | BQ55: 51062014 | BR55: 2.8422413e+08 | BS55: 7.253997e+08 | BT55: 3.3198461e+08 | BU55: 34356449 | BV55: 4.5013402e+08 | BW55: 76664386 | BX55: 5049846.9 | BY55: 57572637 | BZ55: 53723071 | CA55: 3.6625058e+08 | CB55: 63149239 | CC55: 1.1001138e+08 | CD55: 2.7871903e+08 | CF55: 3.5387622e+08 | CH55: 13429809 | CI55: 9968202 | CN55: 1.1292849e+09 | CO55: 1.754759e+09 | CP55: 1.3245254e+09 | CQ55: 1.8935721e+09 | CR55: 3.2956249e+09 | CS55: 4.103137e+09 | CT55: 7.7815677e+09 | CU55: 7.3585436e+09 | CV55: 1.4047113e+10 | CW55: 1.3375582e+08 | CX55: 1.4955789e+08 | CY55: 4.8456171e+08 | CZ55: 2.5402955e+09 | DA55: 1.0086844e+09 | DB55: 1.3376904e+09 | DC55: 1.3910991e+09 | DE55: 4.0741789e+08 | DF55: 32567731 | DG55: 1.0146652e+09 | DH55: 3.8768254e+10 | DI55: 1.1622235e+11
A56: 52 | B56: 7689.3543 | C56: 22709.323 | D56: 12.715788 | E56: 22.787016 | F56: 203.70111 | G56: 238274.02 | H56: 6890.7245 | I56: 4609.7705 | J56: 452960.27 | K56: 1046599.4 | L56: 316850.46 | M56: 101537.56 | N56: 4742.8012 | O56: 3704.85 | P56: 9354.6769 | Q56: 972.88946 | R56: 33520.713 | S56: 35091.183 | T56: 36267.811 | U56: 103345.01 | V56: 160952.42 | W56: 66317.193 | X56: 56943.767 | Y56: 24660.374 | Z56: 282732.85 | AA56: 510982.59 | AB56: 584859.09 | AC56: 47793.067 | AD56: 260603.4 | AE56: 49723.618 | AF56: 158937.6 | AG56: 24217369 | AH56: 27938368 | AI56: 21186.824 | AJ56: 52245.589 | AK56: 35478985 | AL56: 101834.22 | AM56: 214418.19 | AN56: 175943 | AO56: 175654.84 | AP56: 133263.4 | AQ56: 1948120.7 | AR56: 28571.645 | AS56: 22265.699 | AT56: 351663.51 | AU56: 93308.602 | AV56: 4327542.2 | AW56: 769827.41 | AX56: 3876.0414 | AY56: 47593.773 | AZ56: 25288834 | BA56: 1.2801899e+10 | BB56: 3.9536246e+09 | BC56: 2.7276936e+09 | BD56: 5675129.7 | BE56: 2649954.7 | BF56: 2293105.1 | BG56: 8912901 | BH56: 2493668 | BI56: 647923.11 | BJ56: 108001.7 | BK56: 22336298 | BL56: 74079492 | BM56: 233725.52 | BN56: 7.1975967e+08 | BO56: 58455969 | BP56: 12018883 | BQ56: 83318.168 | BR56: 1.08276e+08 | BS56: 10978441 | BT56: 2529373.7 | BU56: 85145009 | BV56: 4.454172e+08 | BW56: 3.8880082e+08 | BX56: 23312.779 | BY56: 5100105.8 | BZ56: 79074264 | CA56: 8.7789263e+08 | CB56: 1122910.1 | CC56: 14068392 | CD56: 1.0981168e+08 | CF56: 998857.62 | CH56: 16016.905 | CI56: 12508.66 | CN56: 1.8469226e+08 | CO56: 2.4728521e+08 | CP56: 2.4027242e+08 | CQ56: 2.5238005e+08 | CR56: 6.521071e+08 | CS56: 9.7710991e+08 | CT56: 1.7724143e+09 | CU56: 1.5579935e+09 | CV56: 3.4008138e+09 | CW56: 75257829 | CX56: 9163962.6 | CY56: 4821596 | CZ56: 84421761 | DA56: 22441746 | DB56: 16750660 | DC56: 3145755.2 | DE56: 65936808 | DF56: 67904989 | DG56: 1.7000771e+10 | DH56: 3.4890933e+10 | DI56: 8.4174872e+10
A57: 53 | B57: 2188960.4 | C57: 6450955.8 | D57: 3737.2183 | E57: 6691.5177 | F57: 59817.489 | G57: 78037664 | H57: 2124734.9 | I57: 1330505.5 | J57: 1.3231534e+08 | K57: 3.0512027e+08 | L57: 92728059 | M57: 29780772 | N57: 1392802 | O57: 1087968.1 | P57: 2747055 | Q57: 285696.39 | R57: 9765035.5 | S57: 10190252 | T57: 10524566 | U57: 30244991 | V57: 47206311 | W57: 19292857 | X57: 16491172 | Y57: 7190731.5 | Z57: 82706397 | AA57: 1.4996727e+08 | AB57: 1.7167098e+08 | AC57: 14034983 | AD57: 76429857 | AE57: 14514333 | AF57: 46401073 | AG57: 1.0069458e+09 | AH57: 1.058544e+08 | AI57: 6013007.3 | AJ57: 15019673 | AK57: 58857341 | AL57: 29898944 | AM57: 11783776 | AN57: 51658869 | AO57: 49610741 | AP57: 39102162 | AQ57: 17466713 | AR57: 8390195.7 | AS57: 6538927.8 | AT57: 25804788 | AU57: 27405461 | AV57: 4317917.7 | AW57: 4780735.5 | AX57: 1138234.9 | AY57: 13957776 | AZ57: 1.8714825e+08 | BA57: 1.7909099e+08 | BB57: 1.0496698e+10 | BC57: 1.8100132e+09 | BD57: 1.9469888e+09 | BE57: 7.7693735e+08 | BF57: 1.625608e+08 | BG57: 4.7448604e+08 | BH57: 1.3380688e+08 | BI57: 1.8986177e+08 | BJ57: 31236102 | BK57: 5.3360146e+08 | BL57: 36841976 | BM57: 68634775 | BN57: 2.8130191e+09 | BO57: 3.6221253e+08 | BP57: 3.6846984e+08 | BQ57: 23938365 | BR57: 74399958 | BS57: 2.6020383e+08 | BT57: 2.7585202e+08 | BU57: 62470362 | BV57: 60481244 | BW57: 1.9190935e+08 | BX57: 6846024.2 | BY57: 86432640 | BZ57: 4.4915827e+08 | CA57: 2.5724086e+08 | CB57: 77567606 | CC57: 1.0585362e+08 | CD57: 1.4383229e+08 | CF57: 2.4307814e+08 | CH57: 4599623.4 | CI57: 3584933.7 | CN57: 1.0974795e+08 | CO57: 1.5473004e+08 | CP57: 1.4879801e+08 | CQ57: 1.5995254e+08 | CR57: 4.04311e+08 | CS57: 5.3502242e+08 | CT57: 9.6818232e+08 | CU57: 7.5891244e+08 | CV57: 1.9833625e+09 | CW57: 50628859 | CX57: 5.3488704e+08 | CY57: 1.4158772e+09 | CZ57: 1.686518e+09 | DA57: 6.4143922e+08 | DB57: 2.2079839e+08 | DC57: 9.2376115e+08 | DE57: 2.3435577e+09 | DF57: 382979.17 | DG57: 5.4855189e+09 | DH57: 2.9722666e+10 | DI57: 7.3994949e+10
A58: 54 | B58: 17621349 | C58: 37239665 | D58: 19793.01 | E58: 1590.7115 | F58: 22257.67 | G58: 8809010.6 | H58: 3666920.2 | I58: 5757927.1 | J58: 80863220 | K58: 6.3698811e+08 | L58: 1.0457534e+08 | M58: 44224530 | N58: 1759435 | O58: 2799618 | P58: 2081145.9 | Q58: 868927.21 | R58: 25338139 | S58: 26789211 | T58: 30415831 | U58: 9615507 | V58: 59769208 | W58: 27375581 | X58: 66412332 | Y58: 10588200 | Z58: 98890307 | AA58: 61387923 | AB58: 1.4524505e+08 | AC58: 19826762 | AD58: 99114847 | AE58: 15766200 | AF58: 60356272 | AG58: 1.1306148e+09 | AH58: 98067862 | AI58: 7193653.9 | AJ58: 26022859 | AK58: 53753359 | AL58: 50623786 | AM58: 32595044 | AN58: 65547872 | AO58: 59345096 | AP58: 30639809 | AQ58: 57871062 | AR58: 4518999.7 | AS58: 4814732.1 | AT58: 1.1207748e+08 | AU58: 1.5977436e+08 | AV58: 9616543.2 | AW58: 23276889 | AX58: 4170689.1 | AY58: 36786370 | AZ58: 1.7478219e+08 | BA58: 1.2550859e+08 | BB58: 72501543 | BC58: 3.1328508e+09 | BD58: 5.055136e+08 | BE58: 1.4656168e+09 | BF58: 1.3083205e+08 | BG58: 4.4164793e+08 | BH58: 4.827587e+08 | BI58: 1.5125081e+08 | BJ58: 60708609 | BK58: 8.5772868e+08 | BL58: 1.8753642e+08 | BM58: 27505591 | BN58: 1.4859032e+09 | BO58: 1.5043303e+08 | BP58: 8.9891449e+08 | BQ58: 97989639 | BR58: 2.7760694e+08 | BS58: 7.0670657e+08 | BT58: 1.5074883e+08 | BU58: 1.0200045e+08 | BV58: 1.295205e+08 | BW58: 1.5571595e+08 | BX58: 5680250.6 | BY58: 1.1879739e+08 | BZ58: 87947583 | CA58: 5.6486631e+08 | CB58: 1.8133808e+08 | CC58: 2.1291907e+08 | CD58: 2.0867863e+08 | CF58: 3.4109185e+08 | CH58: 7701012.1 | CI58: 14962641 | CN58: 1.1800146e+09 | CO58: 1.5654003e+09 | CP58: 1.3210489e+09 | CQ58: 1.4559887e+09 | CR58: 3.1967974e+09 | CS58: 3.9557803e+09 | CT58: 6.0836908e+09 | CU58: 4.0852606e+09 | CV58: 7.0301284e+09 | CW58: 2.2076354e+08 | CX58: 1.0115029e+09 | CY58: 16192709 | CZ58: 5.5861998e+09 | DA58: 1.5795722e+09 | DB58: 3.7182396e+09 | DC58: 10564614 | DE58: 2.8483742e+09 | DG58: 1.0367336e+09 | DH58: 4.2728716e+08 | DI58: 6.3717306e+10
A59: 55 | B59: 203442.98 | C59: 241000.87 | D59: 98.138542 | E59: 97.159915 | F59: 917.26582 | G59: 4721522.1 | H59: 717580.44 | I59: 351642.78 | J59: 2.9114052e+08 | K59: 4.6369777e+08 | L59: 2.7864349e+08 | M59: 76055378 | N59: 8100329.8 | O59: 6267043.3 | P59: 6624770.4 | Q59: 1013786.9 | R59: 85846131 | S59: 1.2228243e+08 | T59: 44135859 | U59: 33445250 | V59: 1.3920404e+08 | W59: 66981385 | X59: 1.8268646e+08 | Y59: 52942090 | Z59: 3.1404668e+08 | AA59: 2.7151004e+08 | AB59: 2.4486315e+08 | AC59: 1.1530247e+08 | AD59: 4.9957392e+08 | AE59: 96587649 | AF59: 2.1519691e+08 | AG59: 8.5166139e+08 | AH59: 4.9295238e+08 | AI59: 16987842 | AJ59: 69636687 | AK59: 2.1953548e+08 | AL59: 1.0832157e+08 | AM59: 1.2805186e+08 | AN59: 1.7355951e+08 | AO59: 1.484104e+08 | AP59: 1.1139002e+08 | AQ59: 1.345371e+08 | AR59: 422483.94 | AS59: 237383.4 | AT59: 27840847 | AU59: 56118708 | AV59: 5164794.8 | AW59: 32463039 | AX59: 18772147 | AY59: 35149539 | AZ59: 7.2734765e+08 | BA59: 41326852 | BB59: 74674607 | BC59: 5.5685858e+08 | BD59: 1.0477354e+09 | BE59: 9.5910459e+08 | BF59: 2.6119674e+09 | BG59: 1.1253591e+09 | BH59: 1.1636397e+09 | BI59: 1.6857629e+08 | BJ59: 4.055136e+08 | BK59: 3.3091418e+08 | BL59: 77291548 | BM59: 15850171 | BN59: 3.7555507e+09 | BO59: 1.5114496e+08 | BP59: 4.6160854e+09 | BQ59: 2.5916123e+08 | BR59: 1.9402908e+08 | BS59: 3.0427829e+08 | BT59: 3.28704e+08 | BU59: 29889701 | BV59: 1.4176173e+08 | BW59: 2.3235522e+08 | BX59: 5254672.8 | BY59: 1.6616147e+08 | BZ59: 1.247027e+08 | CA59: 1.8527238e+09 | CB59: 1.689609e+08 | CC59: 2.1314699e+08 | CD59: 1.0862373e+09 | CF59: 8.9317985e+08 | CH59: 506958.37 | CI59: 379462.9 | CN59: 3.5077973e+08 | CO59: 5.0879719e+08 | CP59: 4.7222476e+08 | CQ59: 6.0726852e+08 | CR59: 1.2376357e+09 | CS59: 1.6857448e+09 | CT59: 3.1275687e+09 | CU59: 2.6247566e+09 | CV59: 5.1687379e+09 | CW59: 3.1256024e+08 | CX59: 6.3803506e+08 | CY59: 30478320 | CZ59: 8.222728e+09 | DA59: 3.3198975e+08 | DB59: 4.2981381e+09 | DC59: 53689140 | DE59: 38023560 | DF59: 1024157.7 | DG59: 4.8367579e+08 | DH59: 2.8760903e+10 | DI59: 8.903873e+10
A60: 56 | B60: 7276688.9 | C60: 21046069 | D60: 12099.405 | E60: 21682.441 | F60: 193826.93 | G60: 2.2689736e+08 | H60: 6567562.5 | I60: 4579140.2 | J60: 4.390214e+08 | K60: 1.0027173e+09 | L60: 3.0240086e+08 | M60: 96996819 | N60: 4565815.2 | O60: 3566197.8 | P60: 8943904.2 | Q60: 932156.23 | R60: 32352206 | S60: 33881214 | T60: 34690226 | U60: 98299666 | V60: 1.5446132e+08 | W60: 62992762 | X60: 54632264 | Y60: 23708488 | Z60: 2.7057899e+08 | AA60: 4.8799226e+08 | AB60: 5.699613e+08 | AC60: 46234781 | AD60: 2.5397326e+08 | AE60: 47760035 | AF60: 1.5215281e+08 | AG60: 3.3160687e+09 | AH60: 4.0374045e+08 | AI60: 21143858 | AJ60: 54260891 | AK60: 2.3310789e+08 | AL60: 1.1110131e+08 | AM60: 56066558 | AN60: 1.8636575e+08 | AO60: 1.7551796e+08 | AP60: 2.1484929e+08 | AQ60: 58447924 | AR60: 27482308 | AS60: 21186394 | AT60: 86809318 | AU60: 89353937 | AV60: 13944906 | AW60: 19790701 | AX60: 3817398.9 | AY60: 46996691 | AZ60: 1.128313e+09 | BA60: 3.6488845e+08 | BB60: 2.4449755e+08 | BC60: 6.9196662e+08 | BD60: 1.0268205e+09 | BE60: 9.4301059e+09 | BF60: 5.5640335e+08 | BG60: 1.587324e+09 | BH60: 4.4920693e+08 | BI60: 7.770915e+08 | BJ60: 2.3853063e+08 | BK60: 1.7934041e+09 | BL60: 1.6554761e+08 | BM60: 4.0157329e+08 | BN60: 1.1036453e+10 | BO60: 1.2931517e+09 | BP60: 2.3192649e+09 | BQ60: 1.2893684e+08 | BR60: 1.9108597e+09 | BS60: 1.0230644e+09 | BT60: 1.0365775e+09 | BU60: 2.3206329e+08 | BV60: 4.1486171e+08 | BW60: 7.5984631e+08 | BX60: 26182392 | BY60: 3.5246324e+08 | BZ60: 2.501028e+08 | CA60: 1.463336e+09 | CB60: 2.9817248e+08 | CC60: 1.6247448e+09 | CD60: 6.1214994e+08 | CF60: 1.237677e+09 | CH60: 15416846 | CI60: 11995997 | CN60: 3.6274667e+08 | CO60: 5.5294334e+08 | CP60: 4.1068036e+08 | CQ60: 4.9757033e+08 | CR60: 1.158865e+09 | CS60: 1.3938274e+09 | CT60: 2.472554e+09 | CU60: 2.2572912e+09 | CV60: 5.1346577e+09 | CW60: 1.0879143e+08 | CX60: 1.1012739e+09 | CY60: 4.6008812e+09 | CZ60: 3.2843795e+09 | DA60: 4.5889672e+08 | DB60: 9.4711152e+08 | DC60: 3.0444444e+09 | DE60: 7.1646567e+09 | DF60: 1293377.7 | DG60: 2.0187488e+10 | DH60: 6.513305e+10 | DI60: 1.7476586e+11
A61: 57 | B61: 18407846 | C61: 16969863 | D61: 40933.6 | E61: 8729.9225 | F61: 62840.359 | G61: 28915185 | H61: 11243574 | I61: 10797744 | J61: 76638552 | K61: 6.797383e+08 | L61: 88085975 | M61: 35963032 | N61: 1502132.8 | O61: 1209290.2 | P61: 41904364 | Q61: 26949392 | R61: 10644097 | S61: 15052127 | T61: 12252890 | U61: 32615298 | V61: 51713742 | W61: 19690259 | X61: 25270345 | Y61: 10814178 | Z61: 37815389 | AA61: 23510729 | AB61: 70474483 | AC61: 15327420 | AD61: 67271198 | AE61: 11933706 | AF61: 27159178 | AG61: 2.0595148e+09 | AH61: 60556155 | AI61: 6852710.3 | AJ61: 15677548 | AK61: 83366506 | AL61: 47139327 | AM61: 43056938 | AN61: 88406943 | AO61: 64058791 | AP61: 76935512 | AQ61: 2.7208703e+08 | AR61: 2.2300648e+08 | AS61: 92138045 | AT61: 1.9130657e+08 | AU61: 4.8993495e+08 | AV61: 3979204.5 | AW61: 24503897 | AX61: 4529700.5 | AY61: 1.0794239e+08 | AZ61: 19015235 | BA61: 76677038 | BB61: 86897422 | BC61: 99217387 | BD61: 57285289 | BE61: 2.7095918e+08 | BF61: 7.2225808e+08 | BG61: 1.9659222e+09 | BH61: 1.0032171e+09 | BI61: 35688438 | BJ61: 38379748 | BK61: 1.1415001e+10 | BL61: 3.0461842e+08 | BM61: 1.0513151e+09 | BN61: 6.9621358e+08 | BO61: 9.7788092e+08 | BP61: 3.0327753e+08 | BQ61: 49939698 | BR61: 57332539 | BS61: 2.1477465e+08 | BT61: 1.3431828e+08 | BU61: 32903795 | BV61: 59408803 | BW61: 69788926 | BX61: 3716202 | BY61: 1.4787001e+08 | BZ61: 78324312 | CA61: 5.8858662e+08 | CB61: 64446867 | CC61: 75993604 | CD61: 8.8551679e+08 | CF61: 5.1295039e+08 | CH61: 28984787 | CI61: 18241843 | CN61: 2.5057174e+08 | CO61: 3.9542265e+08 | CP61: 1.6401359e+08 | CQ61: 2.6861596e+08 | CR61: 8.4758628e+08 | CS61: 8.4668799e+08 | CT61: 1.4338252e+09 | CU61: 7.8247375e+08 | CV61: 2.2167298e+09 | CW61: 2884253 | CX61: 9043531.3 | CZ61: 1.4040442e+09 | DA61: 16180998 | DB61: 4.3730198e+08 | DG61: 1.83795e+09 | DH61: 18738136 | DI61: 3.8503968e+10
A62: 58 | B62: 6285220.4 | C62: 13083168 | D62: 613.31317 | E62: 19939.29 | F62: 36006.43 | G62: 3406542.5 | H62: 22163006 | I62: 1.3843301e+08 | J62: 84499027 | K62: 2.3710815e+08 | L62: 20764757 | M62: 7166267.6 | N62: 266810.52 | O62: 273960.99 | P62: 292437.03 | Q62: 57390.292 | R62: 3247768.2 | S62: 2310347.2 | T62: 3525653 | U62: 5331938.4 | V62: 7021490.5 | W62: 7961178.5 | X62: 9207181.3 | Y62: 84669029 | Z62: 2.5346602e+08 | AA62: 1.7688096e+08 | AB62: 1.0796755e+08 | AC62: 75837691 | AD62: 1.8352436e+08 | AE62: 74953400 | AF62: 1.9318531e+08 | AG62: 7.0888992e+08 | AH62: 14157939 | AI62: 1747428.9 | AJ62: 3829406.8 | AK62: 23929595 | AL62: 12488673 | AM62: 13843457 | AN62: 25167391 | AO62: 16502729 | AP62: 19010277 | AQ62: 2.5788207e+08 | AR62: 44121544 | AS62: 54718185 | AT62: 66175783 | AU62: 6.2399477e+08 | AV62: 7931742.6 | AW62: 67632171 | AX62: 732920.16 | AY62: 5719618.6 | AZ62: 20204337 | BA62: 1.0679268e+08 | BB62: 16245507 | BC62: 19613945 | BD62: 26424663 | BE62: 10832704 | BF62: 1.4123685e+09 | BG62: 6.2462605e+09 | BH62: 1.8992917e+09 | BI62: 2.8077271e+08 | BJ62: 1.320576e+10 | BK62: 2.731313e+09 | BL62: 71521830 | BM62: 7.8253627e+08 | BN62: 5.8897442e+08 | BO62: 1.1178934e+09 | BP62: 1.6425556e+08 | BQ62: 6481767.4 | BR62: 48683390 | BS62: 2.3322334e+08 | BT62: 7.064232e+08 | BU62: 45146157 | BV62: 4.1120595e+08 | BW62: 2.8792895e+08 | BX62: 1563415.9 | BY62: 22951939 | BZ62: 22064302 | CA62: 1.6112555e+09 | CB62: 16453684 | CC62: 16317778 | CD62: 8.8712593e+08 | CF62: 9.4956358e+08 | CH62: 5504183 | CI62: 5143588.9 | CN62: 1.5025983e+08 | CO62: 4.5865723e+08 | CP62: 5.8902611e+08 | CQ62: 4.8583391e+08 | CR62: 1.959943e+09 | CS62: 2.8968786e+09 | CT62: 6.6288239e+09 | CU62: 4.8820869e+09 | CV62: 3.8449924e+10 | CW62: 231801.45 | CZ62: 3.7790381e+08 | DA62: 361906.89 | DB62: 29750105 | DE62: 16225.781 | DG62: 1.0352608e+10 | DH62: 1.1612234e+08 | DI62: 1.0504795e+11
A63: 59 | B63: 54657661 | C63: 69641367 | D63: 377227.84 | E63: 49439.02 | F63: 265163.75 | G63: 56045109 | H63: 13693152 | I63: 9576623.9 | J63: 9.4829107e+08 | K63: 7.3780885e+08 | L63: 2.2339398e+08 | M63: 60745420 | N63: 5567671.1 | O63: 4854875.4 | P63: 35751292 | Q63: 4468395.9 | R63: 33629599 | S63: 57972608 | T63: 38533459 | U63: 1.4156055e+08 | V63: 2.7743629e+08 | W63: 82893817 | X63: 55272657 | Y63: 31971801 | Z63: 1.3884767e+08 | AA63: 87691294 | AB63: 5.0339843e+08 | AC63: 80743455 | AD63: 2.7829134e+08 | AE63: 29634124 | AF63: 2.0604206e+08 | AG63: 1.5562337e+09 | AH63: 1.6366428e+08 | AI63: 5745056.3 | AJ63: 21618268 | AK63: 86397068 | AL63: 28382486 | AM63: 30340215 | AN63: 47373875 | AO63: 52009488 | AP63: 97613955 | AQ63: 99000668 | AR63: 61926407 | AS63: 49482263 | AT63: 1.779575e+08 | AU63: 4.05223e+08 | AV63: 84919540 | AW63: 29638746 | AX63: 11550703 | AY63: 20524059 | AZ63: 3.3162808e+08 | BA63: 4.6668521e+08 | BB63: 6.5933293e+08 | BC63: 6.8197403e+08 | BD63: 3.1681033e+08 | BE63: 4.7030323e+08 | BF63: 9.9686415e+08 | BG63: 3.5125248e+09 | BH63: 1.8171341e+09 | BI63: 70275250 | BJ63: 6.4673845e+08 | BK63: 1.3964922e+10 | BL63: 2.2665893e+08 | BM63: 1.2321543e+09 | BN63: 2.1129028e+09 | BO63: 8.1042259e+08 | BP63: 5.2623593e+08 | BQ63: 1.0059411e+08 | BR63: 1.4262083e+08 | BS63: 5.4994966e+08 | BT63: 2.9523827e+08 | BU63: 66657204 | BV63: 1.8028141e+08 | BW63: 1.7228127e+08 | BX63: 5016960 | BY63: 1.3548986e+08 | BZ63: 3.5256741e+08 | CA63: 4.4992539e+08 | CB63: 1.0398657e+08 | CC63: 2.3390761e+08 | CD63: 3.0405984e+08 | CF63: 1.2323598e+08 | CH63: 65663691 | CI63: 93597673 | CN63: 1.7857979e+09 | CO63: 2.6475738e+09 | CP63: 1.6967634e+09 | CQ63: 1.996708e+09 | CR63: 4.3278046e+09 | CS63: 4.5521835e+09 | CT63: 5.7090185e+09 | CU63: 2.6451882e+09 | CV63: 6.81899e+09 | CW63: 70460929 | CX63: 98949.553 | CZ63: 1.115063e+09 | DA63: 177043.95 | DB63: 13752526 | DG63: 2.7290599e+09 | DH63: 4616376.5 | DI63: 7.5630605e+10
A64: 60 | B64: 1.9847669e+08 | C64: 66637624 | D64: 32261.013 | E64: 291531.76 | F64: 431107.38 | G64: 75708091 | H64: 28275634 | I64: 35435039 | J64: 1.2092209e+08 | K64: 52852291 | L64: 3.1465888e+08 | M64: 2.5542844e+08 | N64: 12302324 | O64: 8195091.9 | P64: 17938114 | Q64: 2752879.5 | R64: 19706604 | S64: 15988711 | T64: 5948797.2 | U64: 15742671 | V64: 2.6504212e+08 | W64: 67983753 | X64: 97025208 | Y64: 35487062 | Z64: 80595710 | AA64: 1.2562234e+08 | AB64: 3.9105371e+08 | AC64: 1.1860436e+08 | AD64: 3.3587498e+08 | AE64: 48667660 | AF64: 1.0246707e+08 | AG64: 4.1458156e+09 | AH64: 1.9421345e+08 | AI64: 13737035 | AJ64: 40128419 | AK64: 1.1009127e+08 | AL64: 68717363 | AM64: 47406404 | AN64: 96790704 | AO64: 1.2987368e+08 | AP64: 1.027512e+08 | AQ64: 62432232 | AR64: 1991612.3 | AS64: 48942842 | AT64: 1.3166936e+09 | AU64: 1.4166209e+09 | AV64: 24386449 | AW64: 94625918 | AX64: 12431979 | AY64: 2.2638183e+08 | AZ64: 28527606 | BA64: 2.9727821e+08 | BB64: 1471305.2 | BC64: 2.0638671e+08 | BD64: 89396383 | BE64: 1.6245785e+08 | BF64: 2.2123451e+08 | BG64: 1.3623369e+09 | BH64: 40535449 | BI64: 2.5047507e+10 | BJ64: 1.0652223e+09 | BK64: 8.6269943e+09 | BL64: 5.543372e+08 | BM64: 9.8641913e+08 | BN64: 2.0073443e+09 | BO64: 31088905 | BP64: 7.2628853e+08 | BQ64: 1.3669541e+08 | BR64: 4.2062164e+08 | BS64: 1.2345792e+09 | BT64: 9.2497412e+08 | BU64: 2.7168046e+08 | BV64: 1.9553081e+09 | BW64: 2.2462527e+08 | BX64: 1.0772259e+08 | BY64: 1.6930288e+08 | BZ64: 1.1536968e+08 | CA64: 8.4006011e+08 | CB64: 1.1996929e+08 | CC64: 1.9980647e+08 | CD64: 2.4517871e+08 | CF64: 2.7421635e+09 | CH64: 1.3292265e+08 | CI64: 1.9156211e+08 | CN64: 1.0271764e+09 | CO64: 1.5424335e+09 | CP64: 1.3495676e+09 | CQ64: 1.3818794e+09 | CR64: 3.3442828e+09 | CS64: 4.3395511e+09 | CT64: 7.1425814e+09 | CU64: 5.2203626e+09 | CV64: 1.2472832e+10 | CW64: 26995981 | CZ64: 1.1816739e+08 | DA64: 64763678 | DB64: 4.626658e+08 | DE64: 2903623.3 | DG64: 1.372687e+09 | DH64: 2090790 | DI64: 1.0242849e+11
A65: 61 | BI65: 3.6909353e+08 | BJ65: 8.009346e+08 | BO65: 8347334.2 | CN65: 1.3013592e+09 | CO65: 1.3981091e+09 | CP65: 1.0408667e+09 | CQ65: 1.0843018e+09 | CR65: 2.4795448e+09 | CS65: 2.36162e+09 | CT65: 4.4986949e+09 | CU65: 3.7642429e+09 | CV65: 9.6350977e+09 | DH65: 3346934.1 | DI65: 2.874556e+10
A66: 62 | B66: 1.0631581e+08 | C66: 1.7485197e+08 | D66: 101459.66 | E66: 9088.5296 | F66: 9232.0982 | G66: 55662836 | H66: 7676431.9 | I66: 10896499 | J66: 6.9534238e+08 | K66: 2.1194708e+09 | L66: 4.8868895e+08 | M66: 2.7016367e+08 | N66: 10215192 | O66: 21071511 | P66: 19754467 | Q66: 399514.6 | R66: 67470816 | S66: 1.7908665e+08 | T66: 1.6645197e+08 | U66: 4107346.6 | V66: 98125802 | W66: 2.0684484e+08 | X66: 98827687 | Y66: 28638347 | Z66: 5.6717428e+08 | AA66: 1.1178699e+08 | AB66: 29162069 | AC66: 1.145545e+08 | AD66: 57145907 | AE66: 1.0272072e+08 | AF66: 1.2749097e+08 | AG66: 1.0066759e+10 | AH66: 9.5089026e+08 | AI66: 2.0583313e+08 | AJ66: 3.2387562e+08 | AK66: 2.0365559e+09 | AL66: 1.4613227e+09 | AM66: 4.5027381e+08 | AN66: 2.8450908e+09 | AO66: 1.964449e+09 | AP66: 1.28815e+09 | AQ66: 29177207 | AR66: 7976603.6 | AS66: 63724729 | AT66: 8.8125917e+08 | AU66: 5.624999e+08 | AV66: 23555718 | AW66: 1.8116873e+08 | AX66: 66735749 | AY66: 1.0233663e+09 | AZ66: 5.6153633e+08 | BA66: 1.0607434e+09 | BB66: 2.7772532e+08 | BC66: 2.0437955e+09 | BD66: 1.82531e+09 | BE66: 1.282976e+09 | BF66: 5.1279198e+08 | BG66: 4.0530844e+09 | BH66: 1.438897e+09 | BI66: 1.7283189e+09 | BJ66: 67451395 | BK66: 3.5572113e+10 | BL66: 1.2114176e+09 | BM66: 6.0871554e+08 | BN66: 2.612764e+10 | BO66: 3.6062318e+09 | BP66: 3.731628e+09 | BQ66: 3.5562062e+08 | BR66: 2.9684571e+09 | BS66: 7.9877036e+09 | BT66: 5.9657132e+09 | BU66: 3.4102698e+09 | BV66: 3.4153958e+09 | BW66: 2.5561912e+09 | BX66: 2.8649469e+08 | BY66: 1.8791872e+09 | BZ66: 6.4641159e+08 | CA66: 8.6956693e+09 | CB66: 2.8174142e+09 | CC66: 4.3071419e+09 | CD66: 3.0825071e+09 | CF66: 7.6232975e+08 | CH66: 1.2203507e+08 | CI66: 62722371 | CN66: 1.5505531e+10 | CO66: 2.7882318e+10 | CP66: 1.2245509e+10 | CQ66: 1.7474526e+10 | CR66: 3.8303333e+10 | CS66: 4.6184133e+10 | CT66: 6.3198024e+10 | CU66: 4.6323477e+10 | CV66: 1.4373177e+11 | CW66: 2.6757359e+08 | CX66: 64175921 | CZ66: 2.6558504e+09 | DA66: 1.216159e+08 | DB66: 2.7139773e+08 | DE66: 6.3854661e+10 | DG66: 4.4387943e+08 | DH66: 5.2585328e+10 | DI66: 6.9651763e+11
A67: 63 | B67: 61398754 | C67: 62614196 | D67: 143432.07 | E67: 0.99884285 | F67: 169278.38 | G67: 1.0174489e+08 | H67: 37231035 | I67: 39801101 | J67: 1.2136588e+08 | K67: 2.732022e+09 | L67: 1.5172538e+08 | M67: 38802680 | N67: 916586.83 | O67: 1353779.4 | P67: 1.8207379e+08 | Q67: 1.2169858e+08 | R67: 16057976 | S67: 28506692 | T67: 21238533 | U67: 83001056 | V67: 77543519 | W67: 27851457 | X67: 46746622 | Y67: 14865187 | Z67: 72966071 | AA67: 23195500 | AB67: 45048452 | AC67: 12855823 | AD67: 1.3608674e+08 | AE67: 13309121 | AF67: 19067341 | AG67: 9.1813986e+08 | AH67: 29067693 | AI67: 1966712.8 | AJ67: 19189766 | AK67: 23899838 | AL67: 27459824 | AM67: 12742891 | AN67: 13635059 | AO67: 16396088 | AP67: 22343793 | AQ67: 1.1835482e+09 | AR67: 2.6149621e+08 | AS67: 3.7857993e+08 | AT67: 7.9540735e+08 | AU67: 1.8361202e+08 | AV67: 6099295.7 | AW67: 73256912 | AX67: 17115898 | AY67: 4.6241542e+08 | AZ67: 25053047 | BA67: 1.8816722e+08 | BB67: 3.2116148e+08 | BC67: 2.719901e+08 | BD67: 1.5492576e+08 | BE67: 1.1525758e+09 | BF67: 49215034 | BG67: 1.8281748e+08 | BH67: 1.1355055e+08 | BI67: 1.5438451e+08 | BJ67: 2763973 | BK67: 8.1535171e+08 | BL67: 6.8312188e+08 | BM67: 4.0355395e+08 | BN67: 9.5073714e+08 | BO67: 2.1969134e+08 | BP67: 5.3507508e+08 | BQ67: 2.0988031e+08 | BR67: 95938635 | BS67: 3.2694337e+08 | BT67: 2.5597633e+08 | BU67: 51793053 | BV67: 53589228 | BW67: 2.0726373e+08 | BX67: 6052969.3 | BY67: 2.8322952e+08 | BZ67: 67230439 | CA67: 85804807 | CB67: 1.1785785e+08 | CC67: 1.3348323e+08 | CD67: 38904020 | CF67: 64823317 | CH67: 1.1018388e+08 | CI67: 60060675 | CN67: 1.9064179e+08 | CO67: 2.6822789e+08 | CP67: 2.7316793e+08 | CQ67: 2.9055829e+08 | CR67: 7.9067919e+08 | CS67: 1.07238e+09 | CT67: 2.1824966e+09 | CU67: 1.9844643e+09 | CV67: 4.9786022e+09 | CW67: 4959068.1 | CX67: 41512301 | CZ67: 1.6462278e+08 | DA67: 74275986 | DB67: 9.1623364e+08 | DE67: 7017721.7 | DG67: 5.7888196e+08 | DH67: 55596084 | DI67: 3.1005243e+10
A68: 64 | B68: 6593814.8 | C68: 2724.2309 | E68: 3.8061146 | F68: 56761.041 | G68: 12025928 | H68: 6039239.1 | I68: 24413933 | J68: 61176618 | K68: 2.4075884e+08 | L68: 1.8652784e+08 | M68: 4.2666285e+08 | N68: 4282734.1 | O68: 28.919906 | P68: 21548151 | Q68: 867588.59 | R68: 8871412.3 | S68: 65274934 | T68: 26087695 | U68: 74955977 | V68: 3.8409364e+08 | W68: 64204495 | X68: 63374400 | Y68: 27904599 | Z68: 2.1860438e+08 | AA68: 1.5806975e+08 | AB68: 5.6920648e+08 | AC68: 1.1647368e+08 | AD68: 2.3125104e+08 | AE68: 10151787 | AF68: 2.5475336e+08 | AG68: 4.4070573e+09 | AH68: 45266402 | AI68: 6818687.3 | AJ68: 1.4989859e+08 | AK68: 1.4475941e+08 | AL68: 38222406 | AM68: 30757935 | AN68: 1.0875266e+08 | AO68: 61747030 | AP68: 4.1943142e+08 | AQ68: 84875547 | AR68: 4075285.9 | AS68: 573824.03 | AT68: 2.8505837e+08 | AU68: 123662.36 | AV68: 1672.1066 | AW68: 4408910.7 | AX68: 129.56539 | AY68: 15989752 | AZ68: 1.9906714e+08 | BA68: 48728944 | BB68: 2.9743474e+08 | BC68: 3.5544034e+08 | BD68: 2.9629845e+09 | BE68: 1.9115988e+08 | BF68: 1.0144918e+08 | BG68: 1.5369743e+09 | BH68: 96710256 | BI68: 1.9337045e+08 | BJ68: 2886642.6 | BK68: 5.9096316e+08 | BL68: 1.9138261e+08 | BM68: 1.7521975e+09 | BN68: 3.6025626e+09 | BO68: 3.2936917e+09 | BP68: 5.8321714e+08 | BQ68: 93047978 | BR68: 83641245 | BS68: 3.1235019e+08 | BT68: 48646961 | BU68: 312698 | BV68: 89997357 | BW68: 4.5938743e+08 | BX68: 273634.01 | BY68: 80253491 | BZ68: 1.1177304e+08 | CA68: 3.0525967e+09 | CB68: 9288668.8 | CC68: 45068013 | CD68: 6388846 | CF68: 1.8676131e+08 | CH68: 18667078 | CI68: 13388438 | CN68: 27072.099 | CO68: 91030.054 | CP68: 125236.66 | CQ68: 100216.77 | CR68: 409406.01 | CS68: 614776.43 | CT68: 1419481.8 | CU68: 1053776.9 | CV68: 8369573.7 | CZ68: 48721.543 | DG68: 1.9406846e+10 | DH68: 3.0924108e+09 | DI68: 5.2195634e+10
A69: 65 | B69: 44802511 | C69: 1.3176363e+08 | D69: 76233.543 | E69: 136594.03 | F69: 1221109.3 | G69: 1.4282691e+09 | H69: 41324062 | I69: 27189544 | J69: 2.7038827e+09 | K69: 6.2347684e+09 | L69: 1.8932549e+09 | M69: 6.0797786e+08 | N69: 28439786 | O69: 22211635 | P69: 56297060 | Q69: 5832470.1 | R69: 1.994608e+08 | S69: 2.081402e+08 | T69: 2.1523343e+08 | U69: 6.1772473e+08 | V69: 9.6423213e+08 | W69: 3.9396313e+08 | X69: 3.3673306e+08 | Y69: 1.4699773e+08 | Z69: 1.6894599e+09 | AA69: 3.0614574e+09 | AB69: 3.5114947e+09 | AC69: 2.8655743e+08 | AD69: 1.5634758e+09 | AE69: 2.9635456e+08 | AF69: 9.4766069e+08 | AG69: 2.0577775e+10 | AH69: 2.1592906e+09 | AI69: 1.2281043e+08 | AJ69: 3.0688638e+08 | AK69: 1.1978618e+09 | AL69: 6.1073645e+08 | AM69: 2.4079474e+08 | AN69: 1.0549262e+09 | AO69: 1.0132719e+09 | AP69: 7.9937623e+08 | AQ69: 3.5693704e+08 | AR69: 1.7145993e+08 | AS69: 1.3392501e+08 | AT69: 5.2799368e+08 | AU69: 5.6117805e+08 | AV69: 87758248 | AW69: 98205806 | AX69: 23295934 | AY69: 2.8607799e+08 | AZ69: 4.0382374e+09 | BA69: 2.1826148e+09 | BB69: 1.5286151e+09 | BC69: 3.684929e+09 | BD69: 5.2813799e+09 | BE69: 1.5876637e+10 | BF69: 3.3199794e+09 | BG69: 9.6926585e+09 | BH69: 2.7336591e+09 | BI69: 3.8776127e+09 | BJ69: 6.3795716e+08 | BK69: 1.0913978e+10 | BL69: 7.4431977e+08 | BM69: 1.4098307e+09 | BN69: 5.6521384e+10 | BO69: 7.3902058e+09 | BP69: 7.5371971e+09 | BQ69: 4.8917962e+08 | BR69: 1.5119657e+09 | BS69: 5.3271673e+09 | BT69: 5.6387937e+09 | BU69: 1.266793e+09 | BV69: 1.1926606e+09 | BW69: 3.8746033e+09 | BX69: 1.3984832e+08 | BY69: 1.7645922e+09 | BZ69: 1.2139462e+09 | CA69: 5.1519431e+09 | CB69: 1.5848685e+09 | CC69: 2.1609774e+09 | CD69: 2.9261218e+09 | CF69: 4.9608223e+09 | CH69: 94199172 | CI69: 73421094 | CN69: 1.1042497e+09 | CO69: 1.5333265e+09 | CP69: 1.3644772e+09 | CQ69: 1.3206451e+09 | CR69: 3.2478293e+09 | CS69: 3.8471133e+09 | CT69: 7.3792896e+09 | CU69: 5.8830814e+09 | CV69: 1.6832974e+10 | CW69: 6.5204114e+08 | CX69: 6.2519235e+09 | CY69: 2.8907303e+10 | CZ69: 1.5881167e+10 | DA69: 1.7092368e+09 | DB69: 4.5184585e+09 | DC69: 1.8881913e+10 | DE69: 4.5095366e+10 | DF69: 663917.57 | DG69: 1.0990535e+11 | DH69: 1.7624371e+11 | DI69: 6.8530018e+11
A70: 66 | G70: 9.5481046e+08 | H70: 1.4695839e+08 | I70: 79362674 | K70: 1.8138788e+09 | L70: 3.5059283e+09 | M70: 3.8710696e+08 | N70: 56853627 | O70: 5608732.8 | P70: 1.070094e+08 | Q70: 3003525.8 | R70: 47961219 | S70: 1.2818221e+08 | T70: 39275589 | U70: 4.406922e+08 | V70: 3.3889341e+09 | W70: 1.5444366e+08 | X70: 3.2281107e+08 | Y70: 66657202 | Z70: 6.0810076e+08 | AA70: 1.4957418e+09 | AB70: 4.7274473e+09 | AC70: 3.8087573e+08 | AD70: 2.0184485e+09 | AE70: 59218338 | AF70: 7.7014156e+08 | AG70: 1.4982996e+10 | AH70: 1.3451538e+08 | AI70: 41279266 | AJ70: 15373302 | AK70: 2.7371841e+08 | AL70: 29421507 | AM70: 4399917 | AN70: 2.3008072e+09 | AO70: 4.0281393e+08 | AP70: 8.9978689e+08 | AQ70: 4.6291415e+08 | AS70: 1.3819805e+08 | AT70: 7.4276796e+08 | AU70: 49400793 | AW70: 1.5380069e+08 | AX70: 1.2092908e+08 | AY70: 2.2082326e+08 | AZ70: 3.3136424e+08 | BA70: 92819873 | BB70: 3.9279976e+08 | BC70: 60925306 | BD70: 6.1940954e+08 | BE70: 11970678 | BF70: 2.1567024e+08 | BG70: 2.5200472e+09 | BH70: 5.7272573e+08 | BI70: 6.2160453e+08 | BJ70: 1.4803743e+08 | BK70: 1.5620343e+09 | BL70: 1.8898366e+09 | BM70: 4.8727455e+08 | BN70: 6.5003979e+09 | BP70: 3.0307059e+09 | BQ70: 4.9716674e+08 | BR70: 9.5275536e+08 | BS70: 8.7474809e+09 | BT70: 1.2017165e+09 | BU70: 9.2937064e+08 | BV70: 1.3148568e+09 | BW70: 1.146209e+09 | BX70: 3834111.3 | BY70: 3.8450759e+08 | BZ70: 8.2897852e+08 | CA70: 1.09229e+10 | CB70: 1.3551878e+09 | CC70: 7.1803942e+08 | DG70: 6.1820284e+08 | DH70: 2.1959196e+10 | DI70: 1.1332142e+11
A71: 67 | B71: 29947682 | C71: 19392227 | D71: 16187.085 | E71: 10391.647 | F71: 140395.75 | G71: 34770198 | H71: 18463628 | I71: 28820287 | J71: 1.1929409e+09 | K71: 1.6963878e+09 | L71: 5.2711505e+08 | M71: 1.1554385e+08 | N71: 11924499 | O71: 5087094.7 | P71: 2.2883684e+08 | Q71: 1050775.4 | R71: 74233446 | S71: 1.2774418e+08 | T71: 2.669107e+08 | U71: 3.6027261e+08 | V71: 4.2367927e+08 | W71: 1.6422184e+08 | X71: 1.5476342e+08 | Y71: 2.0781848e+08 | Z71: 1.0747911e+09 | AA71: 2.5943558e+08 | AB71: 1.3268769e+09 | AC71: 87854772 | AD71: 1.9060861e+09 | AE71: 47916290 | AF71: 3.6525861e+08 | AG71: 9.1218174e+09 | AH71: 4.9527537e+08 | AI71: 32157961 | AJ71: 1.3189372e+08 | AK71: 3.3751882e+08 | AL71: 2.220909e+08 | AM71: 1.5547978e+08 | AN71: 2.5496761e+08 | AO71: 2.6977822e+08 | AP71: 4.6234743e+08 | AQ71: 5.6415623e+08 | AR71: 52372611 | AS71: 4.7226682e+08 | AT71: 1.4517547e+09 | AU71: 1.8112114e+09 | AV71: 1.2677436e+08 | AW71: 2.9084897e+08 | AX71: 60694525 | AY71: 6.4807345e+08 | AZ71: 2.1657146e+09 | BA71: 4.6003079e+08 | BB71: 3.327158e+08 | BC71: 2.4733347e+09 | BD71: 2.0849703e+09 | BE71: 5.3090696e+09 | BF71: 8.2231081e+08 | BG71: 2.3925613e+09 | BH71: 8.8154595e+08 | BI71: 8.372901e+08 | BJ71: 29178070 | BK71: 2.0327579e+10 | BL71: 7.8291903e+08 | BM71: 4.9987792e+09 | BN71: 1.9444227e+10 | BO71: 1.8917797e+09 | BP71: 7.5945154e+09 | BQ71: 6.4616472e+08 | BR71: 9.2864112e+08 | BS71: 4.1852399e+09 | BT71: 3.6165123e+09 | BU71: 1.0290671e+09 | BV71: 8.1905477e+08 | BW71: 1.8324266e+09 | BX71: 43723257 | BY71: 5.4949537e+08 | BZ71: 5.4193912e+08 | CA71: 1.9801996e+09 | CB71: 1.2526879e+09 | CC71: 7.220627e+08 | CD71: 1.198749e+09 | CF71: 2.2979042e+09 | CH71: 52484433 | CI71: 53746108 | CN71: 3.6446586e+08 | CO71: 5.1563858e+08 | CP71: 4.4548969e+08 | CQ71: 4.8974293e+08 | CR71: 1.1214233e+09 | CS71: 1.5905062e+09 | CT71: 2.5807208e+09 | CU71: 4.1032882e+09 | CV71: 5.3854895e+09 | CW71: 4.6393558e+08 | CX71: 1.6166749e+09 | CY71: 3.060826e+08 | CZ71: 1.0969974e+10 | DA71: 6.9930584e+08 | DB71: 1.3610904e+09 | DC71: 1.9969755e+08 | DE71: 4.8135523e+08 | DG71: 1.4758768e+09 | DH71: 1.2438972e+10 | DI71: 1.6890814e+11
A72: 68 | B72: 5063848.9 | C72: 11835785 | D72: 9.124346 | E72: 3593.7859 | F72: 9535.7723 | G72: 16030865 | H72: 2094466.8 | I72: 1739850.1 | J72: 46535983 | K72: 2.542127e+08 | L72: 1.1204662e+08 | M72: 27920175 | N72: 2880645.3 | O72: 1176460.6 | P72: 409877.59 | Q72: 110056.29 | R72: 9841652.4 | S72: 13249588 | T72: 6636926.6 | U72: 90425882 | V72: 1.0560416e+08 | W72: 20426458 | X72: 24221716 | Y72: 12699179 | Z72: 35850586 | AA72: 16892474 | AB72: 1.016215e+08 | AC72: 11190255 | AD72: 44820908 | AE72: 8916560.7 | AF72: 22640612 | AG72: 3.2890259e+08 | AH72: 47955758 | AI72: 1556584.3 | AJ72: 4371369.9 | AK72: 33511295 | AL72: 10462702 | AM72: 21578513 | AN72: 13328220 | AO72: 14687374 | AP72: 17700072 | AQ72: 7538102.7 | AR72: 6642762.8 | AS72: 704813.41 | AT72: 88283484 | AU72: 7604198.6 | AV72: 1740024.7 | AW72: 5020690.6 | AX72: 2681228.7 | AY72: 24598837 | AZ72: 4591527.8 | BA72: 12436627 | BB72: 4221251.6 | BC72: 8965627.7 | BD72: 9554273.5 | BE72: 14094781 | BF72: 10045317 | BG72: 22264149 | BH72: 29711631 | BI72: 92180566 | BJ72: 63249498 | BK72: 4.390744e+09 | BL72: 24685149 | BM72: 1.2488268e+08 | BN72: 3.4909778e+08 | BO72: 74585599 | BP72: 2.0765372e+08 | BQ72: 1.2179298e+09 | BR72: 45252339 | BS72: 1.8718557e+08 | BT72: 1.2930305e+08 | BU72: 77131787 | BV72: 1.3738974e+08 | BW72: 16187634 | BX72: 3462551.8 | BY72: 60277202 | BZ72: 1.0572972e+08 | CA72: 2.855647e+08 | CB72: 64262034 | CC72: 71486886 | CD72: 69666956 | CF72: 7.785246e+08 | CH72: 5773433.5 | CI72: 5116876.7 | CN72: 1.5373368e+08 | CO72: 2.1992542e+08 | CP72: 1.7941861e+08 | CQ72: 1.9680879e+08 | CR72: 4.3830331e+08 | CS72: 5.7557679e+08 | CT72: 8.3501649e+08 | CU72: 6.3626496e+08 | CV72: 1.299214e+09 | CW72: 48936529 | CX72: 22228275 | CZ72: 4.6763367e+09 | DA72: 2.2996552e+08 | DB72: 1.9210424e+08 | DE72: 3845.5118 | DF72: 2458.8156 | DG72: 1.2464547e+08 | DH72: 1.4600809e+09 | DI72: 2.1637753e+10
A73: 69 | B73: 6855.1743 | J73: 12747496 | K73: 505924.61 | T73: 1584000.9 | U73: 641808.99 | W73: 58272.803 | AG73: 1.8898381e+08 | AH73: 5148409.6 | AI73: 2114153.6 | AJ73: 26978953 | AK73: 50784054 | AL73: 673537.83 | AM73: 40938099 | AN73: 953649.04 | AO73: 16117621 | AP73: 668346.44 | AQ73: 20734890 | AR73: 503567.8 | AV73: 201197.68 | AW73: 971377.86 | BC73: 1265035.1 | BD73: 18014768 | BF73: 1038339.2 | BG73: 840528.55 | BH73: 472461.64 | BN73: 12921920 | BP73: 27986303 | BR73: 3.1171322e+08 | BT73: 197733.3 | BW73: 5.3271376e+08 | BX73: 8083387.7 | BY73: 21111608 | CC73: 2357355.5 | CD73: 3.7438597e+08 | CF73: 1429524.7 | CN73: 1.0912893e+09 | CO73: 1.190004e+09 | CP73: 7.4648299e+08 | CQ73: 9.3104736e+08 | CR73: 2.6380482e+09 | CS73: 4.4352039e+09 | CT73: 6.9422061e+09 | CU73: 5.2130311e+09 | CV73: 2.6243728e+10 | CW73: 658693.95 | CZ73: 7.1800709e+08 | DA73: 3.9340595e+08 | DB73: 2.7474647e+08 | DG73: 2.5570578e+08 | DH73: 5454620 | DI73: 5.2764867e+10
A74: 70 | BN74: 8582413.6 | BP74: 6751655.7 | BS74: 2.0039617e+09 | BT74: 6.4560708e+08 | BU74: 5512646.3 | BW74: 16268965 | BY74: 338611.77 | CD74: 7925405.4 | CN74: 4.3615567e+09 | CO74: 4.2733357e+09 | CP74: 5.1709461e+09 | CQ74: 3.7395514e+09 | CR74: 1.3092067e+10 | CS74: 2.0448694e+10 | CT74: 3.1430003e+10 | CU74: 2.5960345e+10 | CV74: 5.8892598e+10 | CW74: 37501610 | DB74: 2.171058e+09 | DG74: 44572045 | DH74: 3.9520526e+10 | DI74: 2.118377e+11
A75: 71 | BN75: 11983.676 | BP75: 9427.3774 | BS75: 2798143.7 | BT75: 1.0631859e+09 | BU75: 7697.3411 | BW75: 22716.454 | BY75: 472.80564 | CD75: 11066.291 | CN75: 2.0926333e+09 | CO75: 2.7030676e+09 | CP75: 2.2001132e+09 | CQ75: 1.9991214e+09 | CR75: 6.7940221e+09 | CS75: 1.636085e+10 | CT75: 2.4503568e+10 | CU75: 1.3728735e+10 | CV75: 3.907822e+10 | CW75: 52363.723 | DB75: 3031461.4 | DG75: 1.9223594e+08 | DH75: 1.1314401e+08 | DI75: 1.1083484e+11
A76: 72 | CN76: 9.014289e+08 | CO76: 6.7180039e+09 | CP76: 1.629205e+09 | CQ76: 1.3558984e+09 | CR76: 1.7261208e+09 | CS76: 6.8226254e+09 | CT76: 8.9390669e+09 | CU76: 2.8879237e+09 | CV76: 4.6250647e+09 | CW76: 76573907 | CZ76: 8204.1692 | DB76: 2.8908945e+08 | DH76: 1.5702018e+09 | DI76: 3.7541211e+10
A77: 73 | CN77: 6.4788753e+08 | CO77: 1.2909178e+09 | CP77: 1.0566819e+09 | CQ77: 1.0768064e+09 | CR77: 2.9470923e+09 | CS77: 5.1562901e+09 | CT77: 7.6336814e+09 | CU77: 7.0853844e+09 | CV77: 2.2680204e+10 | CW77: 1652024 | CZ77: 4.6500358e+08 | DB77: 6236885.6 | DH77: 1.9742866e+10 | DI77: 6.9790705e+10
A78: 74 | B78: 1566289.7 | C78: 5847183.9 | I78: 402763.82 | J78: 15615087 | K78: 30447831 | L78: 13729192 | M78: 3351346.1 | N78: 296880.54 | O78: 145518.72 | R78: 2856015.2 | S78: 4573792 | T78: 3614832.1 | U78: 7194362.9 | V78: 3242268.7 | W78: 9350336.3 | X78: 5644678.8 | Y78: 2746730.5 | Z78: 10454062 | AA78: 5889696.7 | AB78: 3788448.5 | AC78: 1102496 | AD78: 4097368.5 | AE78: 2264057.9 | AF78: 6700341.2 | AG78: 5.578928e+08 | AH78: 35073205 | AI78: 720558.07 | AJ78: 4681827.2 | AK78: 48445754 | AL78: 2980459.3 | AM78: 7972188.6 | AN78: 4872223 | AO78: 6192190.8 | AP78: 7840217.5 | AR78: 10060147 | AT78: 9777307.1 | AU78: 6792111.3 | AW78: 11412560 | AX78: 99220.557 | AY78: 1070922.4 | AZ78: 21202564 | BA78: 2.7287255e+09 | BB78: 3.6568542e+09 | BC78: 9.1374562e+08 | BD78: 93355798 | BE78: 26042582 | BF78: 46151209 | BG78: 1.2099119e+08 | BH78: 1.533137e+08 | BI78: 20690233 | BJ78: 43118483 | BK78: 1.2472523e+09 | BL78: 56433264 | BN78: 1.0230759e+09 | BO78: 5.5850199e+08 | BP78: 2.7365114e+08 | BQ78: 15194537 | BR78: 60893642 | BS78: 1.34604e+08 | BT78: 1.0481545e+08 | BU78: 26817553 | BV78: 55272601 | BW78: 8.4760872e+09 | BX78: 1100310.1 | BY78: 1.5398008e+08 | BZ78: 25720967 | CA78: 5.9764297e+08 | CB78: 8829461.4 | CC78: 2.124109e+08 | CD78: 1.812296e+08 | CF78: 10460547 | CH78: 2348887.1 | CI78: 2457747.6 | CN78: 3.6452117e+08 | CO78: 4.3978123e+08 | CP78: 4.9454438e+08 | CQ78: 4.5210752e+08 | CR78: 1.294269e+09 | CS78: 2.1024238e+09 | CT78: 4.2689239e+09 | CU78: 4.2811081e+09 | CV78: 1.0417631e+10 | CW78: 940993.45 | CZ78: 2.808933e+08 | DA78: 37728480 | DB78: 47727254 | DE78: 5494361.1 | DG78: 5.0899774e+08 | DH78: 1.8342451e+10 | DI78: 6.5253321e+10
A79: 75 | B79: 48.525465 | C79: 181.15252 | I79: 12.478089 | J79: 483.77344 | K79: 943.30903 | L79: 425.34626 | M79: 103.82858 | N79: 9.1977025 | O79: 4.5083381 | R79: 88.482655 | S79: 141.70137 | T79: 111.99168 | U79: 222.88968 | V79: 100.44923 | W79: 289.68423 | X79: 174.87868 | Y79: 85.096887 | Z79: 323.87892 | AA79: 182.46961 | AB79: 117.37052 | AC79: 34.1566 | AD79: 126.94121 | AE79: 70.143131 | AF79: 207.58432 | AG79: 17284.164 | AH79: 1086.6085 | AI79: 22.323722 | AJ79: 145.04842 | AK79: 1500.9055 | AL79: 92.338077 | AM79: 246.98762 | AN79: 150.9471 | AO79: 191.84123 | AP79: 242.899 | AR79: 311.67499 | AT79: 302.91228 | AU79: 210.42746 | AW79: 353.5743 | AX79: 3.0739676 | AY79: 33.178413 | AZ79: 656.87996 | BA79: 84539.071 | BB79: 113293.57 | BC79: 28308.896 | BD79: 2892.2706 | BE79: 806.82932 | BF79: 1429.8178 | BG79: 3748.447 | BH79: 4749.8358 | BI79: 641.00735 | BJ79: 1335.8605 | BK79: 38641.319 | BL79: 1748.3678 | BN79: 31696.074 | BO79: 17303.037 | BP79: 8478.0289 | BQ79: 470.74433 | BR79: 1886.5554 | BS79: 4170.1876 | BT79: 3247.304 | BU79: 830.83881 | BV79: 1712.4091 | BW79: 262598.98 | BX79: 34.08888 | BY79: 4770.481 | BZ79: 796.8653 | CA79: 18515.67 | CB79: 273.54693 | CC79: 6580.7353 | CD79: 5614.7025 | CF79: 324.07984 | CH79: 72.771238 | CI79: 76.143864 | CN79: 71635252 | CO79: 76122280 | CP79: 64828153 | CQ79: 98076045 | CR79: 1.8458099e+08 | CS79: 2.6772592e+08 | CT79: 5.0054454e+08 | CU79: 4.0476976e+08 | CV79: 9.9824071e+08 | CW79: 29.153065 | CZ79: 8702.3993 | DA79: 1168.8719 | DB79: 1478.6455 | DE79: 170.22166 | DG79: 15769.339 | DH79: 773825.49 | DI79: 2.6680037e+09
A80: 76 | B80: 245530.01 | C80: 773922.27 | I80: 82647.086 | J80: 2495225 | K80: 7915999 | L80: 1133031.4 | M80: 130122.9 | R80: 280375.23 | S80: 409542.79 | T80: 447579.81 | U80: 368430.41 | V80: 214569.34 | W80: 647804.03 | X80: 824859.83 | Y80: 183298.82 | Z80: 1142147.2 | AA80: 303594.37 | AB80: 292491.1 | AD80: 352001.56 | AE80: 310384.19 | AF80: 968677.89 | AG80: 39459662 | AH80: 312569.02 | AI80: 741100.67 | AJ80: 1147378.3 | AK80: 2080606.3 | AL80: 19639.093 | AM80: 1749201.2 | AN80: 27806.608 | AO80: 7002718 | AP80: 118497.54 | AW80: 116875.47 | AY80: 70158.086 | AZ80: 1518165.1 | BA80: 1319389.6 | BB80: 132775.19 | BC80: 2500864.5 | BD80: 13553884 | BE80: 4396126.3 | BF80: 5849775.3 | BG80: 15457010 | BH80: 9654807.4 | BI80: 1443998.2 | BJ80: 1701697.2 | BK80: 65491.01 | BL80: 5480239.2 | BN80: 59891482 | BO80: 53993469 | BP80: 28659888 | BQ80: 1909469.8 | BR80: 4297679 | BS80: 16184163 | BT80: 591880.04 | BU80: 1702868.3 | BV80: 6098304 | BW80: 15810012 | BY80: 26384240 | BZ80: 22577291 | CA80: 49165559 | CB80: 750301.21 | CC80: 1340702.7 | CD80: 4415775.9 | CF80: 15205777 | CH80: 368941.24 | CI80: 313751.47 | CN80: 8.8320864e+08 | CO80: 1.2209375e+09 | CP80: 1.098793e+09 | CQ80: 9.4703205e+08 | CR80: 1.7433194e+09 | CS80: 2.5128315e+09 | CT80: 5.4527009e+09 | CU80: 4.9447641e+09 | CV80: 9.0241445e+09 | CW80: 58914.085 | CX80: 344612.63 | CZ80: 94427483 | DA80: 4724288.3 | DH80: 1.4967541e+09 | DI80: 2.9869145e+10
A81: 77 | B81: 8.6198484 | C81: 38227.31 | D81: 0.017953229 | E81: 0.0015170112 | F81: 0.0071151091 | G81: 11908.503 | H81: 40575.817 | I81: 609399.58 | J81: 16068640 | K81: 11835771 | L81: 7701047.7 | M81: 2361546.1 | N81: 166605.39 | O81: 125830.97 | P81: 96152.388 | Q81: 39795.021 | R81: 1715745.2 | S81: 2444097.8 | T81: 3432682.3 | U81: 2369913.1 | V81: 2717038.1 | W81: 5166080.5 | X81: 4262337 | Y81: 1233210.6 | Z81: 7596411 | AA81: 4363976.2 | AB81: 4985762.3 | AC81: 1065031.1 | AD81: 3911179.8 | AE81: 2161736.6 | AF81: 5459990.1 | AG81: 1.0269526e+08 | AH81: 633008.19 | AI81: 23024.593 | AJ81: 731032.9 | AK81: 1369898.7 | AL81: 53233.809 | AM81: 928479.16 | AN81: 103357.12 | AO81: 151869.56 | AP81: 1007676.1 | AQ81: 755.64751 | AR81: 261600.68 | AS81: 1.0825667 | AT81: 93.428242 | AU81: 32.219124 | AV81: 87340.1 | AW81: 2456035.1 | AX81: 7042.9102 | AY81: 336478.51 | AZ81: 10209987 | BA81: 10682548 | BB81: 1017327.4 | BC81: 16994466 | BD81: 1.4442504e+08 | BE81: 28941731 | BF81: 39738882 | BG81: 1.0591808e+08 | BH81: 64887464 | BI81: 9839868 | BJ81: 11611060 | BK81: 5.0997947e+08 | BL81: 38805959 | BM81: 4873811.9 | BN81: 3.5929141e+08 | BO81: 20625622 | BP81: 1.2383441e+08 | BQ81: 14936473 | BR81: 21285464 | BS81: 77661396 | BT81: 4044750.5 | BU81: 6313797.8 | BV81: 5411335 | BW81: 6277130.1 | BX81: 46041.295 | BY81: 8360850.9 | BZ81: 4918032 | CA81: 85876053 | CB81: 3796665.9 | CC81: 5924809.8 | CD81: 27488489 | CF81: 9607463.1 | CH81: 8.5894673 | CI81: 9.3726599 | CN81: 1.1691897e+08 | CO81: 1.0303836e+08 | CP81: 1.1435383e+08 | CQ81: 1.3477879e+08 | CR81: 3.5200746e+08 | CS81: 5.059796e+08 | CT81: 1.2242527e+09 | CU81: 1.1375723e+09 | CV81: 3.9866596e+09 | CW81: 8865172.8 | CX81: 82508717 | CZ81: 1.2301588e+08 | DA81: 18026511 | DB81: 22958218 | DG81: 261.82664 | DH81: 2.5617409e+10 | DI81: 3.5534798e+10
A82: 78 | B82: 11386717 | C82: 22504790 | D82: 23716.048 | E82: 2005.0611 | F82: 9399.8448 | G82: 507268.73 | H82: 823979.1 | I82: 6288817.1 | J82: 1.2522384e+08 | K82: 76098715 | L82: 61757640 | M82: 16053717 | N82: 1626337.2 | O82: 1317645 | P82: 1838954.6 | Q82: 363441.12 | R82: 13029285 | S82: 17986000 | T82: 16554022 | U82: 27569594 | V82: 23255281 | W82: 30748801 | X82: 28167880 | Y82: 10137906 | Z82: 46222544 | AA82: 28169777 | AB82: 38790400 | AC82: 8232959.4 | AD82: 27511434 | AE82: 13011942 | AF82: 34732444 | AG82: 1.2910236e+09 | AH82: 70467294 | AI82: 4662630.4 | AJ82: 29132370 | AK82: 91594503 | AL82: 25199396 | AM82: 49132379 | AN82: 31559080 | AO82: 40798393 | AP82: 98203436 | AQ82: 9.9821181e+08 | AR82: 125030.55 | AS82: 1430914.2 | AT82: 1.2341843e+08 | AU82: 42561021 | AV82: 2461771.5 | AW82: 12619412 | AX82: 37116876 | AY82: 36410111 | AZ82: 48780723 | BA82: 78968769 | BB82: 4354535 | BC82: 87467945 | BD82: 6.5285166e+08 | BE82: 1.1326605e+08 | BF82: 2.0762044e+08 | BG82: 5.7912149e+08 | BH82: 6.2736876e+08 | BI82: 2.8075066e+08 | BJ82: 1.4697116e+08 | BK82: 7.7597233e+09 | BL82: 2.8832472e+08 | BM82: 4.8984299e+08 | BN82: 4.1143723e+09 | BO82: 5.4293323e+08 | BP82: 1.3158825e+09 | BQ82: 74835572 | BR82: 1.5595583e+08 | BS82: 5.1760295e+09 | BT82: 1.3178887e+09 | BU82: 8.780449e+08 | BV82: 4.1178607e+08 | BW82: 1.2149755e+08 | BX82: 3804046.6 | BY82: 2.6853758e+08 | BZ82: 1.1346883e+09 | CA82: 1.0227397e+09 | CB82: 57694908 | CC82: 1.8307651e+08 | CD82: 1.8529599e+08 | CF82: 1.8559926e+08 | CH82: 11346560 | CI82: 12381146 | CN82: 4.0253507e+09 | CO82: 4.7896932e+09 | CP82: 4.1931967e+09 | CQ82: 5.4321703e+09 | CR82: 1.3290202e+10 | CS82: 1.6930488e+10 | CT82: 3.162776e+10 | CU82: 2.5529111e+10 | CV82: 5.8083782e+10 | CW82: 14499904 | CX82: 1.521463e+08 | CZ82: 8.7964766e+08 | DA82: 4.0823829e+08 | DB82: 9.7383391e+08 | DE82: 40.973424 | DF82: 26.198358 | DG82: 3.468883e+08 | DH82: 29763997 | DI82: 1.9892265e+11
A83: 79 | B83: 5992427.7 | C83: 12736193 | D83: 237825.5 | E83: 2751.096 | G83: 2458445.9 | H83: 2215191.5 | I83: 7389986.1 | J83: 3.409245e+08 | K83: 8.6134208e+08 | L83: 2.1485848e+08 | M83: 42923880 | N83: 4709311.6 | O83: 2009702.8 | P83: 1789320.9 | Q83: 318515.71 | R83: 37582082 | S83: 67991392 | T83: 30820839 | U83: 83505409 | V83: 1.8822867e+08 | W83: 72747888 | X83: 1.2480289e+08 | Y83: 55018221 | Z83: 1.8874398e+08 | AA83: 78753923 | AB83: 5.6513473e+08 | AC83: 29438403 | AD83: 1.4377058e+08 | AE83: 15984251 | AF83: 92949749 | AG83: 1.9599598e+09 | AH83: 1.1527229e+08 | AI83: 5122987.2 | AJ83: 45255617 | AK83: 2.0039496e+08 | AL83: 39204306 | AM83: 89202427 | AN83: 34962565 | AO83: 44083684 | AP83: 1.7121626e+08 | AQ83: 51589078 | AR83: 2993255.5 | AS83: 39831107 | AT83: 9.1569102e+08 | AU83: 3.7984995e+08 | AV83: 21684248 | AW83: 65102861 | AX83: 1707419.6 | AY83: 1.0919052e+08 | AZ83: 1.8230368e+08 | BA83: 86753224 | BB83: 44176783 | BC83: 2.0717146e+08 | BD83: 2.899041e+08 | BE83: 5.394139e+08 | BF83: 51625243 | BG83: 3.7934745e+08 | BH83: 2.1689591e+08 | BI83: 2.6730631e+08 | BJ83: 9801252.9 | BK83: 1.0228094e+09 | BL83: 1.4832204e+09 | BM83: 38966647 | BN83: 3.2309228e+09 | BO83: 6.9078378e+08 | BP83: 1.8713867e+09 | BQ83: 6.9313137e+08 | BR83: 2.9832214e+08 | BS83: 8.2846829e+08 | BT83: 8.8559647e+08 | BU83: 1.0080391e+08 | BV83: 79950399 | BW83: 1.2492516e+08 | BX83: 11305300 | BY83: 1.8509528e+08 | BZ83: 1.8378956e+08 | CA83: 1.4971777e+09 | CB83: 3.4780728e+08 | CC83: 2.2301852e+08 | CD83: 83931750 | CF83: 7.0535732e+08 | CH83: 5585400.5 | CI83: 4107211.8 | CN83: 1.0368559e+09 | CO83: 1.3737448e+09 | CP83: 1.4369622e+09 | CQ83: 1.2508293e+09 | CR83: 3.1689994e+09 | CS83: 4.1753411e+09 | CT83: 7.1230095e+09 | CU83: 5.0863694e+09 | CV83: 1.2147376e+10 | CW83: 4.0436231e+08 | CX83: 9.8940305e+08 | CZ83: 2.9745075e+09 | DA83: 7.1369389e+08 | DB83: 9.8272879e+08 | DG83: 8898802.1 | DH83: 2.8052327e+08 | DI83: 6.7592463e+10
A84: 80 | B84: 408.4251 | C84: 671.70417 | D84: 0.38977323 | E84: 0.034915017 | F84: 34159.628 | G84: 213.83469 | H84: 29.489698 | I84: 41.858532 | J84: 853842.69 | K84: 8141.881 | L84: 242864.03 | M84: 1037.8717 | N84: 359771.14 | O84: 115242.19 | P84: 75.889892 | Q84: 1.5347982 | R84: 75871.107 | S84: 687.98295 | T84: 639.44769 | U84: 151804.85 | V84: 225810.56 | W84: 221351.6 | X84: 5627904.2 | Y84: 1255360.6 | Z84: 16321855 | AA84: 4487647.7 | AB84: 112.02916 | AC84: 440.0776 | AD84: 3103063.8 | AE84: 394.61265 | AF84: 2483080.5 | AG84: 4.4583951e+08 | AH84: 26500186 | AI84: 1740767.8 | AJ84: 1264203.4 | AK84: 3853959.8 | AL84: 2901042 | AM84: 9829988.4 | AN84: 140235.7 | AO84: 17028136 | AP84: 3273202.5 | AQ84: 228556.74 | AR84: 1206699 | AS84: 244.80857 | AT84: 1002144.3 | AU84: 16622785 | AV84: 90.492067 | AW84: 20253454 | AX84: 200901.53 | AY84: 3931.4129 | AZ84: 927964.49 | BA84: 1687085.4 | BB84: 418113.96 | BC84: 41139914 | BD84: 922555.57 | BE84: 4928.7461 | BF84: 2861523.1 | BG84: 8959080.6 | BH84: 2639455 | BI84: 560251.6 | BJ84: 259.07954 | BK84: 1.2474397e+08 | BL84: 9042021.8 | BM84: 2336.8068 | BN84: 6.1084173e+08 | BO84: 1187570.4 | BP84: 33001453 | BQ84: 1715761.5 | BR84: 6910820.5 | BS84: 1.6267495e+08 | BT84: 2.2304078e+08 | BU84: 62215295 | BV84: 57941990 | BW84: 22046136 | BX84: 95160.605 | BY84: 34417644 | BZ84: 33566995 | CA84: 1.1772418e+08 | CB84: 70554005 | CC84: 2.701865e+08 | CD84: 8726860.7 | CF84: 17417884 | CH84: 468.81155 | CI84: 240.95331 | CN84: 1.0003635e+09 | CO84: 1.0506068e+09 | CP84: 9.9951846e+08 | CQ84: 1.2542729e+09 | CR84: 2.8993802e+09 | CS84: 3.4182309e+09 | CT84: 5.3908949e+09 | CU84: 4.5842914e+09 | CV84: 1.0772237e+10 | CW84: 428207.24 | CX84: 34755544 | CZ84: 1.1529358e+09 | DA84: 49711964 | DB84: 1.5833018e+08 | DE84: 245307.73 | DG84: 1705.2327 | DH84: 69164054 | DI84: 3.5351007e+10
A85: 81 | B85: 988183.31 | C85: 4442810.4 | G85: 737937.9 | H85: 135186.43 | I85: 539306.78 | J85: 26822572 | K85: 1.0331659e+08 | L85: 6678714.8 | M85: 1179344.2 | N85: 170361.55 | O85: 116545.16 | R85: 1460652.5 | S85: 1701300 | T85: 971665.11 | U85: 3697932.1 | V85: 912844.92 | W85: 2409542.7 | X85: 2585572.3 | Y85: 961083.05 | Z85: 3410085.8 | AA85: 2322824 | AB85: 390755.78 | AC85: 394070.38 | AD85: 1131060.7 | AE85: 1330618 | AF85: 2542798.7 | AG85: 1.156819e+08 | AH85: 4254689 | AI85: 441191.73 | AJ85: 2454830.2 | AK85: 3582217.4 | AL85: 1688880 | AM85: 4514056.2 | AN85: 4145989.8 | AO85: 3898572.4 | AP85: 1356585.6 | AQ85: 5477575.1 | AR85: 1903195.2 | AT85: 13066908 | AU85: 7701930.4 | AV85: 240546.22 | AW85: 1222475.5 | AX85: 260821.84 | AY85: 2501955.8 | AZ85: 3507244.8 | BA85: 5916562 | BB85: 353547.16 | BC85: 12300729 | BD85: 11448096 | BE85: 2090319 | BF85: 59881806 | BG85: 2.6025071e+08 | BH85: 1.166531e+08 | BI85: 1.7969599e+08 | BJ85: 11796730 | BK85: 2.3944556e+09 | BL85: 23374065 | BM85: 4.3190675e+08 | BN85: 1.9272243e+08 | BO85: 32021092 | BP85: 27123041 | BQ85: 2888886.9 | BR85: 9434304.9 | BS85: 76418042 | BT85: 23640430 | BU85: 11623658 | BV85: 17345302 | BW85: 34962132 | BY85: 1096637.5 | BZ85: 972740.67 | CA85: 39806314 | CB85: 6986892.1 | CC85: 35312996 | CD85: 54922017 | CF85: 4144637.4 | CH85: 1390896.4 | CI85: 1176957.1 | CN85: 6.3497199e+08 | CO85: 1.0510071e+09 | CP85: 9.5786327e+08 | CQ85: 1.2893222e+09 | CR85: 3.2469101e+09 | CS85: 3.9288669e+09 | CT85: 7.2802534e+09 | CU85: 6.3032128e+09 | CV85: 2.0142976e+10 | DH85: 4.3664701e+08 | DI85: 4.9705396e+10
A86: 82 | CN86: 67742742 | CO86: 1.1189075e+08 | CP86: 79976977 | CQ86: 99799855 | CR86: 1.9521288e+08 | CS86: 2.2535556e+08 | CT86: 4.4441801e+08 | CU86: 4.3471313e+08 | CV86: 1.9656061e+09 | DH86: 2.5146234e+09 | DI86: 6.1393394e+09
A87: 83 | B87: 60650256 | C87: 48110478 | D87: 11196.58 | E87: 14301.14 | F87: 72072.227 | G87: 43201685 | H87: 18682229 | I87: 2101399.6 | J87: 1.9322715e+09 | K87: 2.6366351e+08 | L87: 2.7142014e+08 | M87: 59464227 | N87: 8445395.7 | O87: 4502591.1 | P87: 782263.25 | Q87: 508315.01 | R87: 43133041 | S87: 61001605 | T87: 37474489 | U87: 2.5203939e+08 | V87: 3.6109193e+08 | W87: 95816382 | X87: 1.2269529e+08 | Y87: 56198371 | Z87: 1.4548557e+08 | AA87: 70904139 | AB87: 5.1033346e+08 | AC87: 60060778 | AD87: 1.3192501e+08 | AE87: 24823246 | AF87: 60157443 | AG87: 3.6912479e+09 | AH87: 1.7979433e+08 | AI87: 16616680 | AJ87: 47732218 | AK87: 2.6428148e+08 | AL87: 1.0889851e+08 | AM87: 76321893 | AN87: 1.511152e+08 | AO87: 1.4246864e+08 | AP87: 1.6563788e+08 | AQ87: 4.6371277e+08 | AR87: 10650090 | AS87: 2.2431037e+08 | AT87: 1.2027743e+09 | AU87: 1.3797072e+08 | AV87: 28064971 | AW87: 1.089906e+08 | AX87: 73767991 | AY87: 2.2526546e+08 | AZ87: 48294107 | BA87: 1.1526893e+08 | BB87: 22900969 | BC87: 1.0275409e+08 | BD87: 3.1448278e+08 | BE87: 3.0326602e+08 | BF87: 89780856 | BG87: 5.8884207e+08 | BH87: 1.4849759e+08 | BI87: 1.8892437e+08 | BJ87: 69252197 | BK87: 2.2684318e+09 | BL87: 3.2430285e+08 | BM87: 2.7016501e+08 | BN87: 1.432747e+09 | BO87: 2.4880229e+08 | BP87: 3.9132391e+08 | BQ87: 1.8057204e+08 | BR87: 2.4027982e+08 | BS87: 5.4225845e+08 | BT87: 4.9766281e+08 | BU87: 2.1333147e+08 | BV87: 3.0046368e+08 | BW87: 1.2809277e+08 | BX87: 24262556 | BY87: 1.592918e+08 | BZ87: 3.8298437e+08 | CA87: 1.8151525e+09 | CB87: 1.8281414e+08 | CC87: 2.370087e+08 | CD87: 2.1296584e+08 | CF87: 1.6867079e+09 | CH87: 1.0963169e+08 | CI87: 1.0333995e+08 | CN87: 1.3467557e+09 | CO87: 2.0774978e+09 | CP87: 1.7315531e+09 | CQ87: 1.5196943e+09 | CR87: 3.5964485e+09 | CS87: 4.2039597e+09 | CT87: 7.8999322e+09 | CU87: 6.697325e+09 | CV87: 1.1835671e+10 | CW87: 54158852 | CX87: 5.1500428e+08 | CY87: 1723.3606 | CZ87: 2.1273808e+09 | DA87: 5.1844667e+08 | DB87: 7.0553543e+08 | DC87: 22902.309 | DE87: 8.4236893e+08 | DF87: 5665.2336 | DG87: 2.4537153e+08 | DH87: 3.355382e+10 | DI87: 1.0548248e+11
A88: 85 | CW88: 4.9015411e+10 | CX88: 5.2397593e+10 | CZ88: 1.2460091e+11 | DA88: 1.4043361e+11 | DB88: 2.9876609e+10 | DH88: 0.00013200245 | DI88: 3.9632414e+11
A89: 86 | B89: 7410753.4 | C89: 2872211.7 | D89: 225033.37 | E89: 192.66056 | I89: 182.82512 | J89: 5519.7326 | K89: 17511.125 | L89: 7.4735349e+08 | M89: 287.84724 | R89: 620.22314 | S89: 905.95705 | T89: 990.09944 | U89: 815.01161 | V89: 474.65275 | W89: 1433.0191 | X89: 1824.6875 | Y89: 405.47866 | Z89: 2526.5646 | AA89: 671.58663 | AB89: 647.02488 | AD89: 778.66907 | AE89: 686.60651 | AF89: 2142.83 | AG89: 87289.438 | AH89: 691.43962 | AI89: 1639.4023 | AJ89: 2538.1364 | AK89: 4602.547 | AL89: 43.443996 | AM89: 3869.4398 | AN89: 61.511504 | AO89: 15490.84 | AP89: 262.13056 | AW89: 231494.82 | AY89: 155.19798 | AZ89: 3358.3606 | BA89: 2918.6458 | BB89: 293.71441 | BC89: 5532.208 | BD89: 29982.795 | BE89: 9724.7511 | BF89: 12940.394 | BG89: 34192.733 | BH89: 21357.575 | BI89: 3194.2947 | BJ89: 3764.3553 | BK89: 144.87385 | BL89: 12122.937 | BN89: 804859.5 | BO89: 141764.99 | BP89: 63399.061 | BQ89: 4223.9729 | BR89: 2565714.9 | BS89: 35801.281 | BT89: 1309.3086 | BU89: 3766.946 | BV89: 13490.169 | BW89: 34973.615 | BY89: 58365.057 | BZ89: 321851.84 | CA89: 31577426 | CB89: 1659.755 | CC89: 2965.7929 | CD89: 217990.97 | CF89: 33636.976 | CH89: 3.0467652e+08 | CI89: 17342114 | CN89: 1.1571047e+08 | CO89: 1.1440305e+08 | CP89: 90574671 | CQ89: 1.095487e+08 | CR89: 2.5379619e+08 | CS89: 3.3000381e+08 | CT89: 5.3357605e+08 | CU89: 4.2114217e+08 | CV89: 7.6199337e+08 | CW89: 130.32492 | CX89: 762.32388 | CZ89: 15440230 | DA89: 7029484.2 | DB89: 8289050.7 | DG89: 1.1207805e+09 | DH89: 9.121753e+09 | DI89: 1.4120331e+10
A90: 87 | B90: 5704749.3 | C90: 2211005.9 | D90: 173229.25 | E90: 148.30887 | I90: 140.27971 | J90: 4235.2303 | K90: 13436.095 | L90: 1.1313136e+09 | M90: 1.3465369e+09 | R90: 475.89042 | S90: 695.13092 | T90: 759.69245 | U90: 625.34947 | V90: 364.19585 | W90: 1099.5398 | X90: 1400.0627 | Y90: 311.11933 | Z90: 1938.6053 | AA90: 515.30106 | AB90: 496.4551 | AD90: 597.46424 | AE90: 526.82565 | AF90: 1644.17 | AG90: 66976.229 | AH90: 530.53404 | AI90: 1257.8954 | AJ90: 1947.4843 | AK90: 3531.4838 | AL90: 33.334102 | AM90: 2968.9787 | AN90: 47.197103 | AO90: 11885.952 | AP90: 201.12991 | AW90: 370347.88 | AY90: 119.08171 | AZ90: 2576.8332 | BA90: 2239.4449 | BB90: 225.36385 | BC90: 4244.8025 | BD90: 23005.47 | BE90: 7461.695 | BF90: 9929.0228 | BG90: 26235.71 | BH90: 16387.433 | BI90: 2450.9473 | BJ90: 2888.3486 | BK90: 111.16012 | BL90: 9301.7967 | BN90: 719480.66 | BO90: 108830.64 | BP90: 48645.404 | BQ90: 3241.0081 | BR90: 4117955.4 | BS90: 27469.93 | BT90: 1004.6181 | BU90: 2890.3364 | BV90: 10350.859 | BW90: 26834.871 | BY90: 185543.91 | BZ90: 687992.15 | CA90: 14220552 | CB90: 1273.5118 | CC90: 2275.6204 | CD90: 261013.94 | CF90: 25809.283 | CH90: 9732045.5 | CI90: 1.8089649e+08 | CN90: 67897755 | CO90: 63281798 | CP90: 50884303 | CQ90: 57475103 | CR90: 1.361715e+08 | CS90: 1.6261586e+08 | CT90: 2.9544713e+08 | CU90: 2.1907801e+08 | CV90: 4.3878684e+08 | CW90: 99.996883 | CX90: 584.92276 | CZ90: 18518554 | DA90: 6234760.9 | DB90: 12725109 | DG90: 2.0745512e+09 | DH90: 1.0929144e+10 | DI90: 1.7230428e+10
A91: 5001 | B91: 4.3609373e+09 | C91: 9.2640051e+08 | D91: 3.955565e+08 | E91: 56623220 | F91: 1.339349e+10 | G91: 1.0418136e+09 | H91: 7.0688064e+08 | I91: 9.5804271e+08 | J91: 1.483185e+10 | K91: 1.0478454e+11 | L91: 1.4236526e+10 | M91: 5.9928529e+09 | N91: 3.37731e+08 | O91: 5.3722254e+08 | P91: 1.8985562e+09 | Q91: 2.6816639e+08 | R91: 2.0227803e+09 | S91: 2.0281572e+09 | T91: 2.4722091e+09 | U91: 2.9247732e+09 | V91: 1.1678078e+10 | W91: 4.1984464e+09 | X91: 3.0931004e+09 | Y91: 1.5117517e+09 | Z91: 1.1040613e+10 | AA91: 1.0447119e+10 | AB91: 5.4466842e+10 | AC91: 4.5216737e+09 | AD91: 2.2799971e+10 | AE91: 2.196966e+09 | AF91: 1.1491053e+10 | AG91: 8.1904571e+10 | AH91: 1.4633841e+10 | AI91: 7.169762e+09 | AJ91: 7.7306713e+09 | AK91: 1.7776902e+10 | AL91: 8.6701548e+09 | AM91: 2.6314207e+09 | AN91: 7.7189351e+09 | AO91: 8.6525717e+09 | AP91: 1.4800189e+10 | AQ91: 9.7703011e+09 | AR91: 1.4148567e+09 | AS91: 7.552281e+08 | AT91: 1.2822604e+10 | AU91: 6.5228751e+09 | AV91: 4.9658134e+08 | AW91: 1.1385587e+10 | AX91: 1.097422e+10 | AY91: 1.9496864e+10 | AZ91: 3.785316e+10 | BA91: 2.1603108e+10 | BB91: 2.9820556e+10 | BC91: 9.3624236e+09 | BD91: 3.5906879e+10 | BE91: 4.2262655e+10 | BF91: 1.4257988e+10 | BG91: 4.1217357e+10 | BH91: 1.9570959e+10 | BI91: 2.764635e+10 | BJ91: 4.8163888e+09 | BK91: 2.5671626e+10 | BL91: 6.4076289e+09 | BM91: 6.6593933e+08 | BN91: 3.1709553e+11 | BO91: 7.4166324e+10 | BP91: 7.8506428e+10 | BQ91: 6.3619526e+09 | BR91: 2.9085374e+10 | BS91: 1.1187817e+11 | BT91: 5.5173264e+10 | BU91: 2.1513258e+10 | BV91: 3.8848908e+10 | BW91: 1.6469203e+10 | BX91: 1.4991863e+09 | BY91: 1.016941e+10 | BZ91: 1.265583e+10 | CA91: 6.5774241e+10 | CB91: 1.9960493e+10 | CC91: 9.9352754e+09 | CD91: 2.6648492e+10 | CE91: 6.1393394e+09 | CF91: 4.0995271e+10 | CG91: 3.1869111e+11 | CH91: 1.4199785e+09 | CI91: 2.2131513e+09 | DI91: 2.1392121e+12
A92: 6001 | B92: 2.9593404e+09 | C92: 7.4732466e+08 | D92: 2.3682529e+08 | E92: 1.0503178e+08 | F92: 7.6907345e+08 | G92: 4.4207668e+08 | H92: 3.1323058e+08 | I92: 46877348 | J92: 3.1726348e+09 | K92: 2.2005385e+10 | L92: 9.3061289e+08 | M92: 2.0207804e+08 | N92: 13361948 | O92: 52265515 | P92: 5.1529394e+08 | Q92: 37618985 | R92: 44863957 | S92: 1.0209814e+08 | T92: 1.9919225e+08 | U92: 1.250885e+08 | V92: 2.5417381e+08 | W92: 1.4667671e+08 | X92: 1.2332719e+08 | Y92: 4.8627507e+08 | Z92: 4.2079872e+08 | AA92: 1.6509538e+08 | AB92: -1728131.8 | AC92: 96729823 | AD92: 1.849216e+08 | AE92: 1.0244584e+08 | AF92: 3.4434456e+08 | AG92: 7.3302212e+09 | AH92: 1.4414654e+09 | AI92: 6.0150742e+08 | AJ92: 4.0772799e+08 | AK92: 2.4239682e+09 | AL92: 5.0985785e+08 | AM92: 2.5371844e+09 | AN92: 9.0146704e+08 | AO92: 1.9346077e+09 | AP92: 2.4700168e+08 | AQ92: 3.5563243e+08 | AR92: -60142947 | AS92: 40543362 | AT92: 8.623726e+09 | AU92: 5.1613922e+09 | AV92: 2.4164972e+08 | AW92: 4.0395815e+09 | AX92: 1.4802219e+08 | AY92: 2.1090804e+08 | AZ92: 1.4283302e+09 | BA92: 1.4936865e+09 | BB92: 9.257048e+09 | BC92: -2.2743266e+08 | BD92: 1.6103118e+09 | BE92: 5.4130977e+08 | BF92: 4.7460017e+08 | BG92: 9.1934387e+09 | BH92: 6.0941679e+08 | BI92: 9.0024769e+08 | BJ92: 2.0703214e+09 | BK92: 3.9937213e+10 | BL92: 1.6628947e+09 | BM92: 1.4320613e+08 | BN92: 4.8267425e+10 | BO92: 95598066 | BP92: 1.2923051e+10 | BQ92: 1.5909255e+08 | BR92: 1.8694203e+09 | BS92: 1.1627984e+10 | BT92: -91451344 | BU92: 1.8696143e+08 | BV92: 3.3882808e+09 | BW92: 1.2164926e+10 | BX92: -2168195.2 | BY92: 1.512654e+09 | BZ92: 7.8374475e+08 | CA92: 4.848865e+09 | CB92: 1.0966238e+10 | CC92: 8.0836513e+09 | CD92: 3.274848e+08 | CH92: 1.1334942e+09 | CI92: 3.0745376e+09 | DI92: 2.6285404e+11
A93: 7001 | B93: 5.8312208e+09 | C93: 3.0777779e+09 | D93: 69348345 | E93: 89377942 | F93: -2779702.5 | G93: 2.2692799e+09 | H93: 1.3166371e+09 | I93: 5.7899493e+08 | J93: 3.5360048e+10 | K93: 3.9603697e+10 | L93: 8.0198927e+09 | M93: 3.9831619e+09 | N93: 9362343.6 | O93: 42742359 | P93: 1.1182744e+09 | Q93: 33705052 | R93: 1.2715335e+09 | S93: 1.2780417e+09 | T93: 7.8267429e+08 | U93: 1.4416262e+10 | V93: 4.2506078e+10 | W93: 2.3432803e+09 | X93: 2.088547e+09 | Y93: 4.709159e+08 | Z93: 2.6963244e+09 | AA93: 5.028189e+09 | AB93: 4.0907577e+10 | AC93: 1.863515e+09 | AD93: 9.8349509e+09 | AE93: 7.8506115e+08 | AF93: 4.9427164e+09 | AG93: 5.7999214e+10 | AH93: 1.2193951e+10 | AI93: 5.475005e+09 | AJ93: 9.5089979e+09 | AK93: 1.286388e+10 | AL93: 8.7856366e+09 | AM93: 1.7533343e+09 | AN93: 7.7806336e+09 | AO93: 2.7845798e+09 | AP93: 5.1189118e+09 | AQ93: 6.6831058e+09 | AR93: 1.321508e+09 | AS93: 8.9704674e+08 | AT93: 6.6263963e+09 | AU93: 1.042718e+10 | AV93: 2.9024026e+08 | AW93: -2.5399606e+09 | AX93: 9.1693559e+09 | AY93: 1.114156e+09 | AZ93: 4.8551191e+10 | BA93: 3.2081245e+10 | BB93: 7.7766154e+09 | BC93: 2.4334066e+10 | BD93: 2.3177855e+10 | BE93: 8.1300602e+10 | BF93: 6.662393e+09 | BG93: -3.3157082e+09 | BH93: 3.4414897e+10 | BI93: 1.3339828e+10 | BJ93: 2.6203881e+08 | BK93: 3.7803166e+11 | BL93: 4.1774551e+09 | BM93: 2.9491629e+10 | BN93: 1.1071917e+11 | BO93: 8.5390232e+09 | BP93: 1.8742263e+10 | BQ93: 4.0734945e+09 | BR93: 3.2261509e+09 | BS93: 2.2159367e+10 | BT93: 1.1125704e+10 | BU93: 2.0355146e+09 | BV93: 4.4849226e+09 | BW93: 7.5581829e+09 | BX93: 65076179 | BY93: 5.2784427e+09 | BZ93: 8.4365705e+09 | CA93: 3.2674165e+10 | CB93: 6.1968842e+09 | CC93: -8.432274e+08 | CD93: 3.7074032e+09 | CF93: 1.0147897e+10 | CG93: 7.7633023e+10 | CH93: 3.4282693e+09 | CI93: 4.2515472e+09 | DI93: 1.4147952e+12
A94: 8001 | B94: 2.6958594e+08 | C94: 77448874 | D94: 21601407 | E94: 63411011 | F94: 5.8760081e+08 | G94: 1.2953619e+09 | H94: 1.9881881e+08 | I94: 1.4860121e+08 | J94: 1.1040996e+10 | K94: 3.4029085e+09 | L94: 1.6296063e+09 | M94: 1.9762802e+09 | N94: 34030311 | O94: 37175243 | P94: 86052295 | Q94: 12594988 | R94: 77613831 | S94: 1.4958803e+08 | T94: 1.0165101e+08 | U94: 7.3262378e+08 | V94: 1.9856065e+09 | W94: 1.8720559e+08 | X94: 1.8231006e+08 | Y94: 1.4248793e+08 | Z94: 4.2828302e+08 | AA94: 4.1006894e+08 | AB94: 2.9636627e+09 | AC94: 1.115377e+08 | AD94: 1.0140385e+09 | AE94: 54527816 | AF94: 4.728376e+08 | AG94: 5.9624739e+10 | AH94: 8.7736744e+09 | AI94: 3.1534276e+09 | AJ94: 5.4170499e+09 | AK94: 6.4247155e+09 | AL94: 2.5962633e+09 | AM94: 1.9484314e+09 | AN94: 5.3106008e+09 | AO94: 3.2887739e+09 | AP94: 7.4555294e+09 | AQ94: 4.688705e+09 | AR94: -4.2861306e+08 | AS94: 1.0719238e+08 | AT94: 8.1960528e+08 | AU94: 4.4749986e+08 | AV94: 3.0540725e+08 | AW94: 2.3563402e+08 | AX94: 3.6106051e+08 | AY94: 2.4416498e+08 | AZ94: 1.4573113e+09 | BA94: 2.5227673e+09 | BB94: 2.6132972e+08 | BC94: 7.5384526e+08 | BD94: 9.2662198e+08 | BE94: 1.2687455e+09 | BF94: 1.0325625e+09 | BG94: 1.2953259e+09 | BH94: 1.5096092e+09 | BI94: 5.0028645e+09 | BJ94: 91871067 | BK94: 4.8938604e+10 | BL94: 2.0116747e+09 | BM94: 7.0551999e+08 | BN94: 8.9902243e+09 | BO94: 1.5012212e+09 | BP94: 1.5270799e+09 | BQ94: 6.4725318e+08 | BR94: 1.4464014e+09 | BS94: 2.380639e+09 | BT94: 1.533972e+09 | BU94: 7.9219262e+08 | BV94: -2.8659493e+08 | BW94: 1.1266784e+09 | BX94: 31101453 | BY94: 1.6638725e+09 | BZ94: 1.7032295e+09 | CA94: 1.3861445e+10 | CB94: 5.8509777e+09 | CC94: 1.4043005e+09 | CD94: 4.5486395e+08 | CF94: -7.5275603e+09 | CH94: 2.5227812e+08 | CI94: 3.0992703e+08 | DI94: 2.4611213e+11
A95: 10001 | B95: 6560.9697 | C95: 91407.179 | D95: 26.707966 | E95: 305.39688 | F95: 244.63563 | G95: 54300.637 | H95: 427.20155 | I95: 26173.785 | J95: 455274.52 | K95: 939287.65 | L95: 576033.28 | M95: 134880.6 | N95: 2102.9172 | O95: 8105.0567 | P95: 22410.114 | R95: 32867.125 | S95: 156547.1 | T95: 48661.625 | U95: 1859801.6 | V95: 393553.03 | W95: 116351.58 | X95: 74330.374 | Y95: 1681781.8 | Z95: 292367.84 | AA95: 220495.39 | AB95: 1686360.3 | AC95: 119384.65 | AD95: 498560.62 | AE95: 29334.433 | AF95: 229788.15 | AG95: 1838402.5 | AH95: 32251.067 | AI95: 10328.975 | AJ95: 4246.386 | AK95: 161910.93 | AL95: 49109.217 | AM95: 23665.874 | AN95: 126341.86 | AO95: 64453.752 | AP95: 209512.53 | AQ95: 3457619.7 | AR95: 14517.914 | AS95: 236125.21 | AT95: 300656.75 | AU95: 8793.0508 | AV95: 33373.756 | AW95: 214291.68 | AX95: 47633.414 | AY95: 21574.763 | AZ95: 171135.8 | BA95: 202602.74 | BB95: 76193.85 | BC95: 1121656 | BD95: 219607.4 | BE95: 226677.92 | BF95: 191137.08 | BG95: 6385190.1 | BH95: 334742.33 | BI95: 201905.6 | BJ95: 41936.334 | BK95: 451329.49 | BL95: 212816.58 | BM95: 542249.9 | BN95: 1695834.3 | BO95: 457503.34 | BP95: 277280.88 | BQ95: 26904.238 | BR95: 337655.58 | BU95: 63156.454 | BW95: 291160.03 | BX95: 2792.121 | BY95: 171095.67 | BZ95: 140818.3 | CA95: 596227.38 | CB95: 2269708 | CC95: 596656.54 | CD95: 12768.431 | CF95: 1564.4003 | CJ95: 2.6540744e+09 | CK95: 1.0692078e+08 | CL95: 5.06844e+08 | CN95: 2099252.4 | CO95: 4631180.2 | CP95: 6439285.1 | CQ95: 4628741.6 | CR95: 15970807 | CS95: 26453290 | CT95: 42244654 | CU95: 30852527 | CV95: 1.445381e+08 | CW95: 1.7367832e+10 | CX95: 5820581.6 | CZ95: 5.8972489e+09 | DD95: 8.6737701e+08 | DE95: 4.7407429e+10 | DF95: 7197.224 | DG95: 2.8174869e+08 | DH95: 92967973 | DI95: 7.5500061e+10
A96: 10002 | B96: 8640.0552 | C96: 120372.92 | D96: 35.171371 | E96: 402.17316 | F96: 322.15746 | G96: 71507.799 | H96: 562.57613 | I96: 34467.916 | J96: 599545.06 | K96: 1236935.6 | L96: 758570.7 | M96: 177622.5 | N96: 2769.3042 | O96: 10673.443 | P96: 29511.586 | R96: 43282.287 | S96: 206154.83 | T96: 64081.858 | U96: 2449148.5 | V96: 518264.84 | W96: 153221.88 | X96: 97884.699 | Y96: 2214716.5 | Z96: 385015.38 | AA96: 290367.5 | AB96: 2220745.9 | AC96: 157216.09 | AD96: 656547.96 | AE96: 38630.131 | AF96: 302605.01 | AG96: 2420968.2 | AH96: 42471.009 | AI96: 13602.092 | AJ96: 5592.0103 | AK96: 213218.39 | AL96: 64671.286 | AM96: 31165.28 | AN96: 166377.95 | AO96: 84878.304 | AP96: 275904.32 | AQ96: 4553294.2 | AR96: 19118.451 | AS96: 310950.21 | AT96: 395930.94 | AU96: 11579.454 | AV96: 43949.463 | AW96: 282197.91 | AX96: 62727.821 | AY96: 28411.524 | AZ96: 225366.49 | BA96: 266804.9 | BB96: 100338.68 | BC96: 1477094.2 | BD96: 289198.11 | BE96: 298509.19 | BF96: 251705.92 | BG96: 8408573.3 | BH96: 440817.8 | BI96: 265886.84 | BJ96: 55225.41 | BK96: 594349.91 | BL96: 280255.38 | BM96: 714081.8 | BN96: 2233222 | BO96: 602480.16 | BP96: 365147.57 | BQ96: 35429.84 | BR96: 444654.23 | BU96: 83169.909 | BW96: 383424.84 | BX96: 3676.9077 | BY96: 225313.66 | BZ96: 185441.78 | CA96: 785164.05 | CB96: 2988948.8 | CC96: 785729.19 | CD96: 16814.58 | CF96: 2060.1383 | CJ96: 1.0972528e+10 | CK96: 1.0582147e+09 | CL96: 9.0053323e+08 | CN96: 4567602.7 | CO96: 12406715 | CP96: 18048701 | CQ96: 12226527 | CR96: 44552260 | CS96: 74762646 | CT96: 1.1684161e+08 | CU96: 82562071 | CV96: 4.074986e+08 | CW96: 5.0078033e+10 | CX96: 7665047.8 | CZ96: 1.6983622e+10 | DD96: 2.7238894e+09 | DE96: 2.7293476e+10 | DF96: 9477.9302 | DG96: 3.7599783e+08 | DH96: 1.5681135e+08 | DI96: 1.1136893e+11
A97: 10003 | B97: 7692.57 | C97: 107172.59 | D97: 31.31441 | E97: 358.07007 | F97: 286.82905 | G97: 63666.115 | H97: 500.88294 | I97: 30688.097 | J97: 533797.78 | K97: 1101290.9 | L97: 675384.37 | M97: 158144.07 | N97: 2465.6169 | O97: 9502.9727 | P97: 26275.288 | R97: 38535.867 | S97: 183547.49 | T97: 57054.517 | U97: 2180570.1 | V97: 461430.91 | W97: 136419.27 | X97: 87150.472 | Y97: 1971846.4 | Z97: 342793.85 | AA97: 258525.24 | AB97: 1977214.6 | AC97: 139975.47 | AD97: 584549.63 | AE97: 34393.876 | AF97: 269420.76 | AG97: 2155480.1 | AH97: 37813.556 | AI97: 12110.46 | AJ97: 4978.7795 | AK97: 189836.45 | AL97: 57579.307 | AM97: 27747.635 | AN97: 148132.62 | AO97: 75570.384 | AP97: 245648.11 | AQ97: 4053971.1 | AR97: 17021.885 | AS97: 276850.8 | AT97: 352512.38 | AU97: 10309.628 | AV97: 39129.88 | AW97: 251251.54 | AX97: 55848.966 | AY97: 25295.861 | AZ97: 200652.36 | BA97: 237546.56 | BB97: 89335.35 | BC97: 1315113.2 | BD97: 257484.09 | BE97: 265774.09 | BF97: 224103.36 | BG97: 7486472.8 | BH97: 392476.86 | BI97: 236729.18 | BJ97: 49169.284 | BK97: 529172.34 | BL97: 249522.03 | BM97: 635774.2 | BN97: 1988322.5 | BO97: 536411.02 | BP97: 325104.78 | BQ97: 31544.535 | BR97: 395892.58 | BU97: 74049.335 | BW97: 341377.73 | BX97: 3273.6908 | BY97: 200605.32 | BZ97: 165105.87 | CA97: 699061.43 | CB97: 2661174.9 | CC97: 699564.6 | CD97: 14970.661 | CF97: 1834.2195 | CJ97: 1.8121655e+10 | CK97: 1.9129565e+09 | CL97: 1.6264456e+09 | CN97: 6011619.2 | CO97: 17850156 | CP97: 26390762 | CQ97: 17498836 | CR97: 65036560 | CS97: 1.0963021e+08 | CT97: 1.7005182e+08 | CU97: 1.1873821e+08 | CV97: 5.9704546e+08 | CW97: 3.8462809e+10 | CX97: 6824483.8 | CZ97: 1.2868528e+10 | DD97: 4.1287082e+09 | DE97: 1.1652332e+09 | DF97: 8438.562 | DG97: 3.4031256e+08 | DH97: 1.7802155e+08 | DI97: 7.9979542e+10
A98: 10004 | B98: 5939.589 | C98: 82750.127 | D98: 24.17849 | E98: 276.47315 | F98: 221.46651 | G98: 49157.896 | H98: 386.74186 | I98: 23694.901 | J98: 412156.08 | K98: 850328.97 | L98: 521477.94 | M98: 122106.24 | N98: 1903.7527 | O98: 7337.4376 | P98: 20287.682 | R98: 29754.323 | S98: 141720.73 | T98: 44052.947 | U98: 1683662.3 | V98: 356280.15 | W98: 105332.08 | X98: 67290.644 | Y98: 1522502.5 | Z98: 264678.07 | AA98: 199612.57 | AB98: 1526647.4 | AC98: 108077.89 | AD98: 451342.61 | AE98: 26556.208 | AF98: 208025.22 | AG98: 1664289.8 | AH98: 29196.612 | AI98: 9350.7312 | AJ98: 3844.2165 | AK98: 146576.56 | AL98: 44458.149 | AM98: 21424.511 | AN98: 114376.19 | AO98: 58349.424 | AP98: 189669.88 | AQ98: 3130153.2 | AR98: 13142.942 | AS98: 213762.11 | AT98: 272181.95 | AU98: 7960.2727 | AV98: 30212.972 | AW98: 193996.4 | AX98: 43122.117 | AY98: 19531.446 | AZ98: 154927.75 | BA98: 183414.5 | BB98: 68977.632 | BC98: 1015425.5 | BD98: 198808.68 | BE98: 205209.55 | BF98: 173034.74 | BG98: 5780457.2 | BH98: 303039.33 | BI98: 182783.39 | BJ98: 37964.6 | BK98: 408584.68 | BL98: 192661.01 | BM98: 490894.13 | BN98: 1535224.1 | BO98: 414173.81 | BP98: 251019.98 | BQ98: 24356.174 | BR98: 305676.67 | BU98: 57174.991 | BW98: 263584.66 | BX98: 2527.6829 | BY98: 154891.43 | BZ98: 127481.59 | CA98: 539759.48 | CB98: 2054747 | CC98: 540147.99 | CD98: 11559.15 | CF98: 1416.238 | CJ98: 2.8320765e+10 | CK98: 2.2564016e+09 | CL98: 2.7365894e+09 | CN98: 4059566 | CO98: 11745979 | CP98: 17287588 | CQ98: 11531853 | CR98: 42622602 | CS98: 71757649 | CT98: 1.1153915e+08 | CU98: 78142455 | CV98: 3.9088277e+08 | CW98: 3.7737494e+10 | CX98: 5269322.1 | CZ98: 1.2744278e+10 | DD98: 2.6776698e+09 | DE98: 3.4742039e+09 | DF98: 6515.5845 | DG98: 2.7227901e+08 | DH98: 2.033409e+08 | DI98: 9.1198586e+10
A99: 10005 | B99: 13255.803 | C99: 184679.34 | D99: 53.960854 | E99: 617.02477 | F99: 494.26256 | G99: 109709.17 | H99: 863.11929 | I99: 52881.595 | J99: 919838.01 | K99: 1897739.6 | L99: 1163819.4 | M99: 272513.17 | N99: 4248.7402 | O99: 16375.481 | P99: 45277.461 | R99: 66404.838 | S99: 316288.23 | T99: 98316.093 | U99: 3757548.8 | V99: 795135.73 | W99: 235077.09 | X99: 150177.31 | Y99: 3397877.1 | Z99: 590700.86 | AA99: 445489.56 | AB99: 3407127.5 | AC99: 241205.11 | AD99: 1007293.4 | AE99: 59267.377 | AF99: 464264.67 | AG99: 3714313.9 | AH99: 65160.154 | AI99: 20868.691 | AJ99: 8579.4111 | AK99: 327125.34 | AL99: 99220.41 | AM99: 47814.603 | AN99: 255261.48 | AO99: 130222.56 | AP99: 423299.75 | AQ99: 6985785.3 | AR99: 29332.038 | AS99: 477068.09 | AT99: 607447.8 | AU99: 17765.506 | AV99: 67428.438 | AW99: 432955.55 | AX99: 96238.694 | AY99: 43589.716 | AZ99: 345763.28 | BA99: 409339.18 | BB99: 153942.28 | BC99: 2266197.3 | BD99: 443695.45 | BE99: 457980.75 | BF99: 386173.94 | BG99: 12900657 | BH99: 676314.41 | BI99: 407930.68 | BJ99: 84728.296 | BK99: 911867.47 | BL99: 429975.27 | BM99: 1095563.3 | BN99: 3426268.7 | BO99: 924341.12 | BP99: 560219.13 | BQ99: 54357.404 | BR99: 682200.36 | BU99: 127601.49 | BW99: 588260.61 | BX99: 5641.2097 | BY99: 345682.21 | BZ99: 284509.72 | CA99: 1204619.6 | CB99: 4585724.9 | CC99: 1205486.7 | CD99: 25797.377 | CF99: 3160.7191 | CJ99: 9.2009104e+10 | CK99: 6.6115046e+09 | CL99: 8.3825365e+09 | CN99: 14417263 | CO99: 44955880 | CP99: 67011951 | CQ99: 43952187 | CR99: 1.6500539e+08 | CS99: 2.7877223e+08 | CT99: 4.3079065e+08 | CU99: 2.9898203e+08 | CV99: 1.5175571e+09 | CW99: 7.7258429e+10 | CX99: 11759921 | CZ99: 2.5642722e+10 | DD99: 1.0697564e+10 | DE99: 1.333715e+10 | DF99: 14541.293 | DG99: 6.2679484e+08 | DH99: 5.8625678e+08 | DI99: 2.3809384e+11
A100: 10006 | B100: 45274.227 | C100: 630758.79 | D100: 184.29936 | E100: 2107.403 | F100: 1688.1177 | G100: 374703.66 | H100: 2947.9209 | I100: 180613.22 | J100: 3141639.5 | K100: 6481591 | L100: 3974940.1 | M100: 930748.84 | N100: 14511.262 | O100: 55929.259 | P100: 154641.86 | R100: 226800.87 | S100: 1080259.4 | T100: 335791.43 | U100: 12833633 | V100: 2715728 | W100: 802888.63 | X100: 512919.64 | Y100: 11605201 | Z100: 2017495.6 | AA100: 1521537 | AB100: 11636795 | AC100: 823818.43 | AD100: 3440336.9 | AE100: 202423.4 | AF100: 1585662.1 | AG100: 12685968 | AH100: 222549.75 | AI100: 71275.491 | AJ100: 29302.352 | AK100: 1117272.7 | AL100: 338880.06 | AM100: 163307.28 | AN100: 871826.95 | AO100: 444765.63 | AP100: 1445749.4 | AQ100: 23859439 | AR100: 100181.43 | AS100: 1629391.2 | AT100: 2074693.6 | AU100: 60676.789 | AV100: 230296.9 | AW100: 1478728.1 | AX100: 328696.23 | AY100: 148877.49 | AZ100: 1180929.2 | BA100: 1398068.1 | BB100: 525778.62 | BC100: 7740031.2 | BD100: 1515409.4 | BE100: 1564199.8 | BF100: 1318948.9 | BG100: 44061252 | BH100: 2309902.5 | BI100: 1393257.4 | BJ100: 289383.3 | BK100: 3114416.7 | BL100: 1468549.1 | BM100: 3741816.5 | BN100: 11702170 | BO100: 3157019.6 | BP100: 1913387.5 | BQ100: 185653.74 | BR100: 2330005.5 | BU100: 435813.57 | BW100: 2009161.1 | BX100: 19267.14 | BY100: 1180652.3 | BZ100: 971722.15 | CA100: 4114290.2 | CB100: 15662208 | CC100: 4117251.6 | CD100: 88109.056 | CF100: 10795.205 | CJ100: 1.5797886e+11 | CK100: 1.4077981e+10 | CL100: 1.2034343e+10 | CN100: 30364312 | CO100: 87505744 | CP100: 1.2869832e+08 | CQ100: 85930459 | CR100: 3.1732912e+08 | CS100: 5.3413659e+08 | CT100: 8.3052852e+08 | CU100: 5.8215968e+08 | CV100: 2.9096893e+09 | CW100: 8.0698805e+10 | CX100: 40165150 | CZ100: 2.6032101e+10 | DD100: 1.9966185e+10 | DE100: 8.8948149e+09 | DF100: 49664.724 | DG100: 2.0369867e+09 | DH100: 1.2837411e+09 | DI100: 3.2878453e+11
A101: 10007 | B101: 80064.586 | C101: 1115456.7 | D101: 325.92167 | E101: 3726.808 | F101: 2985.3286 | G101: 662639.55 | H101: 5213.2103 | I101: 319402.98 | J101: 5555789.4 | K101: 11462281 | L101: 7029428.4 | M101: 1645970 | N101: 25662.242 | O101: 98907.332 | P101: 273474.28 | R101: 401082.9 | S101: 1910369.9 | T101: 593825.76 | U101: 22695463 | V101: 4802592 | W101: 1419857.4 | X101: 907065.71 | Y101: 20523059 | Z101: 3567812.5 | AA101: 2690741.3 | AB101: 20578931 | AC101: 1456870.4 | AD101: 6084016.7 | AE101: 357972.88 | AF101: 2804142.4 | AG101: 22434326 | AH101: 393565.05 | AI101: 126046.17 | AJ101: 51819.343 | AK101: 1975825.6 | AL101: 599287.81 | AM101: 288798.53 | AN101: 1541770.4 | AO101: 786539.68 | AP101: 2556715.7 | AQ101: 42193899 | AR101: 177164.48 | AS101: 2881474.6 | AT101: 3668963.4 | AU101: 107303.04 | AV101: 407265.4 | AW101: 2615036.4 | AX101: 581278.34 | AY101: 263280.36 | AZ101: 2088398.1 | BA101: 2472394.4 | BB101: 929806.01 | BC101: 13687752 | BD101: 2679905 | BE101: 2766187.7 | BF101: 2332477.1 | BG101: 77919518 | BH101: 4084915.4 | BI101: 2463887 | BJ101: 511755.94 | BK101: 5507647.6 | BL101: 2597035.6 | BM101: 6617164.2 | BN101: 20694543 | BO101: 5582988 | BP101: 3383704 | BQ101: 328316.82 | BR101: 4120466.3 | BU101: 770708.53 | BW101: 3553073.5 | BX101: 34072.709 | BY101: 2087908.5 | BZ101: 1718428.7 | CA101: 7275860.2 | CB101: 27697618 | CC101: 7281097.3 | CD101: 155815.25 | CF101: 19090.633 | CJ101: 3.2823554e+11 | CK101: 3.2608249e+10 | CL101: 2.2427428e+10 | CN101: 52475766 | CO101: 1.5047479e+08 | CP101: 2.2111202e+08 | CQ101: 1.478089e+08 | CR101: 5.452416e+08 | CS101: 9.1753693e+08 | CT101: 1.427268e+09 | CU101: 1.0011036e+09 | CV101: 4.9984793e+09 | CW101: 1.0419536e+11 | CX101: 71029509 | CZ101: 3.288631e+10 | DD101: 3.4398764e+10 | DE101: 137361.69 | DF101: 87828.901 | DG101: 3.6347531e+09 | DH101: 2.494885e+09 | DI101: 5.7082814e+11
A102: 10008 | B102: 91587.285 | C102: 1275990.6 | D102: 372.82752 | E102: 4263.1611 | F102: 3414.9697 | G102: 758005.02 | H102: 5963.4828 | I102: 365370.68 | J102: 6355365 | K102: 13111904 | L102: 8041086.5 | M102: 1882854 | N102: 29355.489 | O102: 113141.83 | P102: 312832.03 | R102: 458805.77 | S102: 2185305.6 | T102: 679287.71 | U102: 25961739 | V102: 5493769.3 | W102: 1624199.8 | X102: 1037608.4 | Y102: 23476687 | Z102: 4081283.4 | AA102: 3077986.3 | AB102: 23540601 | AC102: 1666539.7 | AD102: 6959613.5 | AE102: 409491.46 | AF102: 3207707.7 | AG102: 25663019 | AH102: 450205.97 | AI102: 144186.42 | AJ102: 59277.056 | AK102: 2260181.6 | AL102: 685535.84 | AM102: 330361.71 | AN102: 1763658.2 | AO102: 899736.55 | AP102: 2924672 | AQ102: 48266341 | AR102: 202661.56 | AS102: 3296169.3 | AT102: 4196991.7 | AU102: 122745.83 | AV102: 465878.05 | AW102: 2991386 | AX102: 664934.5 | AY102: 301171.03 | AZ102: 2388955.2 | BA102: 2828215.3 | BB102: 1063621.4 | BC102: 15657660 | BD102: 3065590.4 | BE102: 3164290.7 | BF102: 2668161.5 | BG102: 89133505 | BH102: 4672806.4 | BI102: 2818483.6 | BJ102: 585406.61 | BK102: 6300294.8 | BL102: 2970794.6 | BM102: 7569490.2 | BN102: 23672851 | BO102: 6386478 | BP102: 3870678.4 | BQ102: 375567.37 | BR102: 4713473.7 | BU102: 881627.02 | BW102: 4064423.1 | BX102: 38976.37 | BY102: 2388395.2 | BZ102: 1965740.8 | CA102: 8322984.2 | CB102: 31683791 | CC102: 8328975 | CD102: 178239.8 | CF102: 21838.11 | CJ102: 2.9644529e+11 | CK102: 3.0861199e+10 | CL102: 2.2385485e+10 | CN102: 46764699 | CO102: 1.2573117e+08 | CP102: 1.8254799e+08 | CQ102: 1.2398339e+08 | CR102: 4.5070151e+08 | CS102: 7.5589797e+08 | CT102: 1.1824329e+09 | CU102: 8.3673486e+08 | CV102: 4.1204963e+09 | CW102: 6.4102839e+10 | CX102: 81251902 | CZ102: 1.9683035e+10 | DD102: 2.7808581e+10 | DE102: 157130.45 | DF102: 100469.02 | DG102: 4.1053816e+09 | DH102: 2.4905469e+09 | DI102: 4.7626284e+11
A103: 10009 | B103: 231740.03 | C103: 3228593.2 | D103: 943.35212 | E103: 10786.924 | F103: 8640.7756 | G103: 1917952.9 | H103: 15089.187 | I103: 924484.33 | J103: 16080752 | K103: 33176581 | L103: 20346073 | M103: 4764118 | N103: 74277.143 | O103: 286278.73 | P103: 791547.68 | R103: 1160899.8 | S103: 5529400.5 | T103: 1718777.4 | U103: 65690058 | V103: 13900688 | W103: 4109654.6 | X103: 2625423.3 | Y103: 59402221 | Z103: 10326725 | AA103: 7788118.3 | AB103: 59563938 | AC103: 4216785.6 | AD103: 17609661 | AE103: 1036121.6 | AF103: 8116347.8 | AG103: 64934219 | AH103: 1139140 | AI103: 364829.74 | AJ103: 149986.61 | AK103: 5718856.4 | AL103: 1734586.8 | AM103: 835902.39 | AN103: 4462521.3 | AO103: 2276571.1 | AP103: 7400192.7 | AQ103: 1.2212659e+08 | AR103: 512787.28 | AS103: 8340179.2 | AT103: 10619498 | AU103: 310579.37 | AV103: 1178794.5 | AW103: 7568996.9 | AX103: 1682459.9 | AY103: 762042.26 | AZ103: 6044687.8 | BA103: 7156131.8 | BB103: 2691243.1 | BC103: 39618016 | BD103: 7756753.5 | BE103: 8006491.3 | BF103: 6751153.3 | BG103: 2.2553131e+08 | BH103: 11823435 | BI103: 7131508.1 | BJ103: 1481233.4 | BK103: 15941410 | BL103: 7516895.1 | BM103: 19152810 | BN103: 59898566 | BO103: 16159476 | BP103: 9793838.8 | BQ103: 950284.66 | BR103: 11926334 | BU103: 2230749.3 | BW103: 10284064 | BX103: 98620.513 | BY103: 6043270.7 | BZ103: 4973843.5 | CA103: 21059349 | CB103: 80168362 | CC103: 21074507 | CD103: 450993.79 | CF103: 55256.187 | CJ103: 9.3653305e+11 | CK103: 1.6210642e+11 | CL103: 1.0955107e+11 | CN103: 2.4707e+08 | CO103: 7.6852194e+08 | CP103: 1.1451127e+09 | CQ103: 7.514635e+08 | CR103: 2.8197566e+09 | CS103: 4.7633815e+09 | CT103: 7.3622697e+09 | CU103: 5.1111575e+09 | CV103: 2.5931027e+10 | CW103: 1.8470775e+11 | CX103: 2.0558878e+08 | CZ103: 4.779626e+10 | DD103: 1.8772422e+11 | DE103: 397581.55 | DF103: 254213.17 | DG103: 1.0511567e+10 | DH103: 7.1590775e+09 | DI103: 1.696394e+12
A104: 11001 | B104: 1781144.7 | C104: 1950537.8 | D104: 194757.2 | E104: 681.66955 | F104: 1225.1267 | G104: 138119.6 | H104: 9715.3302 | I104: 59339.695 | J104: 1753691.4 | K104: 2570260.5 | L104: 18246604 | M104: 899607.23 | N104: 52208.962 | O104: 19112.723 | P104: 317669.9 | Q104: 4837.1577 | R104: 2167954.1 | S104: 444535.84 | T104: 122467.93 | U104: 4207347.5 | V104: 2561874.2 | W104: 580307.16 | X104: 204245.43 | Y104: 3757244 | Z104: 689299.48 | AA104: 503542.55 | AB104: 3905183.2 | AC104: 277358.82 | AD104: 1148853.9 | AE104: 89970.704 | AF104: 708092.65 | AG104: 4235581.7 | AH104: 155505.42 | AI104: 24419.717 | AJ104: 14731.556 | AK104: 453340.8 | AL104: 119469.43 | AM104: 91862.373 | AN104: 294684.75 | AO104: 156930.06 | AP104: 508460.65 | AQ104: 7691117.5 | AR104: 32627.909 | AS104: 527107.72 | AT104: 710263.14 | AU104: 25236.778 | AV104: 81341.909 | AW104: 480214.69 | AX104: 106767.04 | AY104: 69232.069 | AZ104: 386614.65 | BA104: 460676.95 | BB104: 174843.94 | BC104: 2510942.6 | BD104: 520774.89 | BE104: 529629.89 | BF104: 428187.97 | BG104: 14210410 | BH104: 762922.73 | BI104: 453853.27 | BJ104: 118582.82 | BK104: 1526898.5 | BL104: 488794.37 | BM104: 1210499.9 | BN104: 4028568.1 | BO104: 1053840.1 | BP104: 1114630.7 | BQ104: 76168.66 | BR104: 822757.65 | BS104: 59484.578 | BT104: 59132.201 | BU104: 176866.31 | BV104: 31542.039 | BW104: 659536.46 | BX104: 8461.7034 | BY104: 427296.13 | BZ104: 377278.73 | CA104: 1651848.9 | CB104: 5076878.4 | CC104: 1352257.2 | CD104: 50926.187 | CF104: 446467.09 | CH104: 73077.075 | CI104: 42041.851 | CJ104: 2.4295242e+11 | CK104: 1.1254187e+10 | CL104: 9.5963432e+09 | CM104: 1.1802374e+10 | CN104: -3.7333521e+09 | CO104: -4.0167278e+09 | CP104: -3.4240603e+09 | CQ104: -2.255377e+09 | CR104: 3.7732383e+09 | CS104: 8.2052794e+09 | CT104: 3.6635583e+10 | CU104: 4.8505404e+10 | CV104: 2.7898545e+11 | CW104: 556556.67 | CX104: 13028099 | CZ104: 1115867.3 | DA104: 134515.86 | DB104: 141592.73 | DD104: 6.7128125e+10 | DE104: 2.441329e+11 | DF104: 105758.83 | DG104: 5.1444351e+09 | DH104: 2.2293152e+08 | DI104: 9.5503076e+11
A105: 11002 | CW105: 1.1087429e+11 | DI105: 1.1087429e+11
A106: 11003 | B106: 18059.617 | C106: 251605.9 | D106: 73.515907 | E106: 840.63043 | F106: 673.38001 | G106: 149467.04 | H106: 1175.908 | I106: 72045.531 | J106: 1253181.2 | K106: 2585467.8 | L106: 1585579.8 | M106: 371270.13 | N106: 5788.4553 | O106: 22309.846 | P106: 61685.711 | R106: 90469.507 | S106: 430908.97 | T106: 133945.19 | U106: 5119259.4 | V106: 1083287.6 | W106: 320267.46 | X106: 204600.57 | Y106: 4629245.1 | Z106: 804766.91 | AA106: 606932 | AB106: 4641847.8 | AC106: 328616.23 | AD106: 1372329.8 | AE106: 80745.478 | AF106: 632511.09 | AG106: 5060356.5 | AH106: 88773.758 | AI106: 28431.366 | AJ106: 11688.532 | AK106: 445673.37 | AL106: 135177.22 | AM106: 65142.296 | AN106: 347766.54 | AO106: 177414.34 | AP106: 576700.76 | AQ106: 9517387.2 | AR106: 39961.772 | AS106: 649954.38 | AT106: 827582.82 | AU106: 24203.607 | AV106: 91864.053 | AW106: 589855.75 | AX106: 131114.95 | AY106: 59386.338 | AZ106: 471065.58 | BA106: 557680.97 | BB106: 209729.94 | BC106: 3087452 | BD106: 604487.72 | BE106: 623949.91 | BF106: 526120.79 | BG106: 17575769 | BH106: 921406.24 | BI106: 555762.03 | BJ106: 115433.26 | BK106: 1242322.1 | BL106: 585795.43 | BM106: 1492588.2 | BN106: 4667925.5 | BO106: 1259316.2 | BP106: 763238.8 | BQ106: 74056.164 | BR106: 929425.21 | BU106: 173843.42 | BW106: 801442.32 | BX106: 7685.5464 | BY106: 470955.14 | BZ106: 387614.14 | CA106: 1641165.7 | CB106: 6247561 | CC106: 1642347 | CD106: 35146.174 | CF106: 4306.1426 | CN106: 3085919.8 | CO106: 3328566.1 | CP106: 3436285.4 | CQ106: 3586117 | CR106: 8839864.1 | CS106: 13195926 | CT106: 24882152 | CU106: 22309617 | CV106: 73589817 | CW106: 651670 | CX106: 16021637 | DE106: 4.3391392e+10 | DF106: 19810.961 | DG106: 7.7068624e+08 | DH106: 2.2230929e+08 | DI106: 4.4650738e+10
...

Sheet industry_code_list
A1: PayingCode | B1: PayingDescription | G1: ** Generated in R to match industry code with industry description so the SAM has the industry description in place of the number
A2: 1 | B2: 111 - Crop Production
A3: 2 | B3: 112 - Animal Production and Aquaculture
A4: 3 | B4: 113 - Forestry and Logging
A5: 4 | B5: 114 - Fishing, Hunting and Trapping
A6: 5 | B6: 115 - Support Activities for Agriculture and Forestry
A7: 6 | B7: 211 - Oil and Gas Extraction
A8: 7 | B8: 212 - Mining (except Oil and Gas)
A9: 8 | B9: 213 - Support Activities for Mining
A10: 9 | B10: 221 - Utilities
A11: 10 | B11: 23 - Construction
A12: 11 | B12: 311 - Food Manufacturing
A13: 12 | B13: 312 - Beverage and Tobacco Product Manufacturing
... A112: 28001 | B112: Domestic Trade

Sheet SAM_orig
B1: 111 - Crop Production | C1: 112 - Animal Production and Aquaculture | D1: 113 - Forestry and Logging | E1: 114 - Fishing, Hunting and Trapping | F1: 115 - Support Activities for Agriculture and Forestry | G1: 211 - Oil and Gas Extraction | H1: 212 - Mining (except Oil and Gas) | I1: 213 - Support Activities for Mining | J1: 221 - Utilities | K1: 23 - Construction | L1: 311 - Food Manufacturing | M1: 312 - Beverage and Tobacco Product Manufacturing | N1: 313 - Textile Mills | O1: 314 - Textile Product Mills | P1: 315 - Apparel Manufacturing | Q1: 316 - Leather and Allied Product Manufacturing | R1: 321 - Wood Product Manufacturing | S1: 322 - Paper Manufacturing | T1: 323 - Printing and Related Support Activities | U1: 324 - Petroleum and Coal Products Manufacturing | V1: 325 - Chemical Manufacturing | W1: 326 - Plastics and Rubber Products Manufacturing | X1: 327 - Nonmetallic Mineral Product Manufacturing | Y1: 331 - Primary Metal Manufacturing | Z1: 332 - Fabricated Metal Product Manufacturing | AA1: 333 - Machinery Manufacturing | AB1: 334 - Computer and Electronic Product Manufacturing | AC1: 335 - Electrical Equipment, Appliance, and Component Manufacturing | AD1: 336 - Transportation Equipment Manufacturing | AE1: 337 - Furniture and Related Product Manufacturing | AF1: 339 - Miscellaneous Manufacturing | AG1: 42 - Wholesale Trade | AH1: 441 - Motor Vehicle and Parts Dealers | AI1: 449 - Furniture, Home Furnishings, Electronics, and Appliance Retailers | AJ1: 444 - Building Material and Garden Equipment and Supplies Dealers | AK1: 445 - Food and Beverage Stores | AL1: 446 - Health and Personal Care Stores | AM1: 457 - Gasoline Stations and Fuel Dealers | AN1: 458 - Clothing, Clothing Accessories, Shoe, and Jewelry Retailers | AO1: 459 - Sporting Goods, Hobby, Musical Instrument, Book, and Miscellaneous Retailers | AP1: 455 - General Merchandise Retailers | AQ1: 481 - Air Transportation | AR1: 482 - Rail Transportation | AS1: 483 - Water Transportation | AT1: 484 - Truck Transportation | AU1: 485 - Transit and Ground Passenger Transportation | AV1: 486 - Pipeline Transportation | AW1: 487-488 - Scenic and Sightseeing Transportation and Support Activities for Transportation | AX1: 492 - Couriers and Messengers | AY1: 493 - Warehousing and Storage | AZ1: 513 - Publishing Industries | BA1: 512 - Motion Picture and Sound Recording Industries | BB1: 516 - Broadcasting and Content Providers | BC1: 517 - Telecommunications | BD1: 518 - Computing Infrastructure Providers, Data Processing, Web Hosting, and Related Services | BE1: 519 - Web Search Portals, Libraries, Archives, and Other Information Services | BF1: 522 - Credit Intermediation and Related Activities | BG1: 523 - Securities, Commodity Contracts, and Other Financial Investments and Related Activities | BH1: 521 - Monetary Authorities-Central Bank | BI1: 524 - Insurance Carriers and Related Activities | BJ1: 525 - Funds, Trusts, and Other Financial Vehicles | BK1: 531 - Real Estate | BL1: 532 - Rental and Leasing Services | BM1: 533 - Lessors of Nonfinancial Intangible Assets (except Copyrighted Works) | BN1: 541 - Professional, Scientific, and Technical Services | BO1: 551 - Management of Companies and Enterprises | BP1: 561 - Administrative and Support Services | BQ1: 562 - Waste Management and Remediation Services | BR1: 611 - Educational Services | BS1: 621 - Ambulatory Health Care Services | BT1: 622 - Hospitals | BU1: 623 - Nursing and Residential Care Facilities | BV1: 624 - Social Assistance | BW1: 711 - Performing Arts, Spectator Sports, and Related Industries | BX1: 712 - Museums, Historical Sites, and Similar Institutions | BY1: 713 - Amusement, Gambling, and Recreation Industries | BZ1: 721 - Accommodation | CA1: 722 - Food Services and Drinking Places | CB1: 811 - Repair and Maintenance | CC1: 812 - Personal and Laundry Services | CD1: 813 - Religious, Grantmaking, Civic, Professional, and Similar Organizations | CE1: 814 - Private Households | CF1: 9A - Government Enterprises | CG1: 9B - Administrative Government | CH1: Vegetable and melon farming | CI1: Fruit farming | CJ1: Employee Compensation | CK1: Proprietor Income | CL1: Other Property Type Income | CM1: Tax on Production and Imports | CN1: Households LT15k | CO1: Households 15-30k | CP1: Households 30-40k | CQ1: Households 40-50k | CR1: Households 50-70k | CS1: Households 70-100k | CT1: Households 100-150k | CU1: Households 150-200k | CV1: Households GT200k | CW1: Federal Government NonDefense | CX1: Federal Government Defense | CY1: Federal Government Investment | CZ1: State/Local Govt Other | DA1: State/Local Govt Education | DB1: State/Local Govt Hospital & Health Services | DC1: State/Local Govt Investment | DD1: Enterprises (Corporations) | DE1: Capital | DF1: Inventory Additions/Deletions | DG1: Foreign Trade | DH1: Domestic Trade | DI1: Total
A2: 111 - Crop Production | B2: 3.5000368e+08 | C2: 3.3876685e+08 | D2: 6476600.7 | E2: 177.57912 | F2: 119434.91 | H2: 388693.05 | I2: 89626.476 | J2: 5018.2717 | K2: 77333386 | L2: 3.1613548e+09 | M2: 88518566 | N2: 8898969.3 | O2: 307.24735 | P2: 8624970.8 | Q2: 147370.67 | R2: 67456209 | S2: 2572527 | T2: 169451.31 | U2: 740.96881 | V2: 2.8777525e+08 | W2: 9412174.4 | X2: 39748.938 | Y2: 4018.08 | Z2: 3238.0838 | AA2: 3920.8077 | AB2: 41106.795 | AC2: 4074.6214 | AD2: 16024.14 | AE2: 721216.84 | AF2: 14726032 | AG2: 2276261.9 | AH2: 12539322 | AI2: 1711.7622 | AJ2: 2715.3615 | AK2: 7745341.4 | AL2: 2875.9914 | AM2: 4764014.2 | AN2: 3176.8186 | AO2: 15981.199 | AP2: 543367.16 | AR2: 13294.19 | AT2: 4668.8731 | AV2: 29.10344 | AW2: 24807.807 | AX2: 140.96415 | AY2: 2429.0103 | AZ2: 3389.2414 | BA2: 4593.5178 | BB2: 3541.7297 | BC2: 13101.164 | BD2: 48360.45 | BE2: 14600.84 | BF2: 12127.848 | BG2: 31166.779 | BH2: 49524.649 | BI2: 2904.097 | BJ2: 3422.3683 | BK2: 540085.91 | BL2: 20402.651 | BN2: 27273529 | BO2: 341187.06 | BP2: 92326280 | BQ2: 4089.2611 | BR2: 1940220.3 | BS2: 39002.765 | BT2: 4749.1152 | BU2: 3462.7923 | BV2: 24264.339 | BW2: 31906.65 | BY2: 2756045.3 | BZ2: 430027.85 | CA2: 2869076.2 | CB2: 3836.6812 | CC2: 2983.8288 | CD2: 607244.8 | CF2: 40110.761 | CH2: 17115400 | CI2: 14958024 | CN2: 55011829 | CO2: 62071826 | CP2: 51558299 | CQ2: 60737985 | CR2: 1.5131388e+08 | CS2: 2.028119e+08 | CT2: 3.495471e+08 | CU2: 2.7335106e+08 | CV2: 5.8357399e+08 | CW2: 4969562.8 | CX2: 1635.6765 | CY2: 82.413125 | CZ2: 1.6760034e+08 | DA2: 8089421.3 | DB2: 2377363.6 | DE2: 252771.23 | DF2: 6587933.5 | DG2: 6.3422223e+09 | DH2: 6.3286632e+09 | DI2: =SUM(B2:DH2) -> 1.9263875e+10
A3: 112 - Animal Production and Aquaculture | B3: 20004131 | C3: 2.2761685e+09 | D3: 280654.08 | E3: 194.50563 | F3: 832586.67 | H3: 1.1188251 | I3: 185.11211 | J3: 5588.7798 | K3: 17730.175 | L3: 9.551859e+09 | M3: 309073.33 | N3: 1713479 | O3: 5075172.9 | P3: 73504.49 | Q3: 1255.9354 | R3: 572851.41 | S3: 22768.848 | T3: 2438.5706 | U3: 825.20671 | V3: 37515.769 | W3: 81566.014 | X3: 2138.1401 | Y3: 410.55086 | Z3: 2558.1698 | AA3: 679.98761 | AB3: 655.11861 | AD3: 788.40956 | AE3: 6113.9405 | AF3: 1247973.5 | AG3: 88381.355 | AH3: 700.08895 | AI3: 1659.9098 | AJ3: 2569.8864 | AK3: 4660.1209 | AL3: 43.987443 | AM3: 3917.8432 | AN3: 62.280961 | AO3: 15684.617 | AP3: 102003.95 | AW3: 362728.33 | AY3: 157.13938 | AZ3: 3400.3708 | BA3: 2955.1556 | BB3: 297.38853 | BC3: 5601.4112 | BD3: 30357.854 | BE3: 9846.3995 | BF3: 13102.268 | BG3: 34620.456 | BH3: 21624.741 | BI3: 3234.2526 | BJ3: 3811.4442 | BK3: 146.6861 | BL3: 12274.585 | BN3: 1.7148299e+08 | BO3: 2023212.5 | BP3: 1070195.1 | BQ3: 4276.8112 | BR3: 6709281.6 | BS3: 36249.125 | BT3: 1325.687 | BU3: 3814.0673 | BV3: 13658.92 | BW3: 35411.105 | BY3: 36490752 | BZ3: 2358002.9 | CA3: 3.1742412e+08 | CB3: 1680.5171 | CC3: 3002.8924 | CD3: 178132.95 | CF3: 34057.747 | CH3: 23836904 | CI3: 53965282 | CN3: 72814811 | CO3: 73927106 | CP3: 59091510 | CQ3: 66499060 | CR3: 1.5981715e+08 | CS3: 1.9798674e+08 | CT3: 3.1023926e+08 | CU3: 2.4604752e+08 | CV3: 4.8388357e+08 | CW3: 131.95518 | CX3: 2140964.2 | CZ3: 99671832 | DA3: 2954875.4 | DB3: 38809810 | DF3: 57306791 | DG3: 45033692 | DH3: 3.5655686e+09 | DI3: =SUM(B3:DH3) -> 1.795651e+10
A4: 113 - Forestry and Logging | B4: 26271.042 | C4: 25724.501 | D4: 18717017 | F4: 6178.0757 | H4: 421.35742 | I4: 6.8234766 | K4: 5849.4683 | L4: 78494312 | M4: 14372046 | N4: 680.95768 | P4: 25732145 | Q4: 439672.61 | R4: 2.0032159e+08 | S4: 7649702.5 | T4: 502738.93 | V4: 12986809 | W4: 28046349 | X4: 101741.61 | AE4: 1896971.7 | AF4: 12507925 | AG4: 163.18034 | AH4: 959.32346 | AK4: 591.30149 | AM4: 364.23302 | AP4: 41.405001 | AW4: 1.8684839 | BH4: 2.2649789 | BK4: 28.635415 | BN4: 4284158.4 | BO4: 16.253479 | BP4: 301460.37 | BR4: 345652.34 | BY4: 206.54916 | BZ4: 28.940259 | CA4: 208.20818 | CD4: 45.365127 | CH4: 435.11688 | CN4: 4072.2602 | CO4: 4560.4275 | CP4: 3774.9107 | CQ4: 4500.5543 | CR4: 11307.096 | CS4: 15129.226 | CT4: 25903.501 | CU4: 20151.828 | CV4: 43258.42 | CW4: 380.22431 | CZ4: 12202.281 | DA4: 614.93822 | DB4: 181.56374 | DF4: 5845719.3 | DG4: 81326849 | DH4: 3.1255143e+08 | DI4: =SUM(B4:DH4) -> 8.0663856e+08
A5: 114 - Fishing, Hunting and Trapping | L5: 44900790 | V5: 69107.703 | AK5: 4618407.2 | AW5: 2999.5721 | BN5: 401153.58 | BR5: 584992.13 | BY5: 2253892.2 | BZ5: 3517546.3 | CA5: 63700216 | CD5: 1333627.6 | CF5: 1312.8851 | CN5: 7051647 | CO5: 5413076.1 | CP5: 3636610.1 | CQ5: 6670115.3 | CR5: 6224911.4 | CS5: 13966019 | CT5: 21297172 | CU5: 11960842 | CV5: 27860890 | CZ5: 3353589.7 | DA5: 463624.1 | DB5: 5535505.4 | DF5: 94697.441 | DG5: 79598687 | DH5: 2596621.2 | DI5: =SUM(B5:DH5) -> 3.1710805e+08
A6: 115 - Support Activities for Agriculture and Forestry | B6: 1.0714269e+09 | C6: 4.1503957e+08 | D6: 32537106 | E6: 27856.389 | BN6: 97216934 | BO6: 3227933.2 | CH6: 1.8278219e+09 | CI6: 2.3946997e+09 | CN6: 1933651.5 | CO6: 2132879.7 | CP6: 1945303.5 | CQ6: 1986615.9 | CR6: 5350634 | CS6: 4735380.8 | CT6: 6753597.8 | CU6: 6411981.5 | CV6: 12130747 | CZ6: 1.268897e+09 | DG6: 36054973 | DH6: 7.5741902e+09 | DI6: =SUM(B6:DH6) -> 1.4764521e+10
A7: 211 - Oil and Gas Extraction | B7: 4173471.3 | C7: 3992392.6 | D7: 2679.2508 | E7: 3947.16 | F7: 2106.7942 | G7: 1.1734962e+08 | H7: 1086431.2 | I7: 454602.43 | J7: 4.9639964e+08 | K7: 95129386 | L7: 3677437.2 | M7: 880453.02 | N7: 64010.425 | O7: 32608.021 | P7: 153.20238 | Q7: 6737.2681 | R7: 1111648.7 | S7: 1217828.1 | T7: 675249.88 | U7: 6.3241975e+09 | V7: 26551719 | W7: 993644.59 | X7: 1279687.4 | Y7: 887570.29 | Z7: 1702004.1 | AA7: 1036274.6 | AB7: 2320499.2 | AC7: 1521050.5 | AD7: 867972.7 | AE7: 394673.17 | AF7: 1941835.3 | AG7: 8608050.2 | AH7: 878486.72 | AI7: 30152.575 | AJ7: 308016.02 | AK7: 624983.79 | AL7: 91788.658 | AM7: 207143.1 | AN7: 180610.51 | AO7: 277254.27 | AP7: 300796.33 | AQ7: 41965872 | AR7: 3907900.1 | AS7: 5099197.7 | AT7: 37430550 | AU7: 8081658.5 | AV7: 274518.45 | AW7: 824425.28 | AX7: 3132621.1 | AY7: 7902867.2 | AZ7: 250131.29 | BA7: 268527.03 | BB7: 96285.86 | BC7: 693525.19 | BD7: 1382398.6 | BE7: 828582.44 | BF7: 3093071.6 | BG7: 7259110.9 | BH7: 3059569.7 | BI7: 41443.823 | BJ7: 1333657.5 | BK7: 15023625 | BL7: 3361524.8 | BM7: 770187.84 | BN7: 7023835.7 | BO7: 1385774.9 | BP7: 9579894 | BQ7: 3170632.5 | BR7: 7916522 | BS7: 1712190.7 | BT7: 1917450.9 | BU7: 1280094.5 | BV7: 1585246.9 | BW7: 494327.32 | BX7: 87378.599 | BY7: 2009157.3 | BZ7: 1584805 | CA7: 8264881.8 | CB7: 2400186.4 | CC7: 1211546.7 | CD7: 2530051.2 | CF7: 4.0166575e+08 | CH7: 2946357.4 | CI7: 1792671.5 | CN7: 10406658 | CO7: 12921015 | CP7: 11759338 | CQ7: 13101844 | CR7: 33554073 | CS7: 42534635 | CT7: 68828495 | CU7: 47798846 | CV7: 91764559 | CW7: 973700.29 | CX7: 38760719 | CY7: 706.8717 | CZ7: 1.6800776e+08 | DA7: 54161177 | DB7: 12648041 | DC7: 8886.1661 | DE7: 2950874.4 | DF7: 8036498.2 | DG7: 3.5387288e+09 | DH7: 1.0938401e+08 | DI7: =SUM(B7:DH7) -> 1.1974433e+10
A8: 212 - Mining (except Oil and Gas) | B8: 9474926.3 | C8: 7329170.8 | D8: 14.339965 | E8: 51.079472 | F8: 5147.4062 | G8: 1650095.8 | H8: 73517378 | I8: 407615.43 | J8: 4.2419714e+08 | K8: 6.4168298e+08 | L8: 46566718 | M8: 7635269.1 | N8: 1524454.2 | O8: 542278.08 | P8: 5511.2412 | Q8: 13090.29 | R8: 575234.69 | S8: 12143291 | T8: 519176.67 | U8: 92341707 | V8: 1.6892475e+08 | W8: 8402869.8 | X8: 3.3882914e+08 | Y8: 1.5165705e+08 | Z8: 19911855 | AA8: 3640828.6 | AB8: 3881332.4 | AC8: 3288312.4 | AD8: 6066007.6 | AE8: 601637.04 | AF8: 6328362.7 | AG8: 1744137.9 | AH8: 21326.031 | AI8: 2534.9646 | AJ8: 3611.2322 | AK8: 11315.647 | AL8: 5744.4173 | AM8: 3044.1958 | AN8: 89210.798 | AO8: 23750.903 | AP8: 4149.7976 | AQ8: 224704.79 | AR8: 1718616.2 | AS8: 27881.044 | AT8: 460999.48 | AU8: 137584.05 | AV8: 985.22414 | AW8: 30205.093 | AX8: 17709.357 | AY8: 160340.23 | AZ8: 364096.77 | BA8: 1746912.4 | BB8: 6520385.5 | BC8: 4112023.5 | BD8: 2304796.4 | BE8: 55596390 | BF8: 18983.009 | BG8: 48209.966 | BH8: 20342.839 | BI8: 3163.0036 | BJ8: 7138.0407 | BK8: 2300278.5 | BL8: 98644.168 | BM8: 13698.753 | BN8: 68273966 | BO8: 1565871 | BP8: 38510155 | BQ8: 3449983.3 | BR8: 28049653 | BS8: 3544068 | BT8: 5161848.4 | BU8: 1502522.6 | BV8: 1343949.7 | BW8: 14228143 | BX8: 76538.767 | BY8: 30922493 | BZ8: 5423069.2 | CA8: 42203720 | CB8: 8646329.1 | CC8: 38043453 | CD8: 10145497 | CF8: 2.2620616e+08 | CH8: 7449937.5 | CI8: 3573634.5 | CN8: 1172916.5 | CO8: 2095126.3 | CP8: 1623258.6 | CQ8: 1918456.8 | CR8: 5134694.3 | CS8: 4886285.9 | CT8: 7586122.3 | CU8: 5448868.2 | CV8: 10902208 | CW8: 41934868 | CX8: 1553355.9 | CZ8: 98187380 | DA8: 11536933 | DB8: 37856241 | DE8: 45728851 | DF8: 763619.76 | DG8: 3.0248288e+08 | DH8: 6.4395417e+08 | DI8: =SUM(B8:DH8) -> 3.8725935e+09
A9: 213 - Support Activities for Mining | B9: 3959.0695 | C9: 13529.36 | D9: 1.675336 | E9: 12.517858 | F9: 3.171165 | G9: 13164549 | H9: 545444.29 | I9: 725832.3 | J9: 20392.903 | K9: 1333632 | L9: 140842.32 | M9: 100865.18 | N9: 1431.7779 | O9: 1770.5807 | P9: 368.91522 | Q9: 263.05178 | R9: 24880.823 | S9: 30373.594 | T9: 7272.4445 | U9: 29302.741 | V9: 78968.955 | W9: 48947.132 | X9: 19298.536 | Y9: 22232.738 | Z9: 364025.89 | AA9: 178233.3 | AB9: 475936.74 | AC9: 125128.52 | AD9: 317739.76 | AE9: 38292.422 | AF9: 75599.448 | AG9: 33080.843 | AH9: 2554.2504 | AI9: 441.60212 | AJ9: 372.68977 | AK9: 1527.4506 | AL9: 584.49818 | AM9: 580.45027 | AN9: 870.7237 | AO9: 4296.3859 | AP9: 834.73487 | AQ9: 28734.847 | AR9: 4597.1657 | AS9: 23567.723 | AT9: 44958.134 | AU9: 13703.428 | AV9: 26270.727 | AW9: 1344.6081 | AX9: 2529.7969 | AY9: 11172.152 | AZ9: 9199.0878 | BA9: 707.65986 | BB9: 40615.584 | BC9: 51165.779 | BD9: 20611.203 | BE9: 11843.998 | BF9: 2904.4227 | BG9: 6624.096 | BH9: 2716.4885 | BI9: 25.704051 | BJ9: 1112.2656 | BK9: 36702.722 | BL9: 23620.23 | BM9: 481.59859 | BN9: 226095.85 | BO9: 10420.668 | BP9: 34368.506 | BQ9: 41367.696 | BR9: 9582.5012 | BS9: 5883.4643 | BT9: 11133.869 | BU9: 1023.0809 | BV9: 28977.046 | BW9: 990.17243 | BX9: 71.288276 | BY9: 6224.644 | BZ9: 13829.528 | CA9: 46778.283 | CB9: 74239.461 | CC9: 3631.2883 | CD9: 12379.3 | CF9: 191278.24 | CH9: 3855.5697 | CI9: 2302.4113 | CN9: 12742.533 | CO9: 17100.902 | CP9: 14758.709 | CQ9: 16370.687 | CR9: 46653.842 | CS9: 56951.927 | CT9: 87470.318 | CU9: 66331.879 | CV9: 150903.15 | CW9: 4290.6708 | CX9: 170422.64 | CY9: 3539.2473 | CZ9: 192407.19 | DA9: 38073.062 | DB9: 21664.489 | DC9: 1757.1463 | DE9: 2.5938345e+09 | DF9: 37061.429 | DG9: 5830053 | DH9: 3711990.5 | DI9: =SUM(B9:DH9) -> 2.623339e+09
A10: 221 - Utilities | B10: 1.4283748e+08 | C10: 1.0755043e+08 | D10: 23327.794 | E10: 13537.649 | F10: 92923.83 | G10: 1.0399539e+08 | H10: 40465758 | I10: 4084343.6 | J10: 4.4203523e+09 | K10: 5.5767854e+08 | L10: 3.9651955e+08 | M10: 79381037 | N10: 14151332 | O10: 6359190.8 | P10: 1027474.2 | Q10: 910010.85 | R10: 66275230 | S10: 1.0042095e+08 | T10: 52174993 | U10: 4.5453456e+08 | V10: 6.5114819e+08 | W10: 1.7636253e+08 | X10: 2.1976898e+08 | Y10: 1.0477778e+08 | Z10: 2.3444034e+08 | AA10: 79814024 | AB10: 9.287127e+08 | AC10: 71595599 | AD10: 2.4047652e+08 | AE10: 29963409 | AF10: 82007185 | AG10: 8.7304869e+08 | AH10: 1.2284053e+08 | AI10: 8875751.3 | AJ10: 32174351 | AK10: 3.213472e+08 | AL10: 62776905 | AM10: 90652003 | AN10: 83837751 | AO10: 82873666 | AP10: 2.3777379e+08 | AQ10: 14431954 | AR10: 2051014.5 | AS10: 15620286 | AT10: 2.6022516e+08 | AU10: 36245665 | AV10: 42612105 | AW10: 21525795 | AX10: 5597721.4 | AY10: 1.2901885e+08 | AZ10: 36666023 | BA10: 61966723 | BB10: 32353697 | BC10: 1.0061746e+08 | BD10: 1.9811272e+08 | BE10: 1.5473887e+08 | BF10: 20708752 | BG10: 84196153 | BH10: 1.1178399e+08 | BI10: 29463542 | BJ10: 1.5090145e+08 | BK10: 3.1182426e+09 | BL10: 99219174 | BM10: 34679836 | BN10: 4.795557e+08 | BO10: 2.129807e+08 | BP10: 1.6872126e+08 | BQ10: 1.0019787e+08 | BR10: 3.2324623e+08 | BS10: 3.6106567e+08 | BT10: 3.3386568e+08 | BU10: 1.9133307e+08 | BV10: 91717044 | BW10: 69914978 | BX10: 13666927 | BY10: 1.8243285e+08 | BZ10: 3.5453467e+08 | CA10: 1.4243752e+09 | CB10: 1.795332e+08 | CC10: 1.5469271e+08 | CD10: 1.0966294e+08 | CF10: 2.65235e+09 | CH10: 2.6341445e+08 | CI10: 2.5045239e+08 | CN10: 6.9080499e+08 | CO10: 8.9427861e+08 | CP10: 7.396153e+08 | CQ10: 7.7582238e+08 | CR10: 1.7233254e+09 | CS10: 2.0577241e+09 | CT10: 3.1371771e+09 | CU10: 2.2148899e+09 | CV10: 4.487042e+09 | CW10: 29960511 | CX10: 4.6652907e+08 | CZ10: 1.6784246e+09 | DA10: 4.7132635e+08 | DB10: 5.8407238e+08 | DG10: 3.1988444e+08 | DH10: 4.8872472e+10 | DI10: =SUM(B10:DH10) -> 9.3106158e+10
A11: 23 - Construction | B11: 46657718 | C11: 19524971 | E11: 12576.927 | F11: 53787.845 | G11: 9992563.1 | H11: 63769688 | I11: 29847410 | J11: 3.8170645e+08 | K11: 37463381 | L11: 1.9070259e+08 | M11: 38437345 | N11: 4052221.1 | O11: 2002102.3 | P11: 500502.69 | Q11: 436143.33 | R11: 30503274 | S11: 57639372 | T11: 24705458 | U11: 1.6085577e+09 | V11: 1.5754694e+08 | W11: 59262257 | X11: 1.0304464e+08 | Y11: 47865176 | Z11: 1.4188555e+08 | AA11: 61786815 | AB11: 4.7232363e+08 | AC11: 27171754 | AD11: 1.1412144e+08 | AE11: 12871511 | AF11: 60800315 | AG11: 4.2094259e+08 | AH11: 77857800 | AI11: 3533566.7 | AJ11: 17701652 | AK11: 75608919 | AL11: 21128489 | AM11: 62398819 | AN11: 42669369 | AO11: 33434819 | AP11: 1.3383148e+08 | AQ11: 27440115 | AR11: 1.3406578e+08 | AS11: 5980123.6 | AT11: 75785791 | AU11: 83831080 | AV11: 64869638 | AW11: 34440285 | AX11: 11440235 | AY11: 86453284 | AZ11: 10158491 | BA11: 30190294 | BB11: 9281085.1 | BC11: 2.1481673e+08 | BD11: 40970773 | BE11: 1.773365e+08 | BF11: 50310272 | BG11: 2.1325605e+08 | BH11: 3.5180599e+08 | BI11: 51797522 | BJ11: 9234151.8 | BK11: 1.8560529e+10 | BL11: 1.0670646e+08 | BN11: 2.8053611e+08 | BO11: 76502467 | BP11: 1.0417844e+08 | BQ11: 17238877 | BR11: 59788886 | BS11: 1.4991754e+08 | BT11: 1.0037653e+08 | BU11: 67427680 | BV11: 67729565 | BW11: 17156043 | BX11: 6547900.5 | BY11: 78765835 | BZ11: 5.5888071e+08 | CA11: 3.0711319e+08 | CB11: 95095474 | CC11: 77050477 | CD11: 3.073224e+08 | CF11: 1.3389139e+10 | CH11: 97896335 | CI11: 71954937 | CW11: 29149269 | CX11: 2.8062932e+09 | CY11: 3.4121717e+09 | CZ11: 8.5991377e+09 | DA11: 1.7794371e+09 | DB11: 2.0930176e+09 | DC11: 4.7332005e+10 | DE11: 1.871351e+11 | DG11: 13122292 | DH11: 61539.992 | DI11: =SUM(B11:DH11) -> 2.9417517e+11
A12: 311 - Food Manufacturing | B12: 261125.35 | C12: 1.5603034e+09 | D12: 3.078126 | E12: 21033.827 | F12: 389916.21 | G12: 119725.92 | H12: 23998.258 | I12: 13024.694 | J12: 50556.012 | K12: 697161.86 | L12: 1.1766211e+10 | M12: 8.4238998e+08 | N12: 89305.701 | O12: 2026333.6 | P12: 30741.136 | Q12: 7640039.1 | R12: 2424727.8 | S12: 3226552.7 | T12: 21571574 | U12: 23485603 | V12: 3.0511913e+08 | W12: 22416838 | X12: 74467046 | Y12: 158164.64 | Z12: 297371.31 | AA12: 56761.082 | AB12: 571922.95 | AC12: 121209.56 | AD12: 486963.71 | AE12: 60319.889 | AF12: 741535.29 | AG12: 1.847361e+08 | AH12: 6572.5314 | AI12: 661.82997 | AJ12: 1202.2315 | AK12: 40193708 | AL12: 2570.7569 | AM12: 24968.246 | AN12: 7988.486 | AO12: 6225.3367 | AP12: 9451330.9 | AQ12: 10339915 | AR12: 61846.272 | AS12: 14689082 | AT12: 1117987.4 | AU12: 11549.662 | AV12: 303.90063 | AW12: 138633.72 | AX12: 3738.0179 | AY12: 18266.36 | AZ12: 1000014 | BA12: 3553453.8 | BB12: 2878.8835 | BC12: 19062.015 | BD12: 17824.509 | BE12: 33378995 | BF12: 6908.0105 | BG12: 18734.424 | BH12: 6837.7024 | BI12: 3970.5513 | BJ12: 2044.3619 | BK12: 639829.23 | BL12: 9439.9074 | BM12: 2062.6876 | BN12: 5.6238442e+08 | BO12: 3360964.6 | BP12: 383973.85 | BQ12: 110729.71 | BR12: 3.5086222e+08 | BS12: 1327300.6 | BT12: 2.9072484e+08 | BU12: 3.192618e+08 | BV12: 1.1578441e+09 | BW12: 34257767 | BX12: 918841.8 | BY12: 1.8447241e+08 | BZ12: 2.5340203e+08 | CA12: 5.3427589e+09 | CB12: 113599.02 | CC12: 540345.75 | CD12: 1.1304843e+08 | CF12: 617433.86 | CH12: 456834.59 | CI12: 319246.14 | CN12: 1.7431516e+09 | CO12: 1.6629454e+09 | CP12: 1.3266106e+09 | CQ12: 1.6019981e+09 | CR12: 3.7836708e+09 | CS12: 4.7554149e+09 | CT12: 7.3564301e+09 | CU12: 5.1625572e+09 | CV12: 1.0198615e+10 | CW12: 1731317.4 | CX12: 5.6434554e+08 | CY12: 24701.293 | CZ12: 2.0991004e+09 | DA12: 1.0798174e+09 | DB12: 2.289563e+09 | DC12: 16569.025 | DE12: 450088.17 | DF12: 3.791559e+08 | DG12: 4.8270723e+09 | DH12: 4.1592266e+10 | DI12: =SUM(B12:DH12) -> 1.1397705e+11
A13: 312 - Beverage and Tobacco Product Manufacturing | B13: 427.63126 | C13: 37303338 | D13: 0.0010056252 | E13: 48.138239 | F13: 890.86992 | G13: 185.79834 | H13: 73.263958 | I13: 28.185254 | J13: 82.558412 | K13: 5567.1486 | L13: 1.7391258e+08 | M13: 7.8744555e+08 | N13: 256.88718 | O13: 4611.292 | P13: 13.894698 | Q13: 17406.084 | R13: 6718.2907 | S13: 51467.653 | T13: 59464.51 | U13: 52257.859 | V13: 703284 | W13: 54133.923 | X13: 172934.01 | Y13: 1097.3046 | Z13: 2541.8013 | AA13: 1991.6936 | AB13: 5318.2369 | AC13: 2766.8788 | AD13: 9239.6591 | AE13: 1846.7768 | AF13: 6855.8526 | AG13: 1738701 | AH13: 134.41735 | AI13: 23.096142 | AJ13: 34.801608 | AK13: 92928.779 | AL13: 232.19184 | AM13: 99.577592 | AN13: 321.29574 | AO13: 197.82463 | AP13: 21913.9 | AQ13: 24962216 | AR13: 156.53364 | AS13: 2046705 | AT13: 1086692.2 | AU13: 2762.2464 | AV13: 55.444381 | AW13: 51750.58 | AX13: 262.64467 | AY13: 366.59228 | AZ13: 2876.6763 | BA13: 8304.5233 | BB13: 14.336872 | BC13: 493.48821 | BD13: 243.78202 | BE13: 76759.816 | BF13: 377.94542 | BG13: 718.54537 | BH13: 432.56499 | BI13: 470.03548 | BJ13: 2.9695605 | BK13: 2808.407 | BL13: 331.17919 | BM13: 2569.4487 | BN13: 33418516 | BO13: 1662802.5 | BP13: 5827.3802 | BQ13: 640.918 | BR13: 44410282 | BS13: 6244.628 | BT13: 18851893 | BU13: 8764808.8 | BV13: 15014071 | BW13: 4334010.7 | BX13: 3556207.5 | BY13: 1.8241943e+08 | BZ13: 70927637 | CA13: 1.7332193e+09 | CB13: 618.92084 | CC13: 1388.2525 | CD13: 32247507 | CF13: 75486.495 | CH13: 2067.7036 | CI13: 1704.5255 | CN13: 6.0141295e+08 | CO13: 6.1702848e+08 | CP13: 5.2355485e+08 | CQ13: 5.4052395e+08 | CR13: 1.2737345e+09 | CS13: 1.5116312e+09 | CT13: 2.5930332e+09 | CU13: 1.854697e+09 | CV13: 3.2541527e+09 | CW13: 5206.9466 | CX13: 18151049 | CZ13: 4.4626585e+08 | DA13: 45412274 | DB13: 80965532 | DE13: 408.36103 | DF13: 2.0360364e+08 | DG13: 1.0234949e+09 | DH13: 1.4240998e+10 | DI13: =SUM(B13:DH13) -> 3.2007511e+10
A14: 313 - Textile Mills | B14: 113709.52 | C14: 51915.483 | E14: 52.420503 | F14: 837.7968 | G14: 48280.857 | H14: 9633.6933 | I14: 5282.9214 | J14: 18299.806 | K14: 3237764.1 | L14: 169741.38 | M14: 26401.431 | N14: 55964913 | O14: 32952931 | P14: 85821438 | Q14: 603580.37 | R14: 2794553.4 | S14: 13937351 | T14: 2341861.5 | U14: 846512.39 | V14: 1815072.2 | W14: 5130477.9 | X14: 1366891.4 | Y14: 17858.594 | Z14: 141740.31 | AA14: 5684240.3 | AB14: 303752.52 | AC14: 52611.638 | AD14: 3670469.4 | AE14: 33887970 | AF14: 61809016 | AG14: 10174735 | AH14: 73597.044 | AI14: 391866.9 | AJ14: 679.91642 | AK14: 17385.561 | AL14: 4378.6305 | AM14: 1113.7717 | AN14: 4549001.4 | AO14: 3861033.2 | AP14: 339400.79 | AQ14: 264.49188 | AR14: 1713.9742 | AS14: 13893.835 | AT14: 11074.771 | AU14: 1212.2872 | AV14: 567.45915 | AW14: 3628.7398 | AX14: 2047.6535 | AY14: 5974.9848 | AZ14: 10502.851 | BA14: 6374390.7 | BB14: 4201.9633 | BC14: 15321.077 | BD14: 7086.03 | BE14: 40459.973 | BF14: 427.66919 | BG14: 1733.9523 | BH14: 624.8073 | BI14: 1365.4594 | BJ14: 2.370965 | BK14: 297680.11 | BL14: 361624.8 | BM14: 1835.7235 | BN14: 6306257.6 | BO14: 180414.88 | BP14: 255239.79 | BQ14: 73991.137 | BR14: 500421.19 | BS14: 856988.94 | BT14: 680999.51 | BU14: 255511.47 | BV14: 5159554.7 | BW14: 1947.273 | BX14: 2232.971 | BY14: 1463441 | BZ14: 210290.05 | CA14: 767160.1 | CB14: 1671350.4 | CC14: 530012.87 | CD14: 36574.383 | CF14: 83735.569 | CH14: 218275.77 | CI14: 157394.71 | CN14: 684207.23 | CO14: 968165.58 | CP14: 699827.07 | CQ14: 866457.13 | CR14: 2207640.1 | CS14: 2833121.6 | CT14: 5224471.9 | CU14: 3727129.4 | CV14: 14592938 | CW14: 183886.32 | CX14: 2584710.3 | CY14: 2353.0681 | CZ14: 1568405.3 | DA14: 144205.08 | DB14: 1543314.1 | DC14: 1657.7778 | DE14: 2017479.8 | DF14: 718786.98 | DG14: 1.6914437e+08 | DH14: 1.1013333e+09 | DI14: =SUM(B14:DH14) -> 1.6698542e+09
A15: 314 - Textile Product Mills | B15: 518399.24 | C15: 151013.48 | D15: 0.039734832 | E15: 3936.1435 | F15: 9330.0193 | G15: 19788.921 | H15: 29404.243 | I15: 13812.983 | J15: 15658.506 | K15: 38395545 | L15: 6341085.8 | M15: 1365980.4 | N15: 175996.84 | O15: 3371106.4 | P15: 2383937.1 | Q15: 12522.48 | R15: 1724741.5 | S15: 220092.35 | T15: 516005.57 | U15: 174549.74 | V15: 1490033.5 | W15: 3061536.6 | X15: 1043172.2 | Y15: 45620.072 | Z15: 498256.97 | AA15: 804199.29 | AB15: 2777360.1 | AC15: 390181.9 | AD15: 57306670 | AE15: 3048982.7 | AF15: 1415818.7 | AG15: 38717712 | AH15: 533580.81 | AI15: 41193.446 | AJ15: 64248.448 | AK15: 1498907.2 | AL15: 360179.92 | AM15: 115878.39 | AN15: 4939289.3 | AO15: 281112.57 | AP15: 26333286 | AQ15: 46700.873 | AR15: 4125.0994 | AS15: 1093973 | AT15: 825304.62 | AU15: 94263.857 | AV15: 41856.685 | AW15: 278566.48 | AX15: 204741.75 | AY15: 182655.24 | AZ15: 249624.82 | BA15: 217659.45 | BB15: 596946.79 | BC15: 464163.54 | BD15: 259154.6 | BE15: 2394330.1 | BF15: 69318.309 | BG15: 294228.52 | BH15: 69466.491 | BI15: 405846.13 | BJ15: 514.83467 | BK15: 3547079 | BL15: 2191919 | BM15: 393747.44 | BN15: 8024947.3 | BO15: 280385.54 | BP15: 2703005.5 | BQ15: 2358438.6 | BR15: 623362.06 | BS15: 1817170.9 | BT15: 3689789.1 | BU15: 18660515 | BV15: 29941490 | BW15: 110224.24 | BX15: 94238.669 | BY15: 5968217.4 | BZ15: 16413887 | CA15: 5196593.2 | CB15: 1637565.6 | CC15: 7115264.2 | CD15: 2352267.6 | CF15: 1816829 | CH15: 2408279.4 | CI15: 2051757.9 | CN15: 5688941.6 | CO15: 7629128.2 | CP15: 9100283.3 | CQ15: 7475904.4 | CR15: 17619212 | CS15: 26740451 | CT15: 51549922 | CU15: 47000650 | CV15: 1.2822067e+08 | CW15: 1546491.9 | CX15: 36024602 | CY15: 302476.57 | CZ15: 17959239 | DA15: 2635604.9 | DB15: 32914158 | DC15: 192175.43 | DE15: 1.2652693e+08 | DF15: 1491015.4 | DG15: 1.2854149e+08 | DH15: 9.708709e+08 | DI15: =SUM(B15:DH15) -> 1.9474308e+09
